Workbook

Sheet Document Control
A2: Copyright © 2025 Foodics. All rights reserved.
A3: Anti Financial Crime - Risk Register | D3: Date: | E3: 45685
D4: Version: | E4: 1
D5: Classification: | E5: Internal
D6: Status | E6: Final
A7: Document Information
A9: Document Title | B9: Foodics - Anti Financial Crime - Risk Register | C9: No. of Sheets | D9: 4
A12: Document Developer
A14: Name | B14: Sohaib Aijaz
A17: Title | B17: Risk Specialist | C17: Department | D17: Risk Management Department
A20: Document Approval
A22: Foodics <<Insert Designation>> | C22: Date
A25: Foodics <<Insert Designation>> | C25: Date
A28: Document Version History
A29: Modification History | C29: Author | D29: Date | E29: Version
A30: Initial draft | C30: Risk Management Department | D30: 45685 | E30: 0.1
A32: Document Monitoring History
A34: Review Frequency | B34: Annually | C34: Responsibility | D34: <<Insert department>>
A37: Version | B37: Last Reviewed | C37: Next Review | D37: Reviewer | E37: Sign Off

Sheet Introductions
A2: Copyright © 2025 Foodics. All rights reserved.
A3: Anti Financial Crime - Risk Register
A4: Objective | B4: The objective of this document is to collate information on Foodics availability risks that could affect the continuous operation of critical systems and services.
A5: Instructions | B5: Please keep a note of the below instructions while filling the sheet:
B6: Sheet 1: This contains version control information.
B7: Current Sheet (Sheet 2): This contains general information about the document.
B8: Sheet 3: Availability Risk Register (instructions are provided in column).
B9: Sheet 4: Risk Matrix.
O19: Recruitment will be conducted based on approved and available positions to meet operational requirements | P19: Fill approved vacant positions based on business requirements | Q19: Q4 timeline
K21: Deployed automated transaction monitoring systems with predefined rules and generate alerts for anomalies. 1-Review and update monitoring rules and thresholds based on risk assessment (BRA/CRA) 2-Ensure full integration between core system and monitoring system (e.g., FOCAL) 3-Implement periodic tuning and validation of alerts to reduce false positives 4-Establish escalation and review procedures for alerts (including Compliance approval) 4-Conduct regular testing and quality assurance (sampling every 6 months)
K22: Conduct risk assessments on customers and flag PEPs as high-risk with enhanced monitoring. 1-Implemented automated PEP screening integrated with onboarding and monitoring systems 2-Ensure all identified PEPs are classified as high-risk and subject to EDD 3-Enforce mandatory senior management (CEO) approval before onboarding PEPs 4-Apply enhanced ongoing monitoring for PEP accounts and transactions 5-Conduct periodic reviews and updates of PEP status and related risk profiles
K23: BRA has been developed and finalized
K151: Assign Compliance responsibility to alert Marketing of any regulatory or policy changes requiring updates.
K153: Skills development occurs organically through on-the-job learning, peer collaboration, and ad-hoc exposure to new tools and industry practices. - Could include access to certified training and programs for the team (through HR) - Implement a routine team knowledge sharing hub about new marketing trends, channels and tools, industry case studies.. etc. This will ensure continuous development beyond daily operational tasks and support long-term capability maturity.
E173: Risk that business, operational, regulatory or customer requirements are incomplete, inaccurate, ambiguous or incorrectly translated into technical specifications during product development or enhancement. Inadequate stakeholder consultation, poorly documented requirements or uncontrolled changes may result in incorrect functionality, processing errors, missed regulatory requirements, production defects, rework, financial loss and customer impact.
K186: 1.⁠ ⁠Terminal-level transaction visibility. Every transaction records the terminal that originated it, so a device that has stopped processing is identifiable from platform data without relying on the merchant to report it. 2.⁠ ⁠Daily terminal-level reconciliation. Transactions are reconciled per terminal per day against payment service provider reports, so a terminal that is not reporting or is reporting incompletely is detectable through the reconciliation cycle. 3.⁠ ⁠Central terminal registry with lifecycle management. Terminals are registered against a merchant and branch with their status maintained centrally, so a failed device can be deactivated and a replacement registered against the same merchant and branch. 4.⁠ ⁠Independent approval and audit trail on terminal record changes, so device deactivations and replacements are authorised by a second person and fully traceable. 5.⁠ ⁠Per-terminal integration logging. Failures originating at a device are logged with the exact message exchange, allowing a connectivity failure to be distinguished from an application or platform failure during investigation.

Sheet Availability Risk Register
A2: Copyright © 2025 Foodics. All rights reserved.
A3: Enterprise - Risk Register
A4: Availability Risks
A5: Risk ID | B5: Risk Category | C5: Risk Name | D5: Owner | E5: Risk Description | F5: Likelihood | G5: Risk Impact | H5: Score | J5: Inherent Risk | K5: Existing Controls | L5: Control Effectiveness | M5: Residual risk | N5: ACTION OWNER | O5: Recommended Treatment | P5: Action Plan | Q5: Target completion date | R5: Control Effectiveness | S5: Risk after treatment | U5: Status | V5: Department Responses
A7: Serial number | C7: Define the risk | D7: Foodics Department responsible for managing the risk | E7: A detailed explanation of the risk with the potential impact | F7: The possibility that the risk could occur | G7: The impact on the department if that risk occurs | H7: L and I | J7: The likelihood and impact of a risk occurrence | K7: a | L7: Strength of the existing controls | M7: Residual risk after existing control | O7: The additional controls that are required to effectively mitigate risk | P7: clear list of steps that explain how you will apply the recommended treatment to reduce the risk. | Q7: Tentative date to complete the recommended treatment | R7: Control strength based on the existing controls and the additional identified controls | S7: Net risk that remain after considering control effectiveness and risk severity | T7: Your Task
A8: AFC-001 | B8: People | C8: Incorrect /fake documentation | D8: Anti Money Laundering | E8: Risk of an individual at the time of onboarding might provide incorrect personal information with malicious intentions, lead to fraudulent transactions. | F8: Likely | G8: Major | H8: =IF(F8='Risk Methedology Matrix'!B$26,5,IF(F8='Risk Methedology Matrix'!B$27,4,IF(F8='Risk Methedology Matrix'!B$28,3,IF(F8='Risk Methedology Matrix'!B$29,2,IF(F8='Risk Methedology Matrix'!B$30,1,0))))) -> 4 | I8: =IF(G8='Risk Methedology Matrix'!G$25,5,IF(G8='Risk Methedology Matrix'!F$25,4,IF(G8='Risk Methedology Matrix'!E$25,3,IF(G8='Risk Methedology Matrix'!D$25,2,IF(G8='Risk Methedology Matrix'!C$25,1,0))))) -> 4 | J8: =IF(OR(F8="",G8=""),"",IF(H8*I8>=20,"Very High",IF(AND(H8*I8<20,H8*I8>=11),"High",IF(AND(H8*I8<11,H8*I8>=6),"Medium",IF(AND(H8*I8<6,H8*I8>=3),"Low",IF(AND(H8*I8<3,H8*I8>=1),"Very Low","")))))) -> High | K8: Personal information including CR number, phone number and National ID are validated via third party servies like wathiq, yakeen and absher 2) Enhance data validation by ensuring customer information is verified through available third-party services during onboarding with clear checks before account activation 3-Define key fields to be verified (e.g., CR number, National ID, mobile number) 4-Perform validation through available third-party services (e.g., Wathiq, Yakeen, Absher) during onboarding 5-Ensure validation is completed before activating the customer account 6-Follow up on any incomplete or failed validation before proceeding. Keep basic records of validation results for reference | L8: Good | M8: =IF(OR(J8="",L8=""),"", IF(AND(J8="Very High",L8="Excellent"),"Low", IF(AND(J8="Very High",L8="Good"),"Medium", IF(AND(J8="Very High",L8="Fair"),"High", IF(AND(J8="Very High",L8="Poor"),"Very High", IF(AND(J8="Very High",L8="Unsatisfactory"),"Very High", IF(AND(J8="High",L8="Excellent"),"Very Low", IF(AND(J8="High",L8="Good"),"Low", IF(AND(J8="High",L8="Fair"),"Medium", IF(AND(J8="High",L8="Poor"),"High", IF(AND(J8="High",L8="Unsatisfactory"),"High", IF(AND(J8="Medium",L8="Excellent"),"Very Low", IF(AND(J8="Medium",L8="Good"),"Very Low", IF(AND(J8="Medium",L8="Fair"),"Low", IF(AND(J8="Medium",L8="Poor"),"Medium", IF(AND(J8="Medium",L8="Unsatisfactory"),"Medium", IF(AND(J8="Low",L8="Excellent"),"Very Low", IF(AND(J8="Low",L8="Good"),"Very Low", IF(AND(J8="Low",L8="Fair"),"Very Low", IF(AND(J8="Low",L8="Poor"),"Low", IF(AND(J8="Low",L8="Unsatisfactory"),"Low", IF(AND(J8="Very Low",L8="Excellent"),"Very Low", IF(AND(J8="Very Low",L8="Good"),"Very Low", IF(AND(J8="Very Low",L8="Fair"),"Very Low", IF(AND(J8="Very Low",L8="Poor"),"Very Low", IF(AND(J8="Very Low",L8="Unsatisfactory"),"Very Low","")))))))))))))))))))))))))) -> Low | S8: =IF(OR(L8="",R8=""),"",IF(AND(L8="Very High",R8="Excellent"),"Low",IF(AND(L8="Very High",R8="Good"),"Medium",IF(AND(L8="Very High",R8="Fair"),"High",IF(AND(L8="Very High",R8="Poor"),"Very High",IF(AND(L8="Very High",R8="Unsatisfactory"),"Very High",IF(AND(L8="High",R8="Excellent"),"Low",IF(AND(L8="High",R8="Good"),"Low",IF(AND(L8="High",R8="Fair"),"Medium",IF(AND(L8="High",R8="Poor"),"High",IF(AND(L8="High",R8="Unsatisfactory"),"High",IF(AND(L8="Medium",R8="Excellent"),"Low",IF(AND(L8="Medium",R8="Good"),"Low",IF(AND(L8="Medium",R8="Fair"),"Low",IF(AND(L8="Medium",R8="Poor"),"Medium",IF(AND(L8="Medium",R8="Unsatisfactory"),"Medium",IF(AND(L8="Low",R8="Excellent"),"Very Low",IF(AND(L8="Low",R8="Good"),"Low",IF(AND(L8="Low",R8="Fair"),"Low",IF(AND(L8="Low",R8="Poor"),"Low",IF(AND(L8="Low",R8="Unsatisfactory"),"Low",IF(AND(L8="Very Low",R8="Excellent"),"Very Low",IF(AND(L8="Very Low",R8="Good"),"Very Low",IF(AND(L8="Very Low",R8="Fair"),"Very Low",IF(AND(L8="Very Low",R8="Poor"),"Very Low",IF(AND(L8="Very Low",R8="Unsatisfactory"),"Very Low","Low")))))))))))))))))))))))))) | T8: (check Operation team
A9: AFC-002 | B9: Process | C9: Sanction Screening | D9: Anti Money Laundering | E9: Inadequate sanctions screening for clients and transactions | F9: Likely | G9: Minor | H9: =IF(F9='Risk Methedology Matrix'!B$26,5,IF(F9='Risk Methedology Matrix'!B$27,4,IF(F9='Risk Methedology Matrix'!B$28,3,IF(F9='Risk Methedology Matrix'!B$29,2,IF(F9='Risk Methedology Matrix'!B$30,1,0))))) -> 4 | I9: =IF(G9='Risk Methedology Matrix'!G$25,5,IF(G9='Risk Methedology Matrix'!F$25,4,IF(G9='Risk Methedology Matrix'!E$25,3,IF(G9='Risk Methedology Matrix'!D$25,2,IF(G9='Risk Methedology Matrix'!C$25,1,0))))) -> 2 | J9: =IF(OR(F9="",G9=""),"",IF(H9*I9>=20,"Very High",IF(AND(H9*I9<20,H9*I9>=11),"High",IF(AND(H9*I9<11,H9*I9>=6),"Medium",IF(AND(H9*I9<6,H9*I9>=3),"Low",IF(AND(H9*I9<3,H9*I9>=1),"Very Low","")))))) -> Medium | K9: Customer names are screened through FOCAL against the applicable sanctions lists during the onboarding process Screening records and results are retained as supporting evidence In addition, customer names are periodically re-screened to identify any subsequent sanctions matches or changes in their sanctions status. | L9: Fair | M9: =IF(OR(J9="",L9=""),"", IF(AND(J9="Very High",L9="Excellent"),"Low", IF(AND(J9="Very High",L9="Good"),"Medium", IF(AND(J9="Very High",L9="Fair"),"High", IF(AND(J9="Very High",L9="Poor"),"Very High", IF(AND(J9="Very High",L9="Unsatisfactory"),"Very High", IF(AND(J9="High",L9="Excellent"),"Very Low", IF(AND(J9="High",L9="Good"),"Low", IF(AND(J9="High",L9="Fair"),"Medium", IF(AND(J9="High",L9="Poor"),"High", IF(AND(J9="High",L9="Unsatisfactory"),"High", IF(AND(J9="Medium",L9="Excellent"),"Very Low", IF(AND(J9="Medium",L9="Good"),"Very Low", IF(AND(J9="Medium",L9="Fair"),"Low", IF(AND(J9="Medium",L9="Poor"),"Medium", IF(AND(J9="Medium",L9="Unsatisfactory"),"Medium", IF(AND(J9="Low",L9="Excellent"),"Very Low", IF(AND(J9="Low",L9="Good"),"Very Low", IF(AND(J9="Low",L9="Fair"),"Very Low", IF(AND(J9="Low",L9="Poor"),"Low", IF(AND(J9="Low",L9="Unsatisfactory"),"Low", IF(AND(J9="Very Low",L9="Excellent"),"Very Low", IF(AND(J9="Very Low",L9="Good"),"Very Low", IF(AND(J9="Very Low",L9="Fair"),"Very Low", IF(AND(J9="Very Low",L9="Poor"),"Very Low", IF(AND(J9="Very Low",L9="Unsatisfactory"),"Very Low","")))))))))))))))))))))))))) -> Low | S9: =IF(OR(L9="",R9=""),"",IF(AND(L9="Very High",R9="Excellent"),"Low",IF(AND(L9="Very High",R9="Good"),"Medium",IF(AND(L9="Very High",R9="Fair"),"High",IF(AND(L9="Very High",R9="Poor"),"Very High",IF(AND(L9="Very High",R9="Unsatisfactory"),"Very High",IF(AND(L9="High",R9="Excellent"),"Low",IF(AND(L9="High",R9="Good"),"Low",IF(AND(L9="High",R9="Fair"),"Medium",IF(AND(L9="High",R9="Poor"),"High",IF(AND(L9="High",R9="Unsatisfactory"),"High",IF(AND(L9="Medium",R9="Excellent"),"Low",IF(AND(L9="Medium",R9="Good"),"Low",IF(AND(L9="Medium",R9="Fair"),"Low",IF(AND(L9="Medium",R9="Poor"),"Medium",IF(AND(L9="Medium",R9="Unsatisfactory"),"Medium",IF(AND(L9="Low",R9="Excellent"),"Very Low",IF(AND(L9="Low",R9="Good"),"Low",IF(AND(L9="Low",R9="Fair"),"Low",IF(AND(L9="Low",R9="Poor"),"Low",IF(AND(L9="Low",R9="Unsatisfactory"),"Low",IF(AND(L9="Very Low",R9="Excellent"),"Very Low",IF(AND(L9="Very Low",R9="Good"),"Very Low",IF(AND(L9="Very Low",R9="Fair"),"Very Low",IF(AND(L9="Very Low",R9="Poor"),"Very Low",IF(AND(L9="Very Low",R9="Unsatisfactory"),"Very Low","Low")))))))))))))))))))))))))) | T9: - (Action plan to reduce the alerts on focal + time line + controls) Chatgpt
A10: AFC-003 | B10: Process | C10: Negligence of Customer complaints | D10: Anti Money Laundering | E10: Failure to respond to customer complaints about suspicious activity , leads to financial loss, | F10: Likely | G10: Critical | H10: =IF(F10='Risk Methedology Matrix'!B$26,5,IF(F10='Risk Methedology Matrix'!B$27,4,IF(F10='Risk Methedology Matrix'!B$28,3,IF(F10='Risk Methedology Matrix'!B$29,2,IF(F10='Risk Methedology Matrix'!B$30,1,0))))) -> 4 | I10: =IF(G10='Risk Methedology Matrix'!G$25,5,IF(G10='Risk Methedology Matrix'!F$25,4,IF(G10='Risk Methedology Matrix'!E$25,3,IF(G10='Risk Methedology Matrix'!D$25,2,IF(G10='Risk Methedology Matrix'!C$25,1,0))))) -> 5 | J10: =IF(OR(F10="",G10=""),"",IF(H10*I10>=20,"Very High",IF(AND(H10*I10<20,H10*I10>=11),"High",IF(AND(H10*I10<11,H10*I10>=6),"Medium",IF(AND(H10*I10<6,H10*I10>=3),"Low",IF(AND(H10*I10<3,H10*I10>=1),"Very Low","")))))) -> Very High | K10: AML teams notify PayOps, for any merchant with suspicious activities, and hold their settlements, where our role is to ask the merchant for the needed documents and invoices to help the compliance teams investigate further how legitimate the transaction is. Specially if its with a high amount. 1-Define criteria to identify complaints that may indicate suspicious activity 2-Require escalation of such complaints to the Compliance team 3-Perform manual review of related transactions through existing AML systems (e.g., FOCAL) 4-Document all escalations and investigation outcomes 5-Provide basic awareness to relevant teams on identifying suspicious complaints | L10: Good | M10: =IF(OR(J10="",L10=""),"", IF(AND(J10="Very High",L10="Excellent"),"Low", IF(AND(J10="Very High",L10="Good"),"Medium", IF(AND(J10="Very High",L10="Fair"),"High", IF(AND(J10="Very High",L10="Poor"),"Very High", IF(AND(J10="Very High",L10="Unsatisfactory"),"Very High", IF(AND(J10="High",L10="Excellent"),"Very Low", IF(AND(J10="High",L10="Good"),"Low", IF(AND(J10="High",L10="Fair"),"Medium", IF(AND(J10="High",L10="Poor"),"High", IF(AND(J10="High",L10="Unsatisfactory"),"High", IF(AND(J10="Medium",L10="Excellent"),"Very Low", IF(AND(J10="Medium",L10="Good"),"Very Low", IF(AND(J10="Medium",L10="Fair"),"Low", IF(AND(J10="Medium",L10="Poor"),"Medium", IF(AND(J10="Medium",L10="Unsatisfactory"),"Medium", IF(AND(J10="Low",L10="Excellent"),"Very Low", IF(AND(J10="Low",L10="Good"),"Very Low", IF(AND(J10="Low",L10="Fair"),"Very Low", IF(AND(J10="Low",L10="Poor"),"Low", IF(AND(J10="Low",L10="Unsatisfactory"),"Low", IF(AND(J10="Very Low",L10="Excellent"),"Very Low", IF(AND(J10="Very Low",L10="Good"),"Very Low", IF(AND(J10="Very Low",L10="Fair"),"Very Low", IF(AND(J10="Very Low",L10="Poor"),"Very Low", IF(AND(J10="Very Low",L10="Unsatisfactory"),"Very Low","")))))))))))))))))))))))))) -> Medium | S10: =IF(OR(L10="",R10=""),"",IF(AND(L10="Very High",R10="Excellent"),"Low",IF(AND(L10="Very High",R10="Good"),"Medium",IF(AND(L10="Very High",R10="Fair"),"High",IF(AND(L10="Very High",R10="Poor"),"Very High",IF(AND(L10="Very High",R10="Unsatisfactory"),"Very High",IF(AND(L10="High",R10="Excellent"),"Low",IF(AND(L10="High",R10="Good"),"Low",IF(AND(L10="High",R10="Fair"),"Medium",IF(AND(L10="High",R10="Poor"),"High",IF(AND(L10="High",R10="Unsatisfactory"),"High",IF(AND(L10="Medium",R10="Excellent"),"Low",IF(AND(L10="Medium",R10="Good"),"Low",IF(AND(L10="Medium",R10="Fair"),"Low",IF(AND(L10="Medium",R10="Poor"),"Medium",IF(AND(L10="Medium",R10="Unsatisfactory"),"Medium",IF(AND(L10="Low",R10="Excellent"),"Very Low",IF(AND(L10="Low",R10="Good"),"Low",IF(AND(L10="Low",R10="Fair"),"Low",IF(AND(L10="Low",R10="Poor"),"Low",IF(AND(L10="Low",R10="Unsatisfactory"),"Low",IF(AND(L10="Very Low",R10="Excellent"),"Very Low",IF(AND(L10="Very Low",R10="Good"),"Very Low",IF(AND(L10="Very Low",R10="Fair"),"Very Low",IF(AND(L10="Very Low",R10="Poor"),"Very Low",IF(AND(L10="Very Low",R10="Unsatisfactory"),"Very Low","Low")))))))))))))))))))))))))) | T10: (check Call center for the procedures the relates to fruad)
A11: AFC-004 | B11: People | C11: Not reporting suspicious transactions | D11: Anti Money Laundering | E11: Failure to inform the competent authorities in case of suspicion of valid reasons for fraudulent behavior by customers, lead to financial loss, reputational impact and legal prosecution. | F11: Likely | G11: Moderate | H11: =IF(F11='Risk Methedology Matrix'!B$26,5,IF(F11='Risk Methedology Matrix'!B$27,4,IF(F11='Risk Methedology Matrix'!B$28,3,IF(F11='Risk Methedology Matrix'!B$29,2,IF(F11='Risk Methedology Matrix'!B$30,1,0))))) -> 4 | I11: =IF(G11='Risk Methedology Matrix'!G$25,5,IF(G11='Risk Methedology Matrix'!F$25,4,IF(G11='Risk Methedology Matrix'!E$25,3,IF(G11='Risk Methedology Matrix'!D$25,2,IF(G11='Risk Methedology Matrix'!C$25,1,0))))) -> 3 | J11: =IF(OR(F11="",G11=""),"",IF(H11*I11>=20,"Very High",IF(AND(H11*I11<20,H11*I11>=11),"High",IF(AND(H11*I11<11,H11*I11>=6),"Medium",IF(AND(H11*I11<6,H11*I11>=3),"Low",IF(AND(H11*I11<3,H11*I11>=1),"Very Low","")))))) -> High | K11: In the event of encountering suspected cases of money laundering transactions on these accounts, staff of the Anti-Financial Crime Unit will examine the case and report to the head of the Anti-Financial Crime Unit who will decide to report the case to the Financial Investigations Unit (FIU) of the Ministry of Interior. Conducting Transaction Monitoring to detect unusual and suspicious activity. In case there are reasonable grounds to suspect that another person or entity engaging in Financial Crime: Escalating to the Financial Crime Unit by submitting unusual activity reports. Any employee should be able to escalate this report to the Financial Crime Unit in order that the unit can examine and take appropriate measures. Filing a Suspicious Activity Report (SAR) to the authorities (SAFIU) within 10 working days of validation. 1-Detect suspicious transactions through automated transaction monitoring systems. 2-Ensure all alerts are reviewed and investigated by the Compliance team. 3-Establish clear escalation procedures for potential suspicious cases 4-Define decision-making authority for filing Suspicious Activity Reports (SARs) 5-Ensure timely submission of SARs to SAFIU within regulatory timelines 6-Maintain proper documentation and audit trails for all investigations and reporting decisions | L11: Fair | M11: =IF(OR(J11="",L11=""),"", IF(AND(J11="Very High",L11="Excellent"),"Low", IF(AND(J11="Very High",L11="Good"),"Medium", IF(AND(J11="Very High",L11="Fair"),"High", IF(AND(J11="Very High",L11="Poor"),"Very High", IF(AND(J11="Very High",L11="Unsatisfactory"),"Very High", IF(AND(J11="High",L11="Excellent"),"Very Low", IF(AND(J11="High",L11="Good"),"Low", IF(AND(J11="High",L11="Fair"),"Medium", IF(AND(J11="High",L11="Poor"),"High", IF(AND(J11="High",L11="Unsatisfactory"),"High", IF(AND(J11="Medium",L11="Excellent"),"Very Low", IF(AND(J11="Medium",L11="Good"),"Very Low", IF(AND(J11="Medium",L11="Fair"),"Low", IF(AND(J11="Medium",L11="Poor"),"Medium", IF(AND(J11="Medium",L11="Unsatisfactory"),"Medium", IF(AND(J11="Low",L11="Excellent"),"Very Low", IF(AND(J11="Low",L11="Good"),"Very Low", IF(AND(J11="Low",L11="Fair"),"Very Low", IF(AND(J11="Low",L11="Poor"),"Low", IF(AND(J11="Low",L11="Unsatisfactory"),"Low", IF(AND(J11="Very Low",L11="Excellent"),"Very Low", IF(AND(J11="Very Low",L11="Good"),"Very Low", IF(AND(J11="Very Low",L11="Fair"),"Very Low", IF(AND(J11="Very Low",L11="Poor"),"Very Low", IF(AND(J11="Very Low",L11="Unsatisfactory"),"Very Low","")))))))))))))))))))))))))) -> Medium | S11: =IF(OR(L11="",R11=""),"",IF(AND(L11="Very High",R11="Excellent"),"Low",IF(AND(L11="Very High",R11="Good"),"Medium",IF(AND(L11="Very High",R11="Fair"),"High",IF(AND(L11="Very High",R11="Poor"),"Very High",IF(AND(L11="Very High",R11="Unsatisfactory"),"Very High",IF(AND(L11="High",R11="Excellent"),"Low",IF(AND(L11="High",R11="Good"),"Low",IF(AND(L11="High",R11="Fair"),"Medium",IF(AND(L11="High",R11="Poor"),"High",IF(AND(L11="High",R11="Unsatisfactory"),"High",IF(AND(L11="Medium",R11="Excellent"),"Low",IF(AND(L11="Medium",R11="Good"),"Low",IF(AND(L11="Medium",R11="Fair"),"Low",IF(AND(L11="Medium",R11="Poor"),"Medium",IF(AND(L11="Medium",R11="Unsatisfactory"),"Medium",IF(AND(L11="Low",R11="Excellent"),"Very Low",IF(AND(L11="Low",R11="Good"),"Low",IF(AND(L11="Low",R11="Fair"),"Low",IF(AND(L11="Low",R11="Poor"),"Low",IF(AND(L11="Low",R11="Unsatisfactory"),"Low",IF(AND(L11="Very Low",R11="Excellent"),"Very Low",IF(AND(L11="Very Low",R11="Good"),"Very Low",IF(AND(L11="Very Low",R11="Fair"),"Very Low",IF(AND(L11="Very Low",R11="Poor"),"Very Low",IF(AND(L11="Very Low",R11="Unsatisfactory"),"Very Low","Low")))))))))))))))))))))))))) | T11: Reportt every suspocous transaction to SAFIU within 10 days
A12: AFC-005 | B12: People | C12: Dealing with Prohibited clients | D12: Anti Money Laundering | E12: Risk of dealing with a customer that are registered in the sanction lists, lead to financial loss, reputational impact and legal prosecution. | F12: Almost certain | G12: Major | H12: =IF(F12='Risk Methedology Matrix'!B$26,5,IF(F12='Risk Methedology Matrix'!B$27,4,IF(F12='Risk Methedology Matrix'!B$28,3,IF(F12='Risk Methedology Matrix'!B$29,2,IF(F12='Risk Methedology Matrix'!B$30,1,0))))) -> 5 | I12: =IF(G12='Risk Methedology Matrix'!G$25,5,IF(G12='Risk Methedology Matrix'!F$25,4,IF(G12='Risk Methedology Matrix'!E$25,3,IF(G12='Risk Methedology Matrix'!D$25,2,IF(G12='Risk Methedology Matrix'!C$25,1,0))))) -> 4 | J12: =IF(OR(F12="",G12=""),"",IF(H12*I12>=20,"Very High",IF(AND(H12*I12<20,H12*I12>=11),"High",IF(AND(H12*I12<11,H12*I12>=6),"Medium",IF(AND(H12*I12<6,H12*I12>=3),"Low",IF(AND(H12*I12<3,H12*I12>=1),"Very Low","")))))) -> Very High | K12: FOCAL is used as a preventive control to verify customer names against the relevant sanctions lists before establishing a business relationship Evidence of the verification is documented and retained The customer portfolio is also subject to periodic screening to detect newly listed or prohibited customers and prevent further dealings with them. | L12: Good | M12: =IF(OR(J12="",L12=""),"", IF(AND(J12="Very High",L12="Excellent"),"Low", IF(AND(J12="Very High",L12="Good"),"Medium", IF(AND(J12="Very High",L12="Fair"),"High", IF(AND(J12="Very High",L12="Poor"),"Very High", IF(AND(J12="Very High",L12="Unsatisfactory"),"Very High", IF(AND(J12="High",L12="Excellent"),"Very Low", IF(AND(J12="High",L12="Good"),"Low", IF(AND(J12="High",L12="Fair"),"Medium", IF(AND(J12="High",L12="Poor"),"High", IF(AND(J12="High",L12="Unsatisfactory"),"High", IF(AND(J12="Medium",L12="Excellent"),"Very Low", IF(AND(J12="Medium",L12="Good"),"Very Low", IF(AND(J12="Medium",L12="Fair"),"Low", IF(AND(J12="Medium",L12="Poor"),"Medium", IF(AND(J12="Medium",L12="Unsatisfactory"),"Medium", IF(AND(J12="Low",L12="Excellent"),"Very Low", IF(AND(J12="Low",L12="Good"),"Very Low", IF(AND(J12="Low",L12="Fair"),"Very Low", IF(AND(J12="Low",L12="Poor"),"Low", IF(AND(J12="Low",L12="Unsatisfactory"),"Low", IF(AND(J12="Very Low",L12="Excellent"),"Very Low", IF(AND(J12="Very Low",L12="Good"),"Very Low", IF(AND(J12="Very Low",L12="Fair"),"Very Low", IF(AND(J12="Very Low",L12="Poor"),"Very Low", IF(AND(J12="Very Low",L12="Unsatisfactory"),"Very Low","")))))))))))))))))))))))))) -> Medium | S12: =IF(OR(L12="",R12=""),"",IF(AND(L12="Very High",R12="Excellent"),"Low",IF(AND(L12="Very High",R12="Good"),"Medium",IF(AND(L12="Very High",R12="Fair"),"High",IF(AND(L12="Very High",R12="Poor"),"Very High",IF(AND(L12="Very High",R12="Unsatisfactory"),"Very High",IF(AND(L12="High",R12="Excellent"),"Low",IF(AND(L12="High",R12="Good"),"Low",IF(AND(L12="High",R12="Fair"),"Medium",IF(AND(L12="High",R12="Poor"),"High",IF(AND(L12="High",R12="Unsatisfactory"),"High",IF(AND(L12="Medium",R12="Excellent"),"Low",IF(AND(L12="Medium",R12="Good"),"Low",IF(AND(L12="Medium",R12="Fair"),"Low",IF(AND(L12="Medium",R12="Poor"),"Medium",IF(AND(L12="Medium",R12="Unsatisfactory"),"Medium",IF(AND(L12="Low",R12="Excellent"),"Very Low",IF(AND(L12="Low",R12="Good"),"Low",IF(AND(L12="Low",R12="Fair"),"Low",IF(AND(L12="Low",R12="Poor"),"Low",IF(AND(L12="Low",R12="Unsatisfactory"),"Low",IF(AND(L12="Very Low",R12="Excellent"),"Very Low",IF(AND(L12="Very Low",R12="Good"),"Very Low",IF(AND(L12="Very Low",R12="Fair"),"Very Low",IF(AND(L12="Very Low",R12="Poor"),"Very Low",IF(AND(L12="Very Low",R12="Unsatisfactory"),"Very Low","Low")))))))))))))))))))))))))) | T12: (Check with Operation about procedures to deal with Prohibited clients)
A13: AFC-006 | B13: People | C13: POS terminal | D13: Anti Money Laundering | E13: Risk of an individual performing suspicious transactions on their POS terminal, to lead to fraudulent transaction legal prosecution. | F13: Possible | G13: Critical | H13: =IF(F13='Risk Methedology Matrix'!B$26,5,IF(F13='Risk Methedology Matrix'!B$27,4,IF(F13='Risk Methedology Matrix'!B$28,3,IF(F13='Risk Methedology Matrix'!B$29,2,IF(F13='Risk Methedology Matrix'!B$30,1,0))))) -> 3 | I13: =IF(G13='Risk Methedology Matrix'!G$25,5,IF(G13='Risk Methedology Matrix'!F$25,4,IF(G13='Risk Methedology Matrix'!E$25,3,IF(G13='Risk Methedology Matrix'!D$25,2,IF(G13='Risk Methedology Matrix'!C$25,1,0))))) -> 5 | J13: =IF(OR(F13="",G13=""),"",IF(H13*I13>=20,"Very High",IF(AND(H13*I13<20,H13*I13>=11),"High",IF(AND(H13*I13<11,H13*I13>=6),"Medium",IF(AND(H13*I13<6,H13*I13>=3),"Low",IF(AND(H13*I13<3,H13*I13>=1),"Very Low","")))))) -> High | K13: We have different rules against which we monitor customer transctions via Focal APIs and raise a flag immediately if that happens 1-Establish a formal SOP for investigating, documenting, and escalating POS-related alerts 2-Develop and implement risk-based AML monitoring scenarios and alert thresholds tailored to merchant profiles, transaction behavior, and risk levels 3-Ensure all alerts are reviewed, investigated, and documented with clear audit trails 4-Enforce escalation procedures for suspicious activities, including submission to Compliance for further review and action 5-Integrate POS monitoring with the central transaction monitoring system to ensure consistency and full visibility 6-Conduct targeted training for relevant staff on AML monitoring scenarios and red flags related to POS transactions. 7-Perform periodic tuning and effectiveness testing of monitoring scenarios to enhance detection accuracy and reduce false positives | L13: Fair | M13: =IF(OR(J13="",L13=""),"", IF(AND(J13="Very High",L13="Excellent"),"Low", IF(AND(J13="Very High",L13="Good"),"Medium", IF(AND(J13="Very High",L13="Fair"),"High", IF(AND(J13="Very High",L13="Poor"),"Very High", IF(AND(J13="Very High",L13="Unsatisfactory"),"Very High", IF(AND(J13="High",L13="Excellent"),"Very Low", IF(AND(J13="High",L13="Good"),"Low", IF(AND(J13="High",L13="Fair"),"Medium", IF(AND(J13="High",L13="Poor"),"High", IF(AND(J13="High",L13="Unsatisfactory"),"High", IF(AND(J13="Medium",L13="Excellent"),"Very Low", IF(AND(J13="Medium",L13="Good"),"Very Low", IF(AND(J13="Medium",L13="Fair"),"Low", IF(AND(J13="Medium",L13="Poor"),"Medium", IF(AND(J13="Medium",L13="Unsatisfactory"),"Medium", IF(AND(J13="Low",L13="Excellent"),"Very Low", IF(AND(J13="Low",L13="Good"),"Very Low", IF(AND(J13="Low",L13="Fair"),"Very Low", IF(AND(J13="Low",L13="Poor"),"Low", IF(AND(J13="Low",L13="Unsatisfactory"),"Low", IF(AND(J13="Very Low",L13="Excellent"),"Very Low", IF(AND(J13="Very Low",L13="Good"),"Very Low", IF(AND(J13="Very Low",L13="Fair"),"Very Low", IF(AND(J13="Very Low",L13="Poor"),"Very Low", IF(AND(J13="Very Low",L13="Unsatisfactory"),"Very Low","")))))))))))))))))))))))))) -> Medium | S13: =IF(OR(L13="",R13=""),"",IF(AND(L13="Very High",R13="Excellent"),"Low",IF(AND(L13="Very High",R13="Good"),"Medium",IF(AND(L13="Very High",R13="Fair"),"High",IF(AND(L13="Very High",R13="Poor"),"Very High",IF(AND(L13="Very High",R13="Unsatisfactory"),"Very High",IF(AND(L13="High",R13="Excellent"),"Low",IF(AND(L13="High",R13="Good"),"Low",IF(AND(L13="High",R13="Fair"),"Medium",IF(AND(L13="High",R13="Poor"),"High",IF(AND(L13="High",R13="Unsatisfactory"),"High",IF(AND(L13="Medium",R13="Excellent"),"Low",IF(AND(L13="Medium",R13="Good"),"Low",IF(AND(L13="Medium",R13="Fair"),"Low",IF(AND(L13="Medium",R13="Poor"),"Medium",IF(AND(L13="Medium",R13="Unsatisfactory"),"Medium",IF(AND(L13="Low",R13="Excellent"),"Very Low",IF(AND(L13="Low",R13="Good"),"Low",IF(AND(L13="Low",R13="Fair"),"Low",IF(AND(L13="Low",R13="Poor"),"Low",IF(AND(L13="Low",R13="Unsatisfactory"),"Low",IF(AND(L13="Very Low",R13="Excellent"),"Very Low",IF(AND(L13="Very Low",R13="Good"),"Very Low",IF(AND(L13="Very Low",R13="Fair"),"Very Low",IF(AND(L13="Very Low",R13="Poor"),"Very Low",IF(AND(L13="Very Low",R13="Unsatisfactory"),"Very Low","Low")))))))))))))))))))))))))) | T13: (Action plan to reduce the alerts on focal + time line + controls)
A14: AFC-007 | B14: System | C14: Lack of E-KYC | D14: Anti Money Laundering | E14: Risk of E-KYC, lead to operation insufficiency and fraudulent transaction | F14: Possible | G14: Moderate | H14: =IF(F14='Risk Methedology Matrix'!B$26,5,IF(F14='Risk Methedology Matrix'!B$27,4,IF(F14='Risk Methedology Matrix'!B$28,3,IF(F14='Risk Methedology Matrix'!B$29,2,IF(F14='Risk Methedology Matrix'!B$30,1,0))))) -> 3 | I14: =IF(G14='Risk Methedology Matrix'!G$25,5,IF(G14='Risk Methedology Matrix'!F$25,4,IF(G14='Risk Methedology Matrix'!E$25,3,IF(G14='Risk Methedology Matrix'!D$25,2,IF(G14='Risk Methedology Matrix'!C$25,1,0))))) -> 3 | J14: High | K14: 1- E-KYC implementation during the onboarding process using Elm and Wathiq Services 2- Customer information update incase of E-KYC is due for renewal | L14: Poor | M14: =IF(OR(J14="",L14=""),"", IF(AND(J14="Very High",L14="Excellent"),"Low", IF(AND(J14="Very High",L14="Good"),"Medium", IF(AND(J14="Very High",L14="Fair"),"High", IF(AND(J14="Very High",L14="Poor"),"Very High", IF(AND(J14="Very High",L14="Unsatisfactory"),"Very High", IF(AND(J14="High",L14="Excellent"),"Very Low", IF(AND(J14="High",L14="Good"),"Low", IF(AND(J14="High",L14="Fair"),"Medium", IF(AND(J14="High",L14="Poor"),"High", IF(AND(J14="High",L14="Unsatisfactory"),"High", IF(AND(J14="Medium",L14="Excellent"),"Very Low", IF(AND(J14="Medium",L14="Good"),"Very Low", IF(AND(J14="Medium",L14="Fair"),"Low", IF(AND(J14="Medium",L14="Poor"),"Medium", IF(AND(J14="Medium",L14="Unsatisfactory"),"Medium", IF(AND(J14="Low",L14="Excellent"),"Very Low", IF(AND(J14="Low",L14="Good"),"Very Low", IF(AND(J14="Low",L14="Fair"),"Very Low", IF(AND(J14="Low",L14="Poor"),"Low", IF(AND(J14="Low",L14="Unsatisfactory"),"Low", IF(AND(J14="Very Low",L14="Excellent"),"Very Low", IF(AND(J14="Very Low",L14="Good"),"Very Low", IF(AND(J14="Very Low",L14="Fair"),"Very Low", IF(AND(J14="Very Low",L14="Poor"),"Very Low", IF(AND(J14="Very Low",L14="Unsatisfactory"),"Very Low","")))))))))))))))))))))))))) -> High | O14: Strengthen E-KYC controls by ensuring mandatory non-bypassable identity verification during onboarding using approved third-party sources with defined renewal and data update mechanisms | P14: 1-Implement mandatory E-KYC verification for all customers during onboarding using approved platforms (e.g., Elm, Wathiq) 2-Ensure E-KYC is a non-bypassable step prior to account activation 3-Define E-KYC validity periods and implement automated renewal processes 4-Ensure timely update of customer information upon E-KYC expiry or trigger events 5-Monitor E-KYC completion rates and address any system or integration gaps | Q14: Q4 timeline | S14: =IF(OR(L14="",R14=""),"",IF(AND(L14="Very High",R14="Excellent"),"Low",IF(AND(L14="Very High",R14="Good"),"Medium",IF(AND(L14="Very High",R14="Fair"),"High",IF(AND(L14="Very High",R14="Poor"),"Very High",IF(AND(L14="Very High",R14="Unsatisfactory"),"Very High",IF(AND(L14="High",R14="Excellent"),"Low",IF(AND(L14="High",R14="Good"),"Low",IF(AND(L14="High",R14="Fair"),"Medium",IF(AND(L14="High",R14="Poor"),"High",IF(AND(L14="High",R14="Unsatisfactory"),"High",IF(AND(L14="Medium",R14="Excellent"),"Low",IF(AND(L14="Medium",R14="Good"),"Low",IF(AND(L14="Medium",R14="Fair"),"Low",IF(AND(L14="Medium",R14="Poor"),"Medium",IF(AND(L14="Medium",R14="Unsatisfactory"),"Medium",IF(AND(L14="Low",R14="Excellent"),"Very Low",IF(AND(L14="Low",R14="Good"),"Low",IF(AND(L14="Low",R14="Fair"),"Low",IF(AND(L14="Low",R14="Poor"),"Low",IF(AND(L14="Low",R14="Unsatisfactory"),"Low",IF(AND(L14="Very Low",R14="Excellent"),"Very Low",IF(AND(L14="Very Low",R14="Good"),"Very Low",IF(AND(L14="Very Low",R14="Fair"),"Very Low",IF(AND(L14="Very Low",R14="Poor"),"Very Low",IF(AND(L14="Very Low",R14="Unsatisfactory"),"Very Low","Low")))))))))))))))))))))))))) | T14: (Ask operation team for the effectiveness of controls) (effectiveness of the control is the evidence
A15: AFC-008 | B15: Process | C15: Due Deligence | D15: Anti Money Laundering | E15: Ineffective customer due diligence (CDD) and enhanced due diligence (EDD) processes. | F15: Unlikely | G15: Moderate | H15: =IF(F15='Risk Methedology Matrix'!B$26,5,IF(F15='Risk Methedology Matrix'!B$27,4,IF(F15='Risk Methedology Matrix'!B$28,3,IF(F15='Risk Methedology Matrix'!B$29,2,IF(F15='Risk Methedology Matrix'!B$30,1,0))))) -> 2 | I15: =IF(G15='Risk Methedology Matrix'!G$25,5,IF(G15='Risk Methedology Matrix'!F$25,4,IF(G15='Risk Methedology Matrix'!E$25,3,IF(G15='Risk Methedology Matrix'!D$25,2,IF(G15='Risk Methedology Matrix'!C$25,1,0))))) -> 3 | J15: High | K15: Establish and enforce CDD/EDD procedures, including risk scoring and PEP checks during onboarding and periodic reviews. 1-Enhance existing CDD and EDD procedures to ensure consistent application across all customers 2-Strengthen customer risk scoring methodology to support accurate risk classification 3-Ensure effective identification and handling of PEP customers during onboarding and periodic reviews 4-Standardize documentation and verification requirements for CDD/EDD processes 5-Ensure periodic review of customer information based on defined review cycles | L15: Good | M15: =IF(OR(J15="",L15=""),"", IF(AND(J15="Very High",L15="Excellent"),"Low", IF(AND(J15="Very High",L15="Good"),"Medium", IF(AND(J15="Very High",L15="Fair"),"High", IF(AND(J15="Very High",L15="Poor"),"Very High", IF(AND(J15="Very High",L15="Unsatisfactory"),"Very High", IF(AND(J15="High",L15="Excellent"),"Very Low", IF(AND(J15="High",L15="Good"),"Low", IF(AND(J15="High",L15="Fair"),"Medium", IF(AND(J15="High",L15="Poor"),"High", IF(AND(J15="High",L15="Unsatisfactory"),"High", IF(AND(J15="Medium",L15="Excellent"),"Very Low", IF(AND(J15="Medium",L15="Good"),"Very Low", IF(AND(J15="Medium",L15="Fair"),"Low", IF(AND(J15="Medium",L15="Poor"),"Medium", IF(AND(J15="Medium",L15="Unsatisfactory"),"Medium", IF(AND(J15="Low",L15="Excellent"),"Very Low", IF(AND(J15="Low",L15="Good"),"Very Low", IF(AND(J15="Low",L15="Fair"),"Very Low", IF(AND(J15="Low",L15="Poor"),"Low", IF(AND(J15="Low",L15="Unsatisfactory"),"Low", IF(AND(J15="Very Low",L15="Excellent"),"Very Low", IF(AND(J15="Very Low",L15="Good"),"Very Low", IF(AND(J15="Very Low",L15="Fair"),"Very Low", IF(AND(J15="Very Low",L15="Poor"),"Very Low", IF(AND(J15="Very Low",L15="Unsatisfactory"),"Very Low","")))))))))))))))))))))))))) -> Low | S15: =IF(OR(L15="",R15=""),"",IF(AND(L15="Very High",R15="Excellent"),"Low",IF(AND(L15="Very High",R15="Good"),"Medium",IF(AND(L15="Very High",R15="Fair"),"High",IF(AND(L15="Very High",R15="Poor"),"Very High",IF(AND(L15="Very High",R15="Unsatisfactory"),"Very High",IF(AND(L15="High",R15="Excellent"),"Low",IF(AND(L15="High",R15="Good"),"Low",IF(AND(L15="High",R15="Fair"),"Medium",IF(AND(L15="High",R15="Poor"),"High",IF(AND(L15="High",R15="Unsatisfactory"),"High",IF(AND(L15="Medium",R15="Excellent"),"Low",IF(AND(L15="Medium",R15="Good"),"Low",IF(AND(L15="Medium",R15="Fair"),"Low",IF(AND(L15="Medium",R15="Poor"),"Medium",IF(AND(L15="Medium",R15="Unsatisfactory"),"Medium",IF(AND(L15="Low",R15="Excellent"),"Very Low",IF(AND(L15="Low",R15="Good"),"Low",IF(AND(L15="Low",R15="Fair"),"Low",IF(AND(L15="Low",R15="Poor"),"Low",IF(AND(L15="Low",R15="Unsatisfactory"),"Low",IF(AND(L15="Very Low",R15="Excellent"),"Very Low",IF(AND(L15="Very Low",R15="Good"),"Very Low",IF(AND(L15="Very Low",R15="Fair"),"Very Low",IF(AND(L15="Very Low",R15="Poor"),"Very Low",IF(AND(L15="Very Low",R15="Unsatisfactory"),"Very Low","Low")))))))))))))))))))))))))) | T15: (Ask operation team for the effectiveness of controls) (effectiveness of the control is the evidence
A16: AFC-009 | B16: Process | C16: Risk of Onboarding | D16: Anti Money Laundering | E16: Risk of Onboarding fictitious or anonymous customers | F16: Likely | G16: Critical | H16: =IF(F16='Risk Methedology Matrix'!B$26,5,IF(F16='Risk Methedology Matrix'!B$27,4,IF(F16='Risk Methedology Matrix'!B$28,3,IF(F16='Risk Methedology Matrix'!B$29,2,IF(F16='Risk Methedology Matrix'!B$30,1,0))))) -> 4 | I16: =IF(G16='Risk Methedology Matrix'!G$25,5,IF(G16='Risk Methedology Matrix'!F$25,4,IF(G16='Risk Methedology Matrix'!E$25,3,IF(G16='Risk Methedology Matrix'!D$25,2,IF(G16='Risk Methedology Matrix'!C$25,1,0))))) -> 5 | J16: =IF(OR(F16="",G16=""),"",IF(H16*I16>=20,"Very High",IF(AND(H16*I16<20,H16*I16>=11),"High",IF(AND(H16*I16<11,H16*I16>=6),"Medium",IF(AND(H16*I16<6,H16*I16>=3),"Low",IF(AND(H16*I16<3,H16*I16>=1),"Very Low","")))))) -> Very High | K16: Prohibit anonymous or numerically coded accounts and verify customer identities through official documentation. '1-Developed and implemented mandatory CDD/EDD procedures for all customers. 2-Implement risk-based customer classification using automated scoring models 3-Integrate sanctions and PEP screening within onboarding using a reliable vendor 4-Enforce Compliance review and approval for high-risk and EDD cases 5-Implement system controls to block onboarding until all checks and approvals are completed 6-Ensure all customer data is obtained and verified through reliable independent sources | L16: Good | M16: =IF(OR(J16="",L16=""),"", IF(AND(J16="Very High",L16="Excellent"),"Low", IF(AND(J16="Very High",L16="Good"),"Medium", IF(AND(J16="Very High",L16="Fair"),"High", IF(AND(J16="Very High",L16="Poor"),"Very High", IF(AND(J16="Very High",L16="Unsatisfactory"),"Very High", IF(AND(J16="High",L16="Excellent"),"Very Low", IF(AND(J16="High",L16="Good"),"Low", IF(AND(J16="High",L16="Fair"),"Medium", IF(AND(J16="High",L16="Poor"),"High", IF(AND(J16="High",L16="Unsatisfactory"),"High", IF(AND(J16="Medium",L16="Excellent"),"Very Low", IF(AND(J16="Medium",L16="Good"),"Very Low", IF(AND(J16="Medium",L16="Fair"),"Low", IF(AND(J16="Medium",L16="Poor"),"Medium", IF(AND(J16="Medium",L16="Unsatisfactory"),"Medium", IF(AND(J16="Low",L16="Excellent"),"Very Low", IF(AND(J16="Low",L16="Good"),"Very Low", IF(AND(J16="Low",L16="Fair"),"Very Low", IF(AND(J16="Low",L16="Poor"),"Low", IF(AND(J16="Low",L16="Unsatisfactory"),"Low", IF(AND(J16="Very Low",L16="Excellent"),"Very Low", IF(AND(J16="Very Low",L16="Good"),"Very Low", IF(AND(J16="Very Low",L16="Fair"),"Very Low", IF(AND(J16="Very Low",L16="Poor"),"Very Low", IF(AND(J16="Very Low",L16="Unsatisfactory"),"Very Low","")))))))))))))))))))))))))) -> Medium | S16: =IF(OR(L16="",R16=""),"",IF(AND(L16="Very High",R16="Excellent"),"Low",IF(AND(L16="Very High",R16="Good"),"Medium",IF(AND(L16="Very High",R16="Fair"),"High",IF(AND(L16="Very High",R16="Poor"),"Very High",IF(AND(L16="Very High",R16="Unsatisfactory"),"Very High",IF(AND(L16="High",R16="Excellent"),"Low",IF(AND(L16="High",R16="Good"),"Low",IF(AND(L16="High",R16="Fair"),"Medium",IF(AND(L16="High",R16="Poor"),"High",IF(AND(L16="High",R16="Unsatisfactory"),"High",IF(AND(L16="Medium",R16="Excellent"),"Low",IF(AND(L16="Medium",R16="Good"),"Low",IF(AND(L16="Medium",R16="Fair"),"Low",IF(AND(L16="Medium",R16="Poor"),"Medium",IF(AND(L16="Medium",R16="Unsatisfactory"),"Medium",IF(AND(L16="Low",R16="Excellent"),"Very Low",IF(AND(L16="Low",R16="Good"),"Low",IF(AND(L16="Low",R16="Fair"),"Low",IF(AND(L16="Low",R16="Poor"),"Low",IF(AND(L16="Low",R16="Unsatisfactory"),"Low",IF(AND(L16="Very Low",R16="Excellent"),"Very Low",IF(AND(L16="Very Low",R16="Good"),"Very Low",IF(AND(L16="Very Low",R16="Fair"),"Very Low",IF(AND(L16="Very Low",R16="Poor"),"Very Low",IF(AND(L16="Very Low",R16="Unsatisfactory"),"Very Low","Low")))))))))))))))))))))))))) | T16: (Ask operation team for the effectiveness of controls) (effectiveness of the control is the evidence
A17: AFC-010 | B17: Process | C17: Policies and Procedures | D17: Anti Money Laundering | E17: Risk of the absence of a reviewed, updated, and comprehensive Policies and Procedures Manual covering all departmental functions, potentially resulting in operational inefficiencies, role ambiguity, and misalignment of responsibilities | F17: Unlikely | G17: Moderate | H17: =IF(F17='Risk Methedology Matrix'!B$26,5,IF(F17='Risk Methedology Matrix'!B$27,4,IF(F17='Risk Methedology Matrix'!B$28,3,IF(F17='Risk Methedology Matrix'!B$29,2,IF(F17='Risk Methedology Matrix'!B$30,1,0))))) -> 2 | I17: =IF(G17='Risk Methedology Matrix'!G$25,5,IF(G17='Risk Methedology Matrix'!F$25,4,IF(G17='Risk Methedology Matrix'!E$25,3,IF(G17='Risk Methedology Matrix'!D$25,2,IF(G17='Risk Methedology Matrix'!C$25,1,0))))) -> 3 | J17: =IF(OR(F17="",G17=""),"",IF(H17*I17>=20,"Very High",IF(AND(H17*I17<20,H17*I17>=11),"High",IF(AND(H17*I17<11,H17*I17>=6),"Medium",IF(AND(H17*I17<6,H17*I17>=3),"Low",IF(AND(H17*I17<3,H17*I17>=1),"Very Low","")))))) -> Medium | K17: Perform annual reviews of the AML framework, involving independent audits to assess effectiveness. | L17: Fair | M17: =IF(OR(J17="",L17=""),"", IF(AND(J17="Very High",L17="Excellent"),"Low", IF(AND(J17="Very High",L17="Good"),"Medium", IF(AND(J17="Very High",L17="Fair"),"High", IF(AND(J17="Very High",L17="Poor"),"Very High", IF(AND(J17="Very High",L17="Unsatisfactory"),"Very High", IF(AND(J17="High",L17="Excellent"),"Very Low", IF(AND(J17="High",L17="Good"),"Low", IF(AND(J17="High",L17="Fair"),"Medium", IF(AND(J17="High",L17="Poor"),"High", IF(AND(J17="High",L17="Unsatisfactory"),"High", IF(AND(J17="Medium",L17="Excellent"),"Very Low", IF(AND(J17="Medium",L17="Good"),"Very Low", IF(AND(J17="Medium",L17="Fair"),"Low", IF(AND(J17="Medium",L17="Poor"),"Medium", IF(AND(J17="Medium",L17="Unsatisfactory"),"Medium", IF(AND(J17="Low",L17="Excellent"),"Very Low", IF(AND(J17="Low",L17="Good"),"Very Low", IF(AND(J17="Low",L17="Fair"),"Very Low", IF(AND(J17="Low",L17="Poor"),"Low", IF(AND(J17="Low",L17="Unsatisfactory"),"Low", IF(AND(J17="Very Low",L17="Excellent"),"Very Low", IF(AND(J17="Very Low",L17="Good"),"Very Low", IF(AND(J17="Very Low",L17="Fair"),"Very Low", IF(AND(J17="Very Low",L17="Poor"),"Very Low", IF(AND(J17="Very Low",L17="Unsatisfactory"),"Very Low","")))))))))))))))))))))))))) -> Low | S17: =IF(OR(L17="",R17=""),"",IF(AND(L17="Very High",R17="Excellent"),"Low",IF(AND(L17="Very High",R17="Good"),"Medium",IF(AND(L17="Very High",R17="Fair"),"High",IF(AND(L17="Very High",R17="Poor"),"Very High",IF(AND(L17="Very High",R17="Unsatisfactory"),"Very High",IF(AND(L17="High",R17="Excellent"),"Low",IF(AND(L17="High",R17="Good"),"Low",IF(AND(L17="High",R17="Fair"),"Medium",IF(AND(L17="High",R17="Poor"),"High",IF(AND(L17="High",R17="Unsatisfactory"),"High",IF(AND(L17="Medium",R17="Excellent"),"Low",IF(AND(L17="Medium",R17="Good"),"Low",IF(AND(L17="Medium",R17="Fair"),"Low",IF(AND(L17="Medium",R17="Poor"),"Medium",IF(AND(L17="Medium",R17="Unsatisfactory"),"Medium",IF(AND(L17="Low",R17="Excellent"),"Very Low",IF(AND(L17="Low",R17="Good"),"Low",IF(AND(L17="Low",R17="Fair"),"Low",IF(AND(L17="Low",R17="Poor"),"Low",IF(AND(L17="Low",R17="Unsatisfactory"),"Low",IF(AND(L17="Very Low",R17="Excellent"),"Very Low",IF(AND(L17="Very Low",R17="Good"),"Very Low",IF(AND(L17="Very Low",R17="Fair"),"Very Low",IF(AND(L17="Very Low",R17="Poor"),"Very Low",IF(AND(L17="Very Low",R17="Unsatisfactory"),"Very Low","Low")))))))))))))))))))))))))) | T17: Update the Policies for AML And fraud within 4 months
A18: AFC-011 | B18: Process | C18: Annual Strategy | D18: Anti Money Laundering | E18: Failure to develop a comprehensive strategy and roadmap for the department. | F18: Likely | G18: Minor | H18: =IF(F18='Risk Methedology Matrix'!B$26,5,IF(F18='Risk Methedology Matrix'!B$27,4,IF(F18='Risk Methedology Matrix'!B$28,3,IF(F18='Risk Methedology Matrix'!B$29,2,IF(F18='Risk Methedology Matrix'!B$30,1,0))))) -> 4 | I18: =IF(G18='Risk Methedology Matrix'!G$25,5,IF(G18='Risk Methedology Matrix'!F$25,4,IF(G18='Risk Methedology Matrix'!E$25,3,IF(G18='Risk Methedology Matrix'!D$25,2,IF(G18='Risk Methedology Matrix'!C$25,1,0))))) -> 2 | J18: =IF(OR(F18="",G18=""),"",IF(H18*I18>=20,"Very High",IF(AND(H18*I18<20,H18*I18>=11),"High",IF(AND(H18*I18<11,H18*I18>=6),"Medium",IF(AND(H18*I18<6,H18*I18>=3),"Low",IF(AND(H18*I18<3,H18*I18>=1),"Very Low","")))))) -> Medium | K18: Established and maintain a structured annual AML and Risk strategy aligned with business objectives regulatory requirements and risk appetite with clear governance and performance tracking. 1-Developed an annual AML/Risk strategy aligned with business growth and regulatory expectations 2-Define clear objectives, initiatives, and KPIs for all AML activities 3-Obtain Senior Management and Board approval for the strategy 4-Monitor progress against KPIs on a periodic basis (e.g., monthly/quarterly). 5-Escalate any delays or deviations and implement corrective actions in a timely manner 6-Conduct periodic reviews and update the strategy as needed based on emerging risks | L18: Good | M18: =IF(OR(J18="",L18=""),"", IF(AND(J18="Very High",L18="Excellent"),"Low", IF(AND(J18="Very High",L18="Good"),"Medium", IF(AND(J18="Very High",L18="Fair"),"High", IF(AND(J18="Very High",L18="Poor"),"Very High", IF(AND(J18="Very High",L18="Unsatisfactory"),"Very High", IF(AND(J18="High",L18="Excellent"),"Very Low", IF(AND(J18="High",L18="Good"),"Low", IF(AND(J18="High",L18="Fair"),"Medium", IF(AND(J18="High",L18="Poor"),"High", IF(AND(J18="High",L18="Unsatisfactory"),"High", IF(AND(J18="Medium",L18="Excellent"),"Very Low", IF(AND(J18="Medium",L18="Good"),"Very Low", IF(AND(J18="Medium",L18="Fair"),"Low", IF(AND(J18="Medium",L18="Poor"),"Medium", IF(AND(J18="Medium",L18="Unsatisfactory"),"Medium", IF(AND(J18="Low",L18="Excellent"),"Very Low", IF(AND(J18="Low",L18="Good"),"Very Low", IF(AND(J18="Low",L18="Fair"),"Very Low", IF(AND(J18="Low",L18="Poor"),"Low", IF(AND(J18="Low",L18="Unsatisfactory"),"Low", IF(AND(J18="Very Low",L18="Excellent"),"Very Low", IF(AND(J18="Very Low",L18="Good"),"Very Low", IF(AND(J18="Very Low",L18="Fair"),"Very Low", IF(AND(J18="Very Low",L18="Poor"),"Very Low", IF(AND(J18="Very Low",L18="Unsatisfactory"),"Very Low","")))))))))))))))))))))))))) -> Very Low | S18: =IF(OR(L18="",R18=""),"",IF(AND(L18="Very High",R18="Excellent"),"Low",IF(AND(L18="Very High",R18="Good"),"Medium",IF(AND(L18="Very High",R18="Fair"),"High",IF(AND(L18="Very High",R18="Poor"),"Very High",IF(AND(L18="Very High",R18="Unsatisfactory"),"Very High",IF(AND(L18="High",R18="Excellent"),"Low",IF(AND(L18="High",R18="Good"),"Low",IF(AND(L18="High",R18="Fair"),"Medium",IF(AND(L18="High",R18="Poor"),"High",IF(AND(L18="High",R18="Unsatisfactory"),"High",IF(AND(L18="Medium",R18="Excellent"),"Low",IF(AND(L18="Medium",R18="Good"),"Low",IF(AND(L18="Medium",R18="Fair"),"Low",IF(AND(L18="Medium",R18="Poor"),"Medium",IF(AND(L18="Medium",R18="Unsatisfactory"),"Medium",IF(AND(L18="Low",R18="Excellent"),"Very Low",IF(AND(L18="Low",R18="Good"),"Low",IF(AND(L18="Low",R18="Fair"),"Low",IF(AND(L18="Low",R18="Poor"),"Low",IF(AND(L18="Low",R18="Unsatisfactory"),"Low",IF(AND(L18="Very Low",R18="Excellent"),"Very Low",IF(AND(L18="Very Low",R18="Good"),"Very Low",IF(AND(L18="Very Low",R18="Fair"),"Very Low",IF(AND(L18="Very Low",R18="Poor"),"Very Low",IF(AND(L18="Very Low",R18="Unsatisfactory"),"Very Low","Low")))))))))))))))))))))))))) | T18: (Activate compliance committee ask Khalid alzaini)
A19: AFC-012 | B19: Process | C19: Human Resourcing | D19: Anti Money Laundering | E19: Failure to accurately identify, budget, and communicate the department’s human resource requirements to the Human Resources function may result in misalignment between manpower planning and recruitment activities. This could lead to staffing shortages or surpluses, disrupting departmental operations and impacting service delivery | F19: Likely | G19: Minor | H19: =IF(F19='Risk Methedology Matrix'!B$26,5,IF(F19='Risk Methedology Matrix'!B$27,4,IF(F19='Risk Methedology Matrix'!B$28,3,IF(F19='Risk Methedology Matrix'!B$29,2,IF(F19='Risk Methedology Matrix'!B$30,1,0))))) -> 4 | I19: =IF(G19='Risk Methedology Matrix'!G$25,5,IF(G19='Risk Methedology Matrix'!F$25,4,IF(G19='Risk Methedology Matrix'!E$25,3,IF(G19='Risk Methedology Matrix'!D$25,2,IF(G19='Risk Methedology Matrix'!C$25,1,0))))) -> 2 | J19: =IF(OR(F19="",G19=""),"",IF(H19*I19>=20,"Very High",IF(AND(H19*I19<20,H19*I19>=11),"High",IF(AND(H19*I19<11,H19*I19>=6),"Medium",IF(AND(H19*I19<6,H19*I19>=3),"Low",IF(AND(H19*I19<3,H19*I19>=1),"Very Low","")))))) -> Medium | K19: Established a formal workforce planning process that involves collaboration between department heads and the HR function. | L19: Poor | M19: =IF(OR(J19="",L19=""),"", IF(AND(J19="Very High",L19="Excellent"),"Low", IF(AND(J19="Very High",L19="Good"),"Medium", IF(AND(J19="Very High",L19="Fair"),"High", IF(AND(J19="Very High",L19="Poor"),"Very High", IF(AND(J19="Very High",L19="Unsatisfactory"),"Very High", IF(AND(J19="High",L19="Excellent"),"Very Low", IF(AND(J19="High",L19="Good"),"Low", IF(AND(J19="High",L19="Fair"),"Medium", IF(AND(J19="High",L19="Poor"),"High", IF(AND(J19="High",L19="Unsatisfactory"),"High", IF(AND(J19="Medium",L19="Excellent"),"Very Low", IF(AND(J19="Medium",L19="Good"),"Very Low", IF(AND(J19="Medium",L19="Fair"),"Low", IF(AND(J19="Medium",L19="Poor"),"Medium", IF(AND(J19="Medium",L19="Unsatisfactory"),"Medium", IF(AND(J19="Low",L19="Excellent"),"Very Low", IF(AND(J19="Low",L19="Good"),"Very Low", IF(AND(J19="Low",L19="Fair"),"Very Low", IF(AND(J19="Low",L19="Poor"),"Low", IF(AND(J19="Low",L19="Unsatisfactory"),"Low", IF(AND(J19="Very Low",L19="Excellent"),"Very Low", IF(AND(J19="Very Low",L19="Good"),"Very Low", IF(AND(J19="Very Low",L19="Fair"),"Very Low", IF(AND(J19="Very Low",L19="Poor"),"Very Low", IF(AND(J19="Very Low",L19="Unsatisfactory"),"Very Low","")))))))))))))))))))))))))) -> Medium | O19: Recruitment will be conducted based on approved and available positions to meet operational requirements | P19: Fill approved vacant positions based on business requirements | Q19: Q4 timeline | S19: =IF(OR(L19="",R19=""),"",IF(AND(L19="Very High",R19="Excellent"),"Low",IF(AND(L19="Very High",R19="Good"),"Medium",IF(AND(L19="Very High",R19="Fair"),"High",IF(AND(L19="Very High",R19="Poor"),"Very High",IF(AND(L19="Very High",R19="Unsatisfactory"),"Very High",IF(AND(L19="High",R19="Excellent"),"Low",IF(AND(L19="High",R19="Good"),"Low",IF(AND(L19="High",R19="Fair"),"Medium",IF(AND(L19="High",R19="Poor"),"High",IF(AND(L19="High",R19="Unsatisfactory"),"High",IF(AND(L19="Medium",R19="Excellent"),"Low",IF(AND(L19="Medium",R19="Good"),"Low",IF(AND(L19="Medium",R19="Fair"),"Low",IF(AND(L19="Medium",R19="Poor"),"Medium",IF(AND(L19="Medium",R19="Unsatisfactory"),"Medium",IF(AND(L19="Low",R19="Excellent"),"Very Low",IF(AND(L19="Low",R19="Good"),"Low",IF(AND(L19="Low",R19="Fair"),"Low",IF(AND(L19="Low",R19="Poor"),"Low",IF(AND(L19="Low",R19="Unsatisfactory"),"Low",IF(AND(L19="Very Low",R19="Excellent"),"Very Low",IF(AND(L19="Very Low",R19="Good"),"Very Low",IF(AND(L19="Very Low",R19="Fair"),"Very Low",IF(AND(L19="Very Low",R19="Poor"),"Very Low",IF(AND(L19="Very Low",R19="Unsatisfactory"),"Very Low","Low")))))))))))))))))))))))))) | T19: (allocate Budget For AML and fraud ) -Khalid alzaini or Finance department
A20: AFC-013 | B20: Process | C20: Training & Sufficient Nnumbers | D20: Anti Money Laundering | E20: Failure to identify and effectively communicate the training needs and requirements of department employees to the Human Resources function may result in inadequate skill development, reduced employee performance, and hindered overall departmental growth and effectiveness. | F20: Possible | G20: Minor | H20: =IF(F20='Risk Methedology Matrix'!B$26,5,IF(F20='Risk Methedology Matrix'!B$27,4,IF(F20='Risk Methedology Matrix'!B$28,3,IF(F20='Risk Methedology Matrix'!B$29,2,IF(F20='Risk Methedology Matrix'!B$30,1,0))))) -> 3 | I20: =IF(G20='Risk Methedology Matrix'!G$25,5,IF(G20='Risk Methedology Matrix'!F$25,4,IF(G20='Risk Methedology Matrix'!E$25,3,IF(G20='Risk Methedology Matrix'!D$25,2,IF(G20='Risk Methedology Matrix'!C$25,1,0))))) -> 2 | J20: =IF(OR(F20="",G20=""),"",IF(H20*I20>=20,"Very High",IF(AND(H20*I20<20,H20*I20>=11),"High",IF(AND(H20*I20<11,H20*I20>=6),"Medium",IF(AND(H20*I20<6,H20*I20>=3),"Low",IF(AND(H20*I20<3,H20*I20>=1),"Very Low","")))))) -> Medium | K20: Conduct mandatory AFC awareness training for all employees, including tailored programs for high-risk roles. | L20: Good | M20: =IF(OR(J20="",L20=""),"", IF(AND(J20="Very High",L20="Excellent"),"Low", IF(AND(J20="Very High",L20="Good"),"Medium", IF(AND(J20="Very High",L20="Fair"),"High", IF(AND(J20="Very High",L20="Poor"),"Very High", IF(AND(J20="Very High",L20="Unsatisfactory"),"Very High", IF(AND(J20="High",L20="Excellent"),"Very Low", IF(AND(J20="High",L20="Good"),"Low", IF(AND(J20="High",L20="Fair"),"Medium", IF(AND(J20="High",L20="Poor"),"High", IF(AND(J20="High",L20="Unsatisfactory"),"High", IF(AND(J20="Medium",L20="Excellent"),"Very Low", IF(AND(J20="Medium",L20="Good"),"Very Low", IF(AND(J20="Medium",L20="Fair"),"Low", IF(AND(J20="Medium",L20="Poor"),"Medium", IF(AND(J20="Medium",L20="Unsatisfactory"),"Medium", IF(AND(J20="Low",L20="Excellent"),"Very Low", IF(AND(J20="Low",L20="Good"),"Very Low", IF(AND(J20="Low",L20="Fair"),"Very Low", IF(AND(J20="Low",L20="Poor"),"Low", IF(AND(J20="Low",L20="Unsatisfactory"),"Low", IF(AND(J20="Very Low",L20="Excellent"),"Very Low", IF(AND(J20="Very Low",L20="Good"),"Very Low", IF(AND(J20="Very Low",L20="Fair"),"Very Low", IF(AND(J20="Very Low",L20="Poor"),"Very Low", IF(AND(J20="Very Low",L20="Unsatisfactory"),"Very Low","")))))))))))))))))))))))))) -> Very Low | S20: =IF(OR(L20="",R20=""),"",IF(AND(L20="Very High",R20="Excellent"),"Low",IF(AND(L20="Very High",R20="Good"),"Medium",IF(AND(L20="Very High",R20="Fair"),"High",IF(AND(L20="Very High",R20="Poor"),"Very High",IF(AND(L20="Very High",R20="Unsatisfactory"),"Very High",IF(AND(L20="High",R20="Excellent"),"Low",IF(AND(L20="High",R20="Good"),"Low",IF(AND(L20="High",R20="Fair"),"Medium",IF(AND(L20="High",R20="Poor"),"High",IF(AND(L20="High",R20="Unsatisfactory"),"High",IF(AND(L20="Medium",R20="Excellent"),"Low",IF(AND(L20="Medium",R20="Good"),"Low",IF(AND(L20="Medium",R20="Fair"),"Low",IF(AND(L20="Medium",R20="Poor"),"Medium",IF(AND(L20="Medium",R20="Unsatisfactory"),"Medium",IF(AND(L20="Low",R20="Excellent"),"Very Low",IF(AND(L20="Low",R20="Good"),"Low",IF(AND(L20="Low",R20="Fair"),"Low",IF(AND(L20="Low",R20="Poor"),"Low",IF(AND(L20="Low",R20="Unsatisfactory"),"Low",IF(AND(L20="Very Low",R20="Excellent"),"Very Low",IF(AND(L20="Very Low",R20="Good"),"Very Low",IF(AND(L20="Very Low",R20="Fair"),"Very Low",IF(AND(L20="Very Low",R20="Poor"),"Very Low",IF(AND(L20="Very Low",R20="Unsatisfactory"),"Very Low","Low")))))))))))))))))))))))))) | T20: (Share AFC training with HR and conduct training and awareness sessions)
A21: AFC-014 | B21: System | C21: Transaction Monitoring | D21: Anti Money Laundering | E21: Failure to identify and analyze patterns of behavior that may indicate money laundering or other financial crime occurring, leads to operation insufficiency, financial loss, fraudulent transactions, and reputational impact. | F21: Likely | G21: Critical | H21: =IF(F21='Risk Methedology Matrix'!B$26,5,IF(F21='Risk Methedology Matrix'!B$27,4,IF(F21='Risk Methedology Matrix'!B$28,3,IF(F21='Risk Methedology Matrix'!B$29,2,IF(F21='Risk Methedology Matrix'!B$30,1,0))))) -> 4 | I21: =IF(G21='Risk Methedology Matrix'!G$25,5,IF(G21='Risk Methedology Matrix'!F$25,4,IF(G21='Risk Methedology Matrix'!E$25,3,IF(G21='Risk Methedology Matrix'!D$25,2,IF(G21='Risk Methedology Matrix'!C$25,1,0))))) -> 5 | J21: =IF(OR(F21="",G21=""),"",IF(H21*I21>=20,"Very High",IF(AND(H21*I21<20,H21*I21>=11),"High",IF(AND(H21*I21<11,H21*I21>=6),"Medium",IF(AND(H21*I21<6,H21*I21>=3),"Low",IF(AND(H21*I21<3,H21*I21>=1),"Very Low","")))))) -> Very High | K21: Deployed automated transaction monitoring systems with predefined rules and generate alerts for anomalies. 1-Review and update monitoring rules and thresholds based on risk assessment (BRA/CRA) 2-Ensure full integration between core system and monitoring system (e.g., FOCAL) 3-Implement periodic tuning and validation of alerts to reduce false positives 4-Establish escalation and review procedures for alerts (including Compliance approval) 4-Conduct regular testing and quality assurance (sampling every 6 months) | L21: Good | M21: =IF(OR(J21="",L21=""),"", IF(AND(J21="Very High",L21="Excellent"),"Low", IF(AND(J21="Very High",L21="Good"),"Medium", IF(AND(J21="Very High",L21="Fair"),"High", IF(AND(J21="Very High",L21="Poor"),"Very High", IF(AND(J21="Very High",L21="Unsatisfactory"),"Very High", IF(AND(J21="High",L21="Excellent"),"Very Low", IF(AND(J21="High",L21="Good"),"Low", IF(AND(J21="High",L21="Fair"),"Medium", IF(AND(J21="High",L21="Poor"),"High", IF(AND(J21="High",L21="Unsatisfactory"),"High", IF(AND(J21="Medium",L21="Excellent"),"Very Low", IF(AND(J21="Medium",L21="Good"),"Very Low", IF(AND(J21="Medium",L21="Fair"),"Low", IF(AND(J21="Medium",L21="Poor"),"Medium", IF(AND(J21="Medium",L21="Unsatisfactory"),"Medium", IF(AND(J21="Low",L21="Excellent"),"Very Low", IF(AND(J21="Low",L21="Good"),"Very Low", IF(AND(J21="Low",L21="Fair"),"Very Low", IF(AND(J21="Low",L21="Poor"),"Low", IF(AND(J21="Low",L21="Unsatisfactory"),"Low", IF(AND(J21="Very Low",L21="Excellent"),"Very Low", IF(AND(J21="Very Low",L21="Good"),"Very Low", IF(AND(J21="Very Low",L21="Fair"),"Very Low", IF(AND(J21="Very Low",L21="Poor"),"Very Low", IF(AND(J21="Very Low",L21="Unsatisfactory"),"Very Low","")))))))))))))))))))))))))) -> Medium | S21: =IF(OR(L21="",R21=""),"",IF(AND(L21="Very High",R21="Excellent"),"Low",IF(AND(L21="Very High",R21="Good"),"Medium",IF(AND(L21="Very High",R21="Fair"),"High",IF(AND(L21="Very High",R21="Poor"),"Very High",IF(AND(L21="Very High",R21="Unsatisfactory"),"Very High",IF(AND(L21="High",R21="Excellent"),"Low",IF(AND(L21="High",R21="Good"),"Low",IF(AND(L21="High",R21="Fair"),"Medium",IF(AND(L21="High",R21="Poor"),"High",IF(AND(L21="High",R21="Unsatisfactory"),"High",IF(AND(L21="Medium",R21="Excellent"),"Low",IF(AND(L21="Medium",R21="Good"),"Low",IF(AND(L21="Medium",R21="Fair"),"Low",IF(AND(L21="Medium",R21="Poor"),"Medium",IF(AND(L21="Medium",R21="Unsatisfactory"),"Medium",IF(AND(L21="Low",R21="Excellent"),"Very Low",IF(AND(L21="Low",R21="Good"),"Low",IF(AND(L21="Low",R21="Fair"),"Low",IF(AND(L21="Low",R21="Poor"),"Low",IF(AND(L21="Low",R21="Unsatisfactory"),"Low",IF(AND(L21="Very Low",R21="Excellent"),"Very Low",IF(AND(L21="Very Low",R21="Good"),"Very Low",IF(AND(L21="Very Low",R21="Fair"),"Very Low",IF(AND(L21="Very Low",R21="Poor"),"Very Low",IF(AND(L21="Very Low",R21="Unsatisfactory"),"Very Low","Low")))))))))))))))))))))))))) | T21: (Action plan+ time line + controls)
A22: AFC-015 | B22: Process | C22: Politically Exposed Person | D22: Anti Money Laundering | E22: Failure to detect politically exposed persons (PEPs) | F22: Almost certain | G22: Moderate | H22: =IF(F22='Risk Methedology Matrix'!B$26,5,IF(F22='Risk Methedology Matrix'!B$27,4,IF(F22='Risk Methedology Matrix'!B$28,3,IF(F22='Risk Methedology Matrix'!B$29,2,IF(F22='Risk Methedology Matrix'!B$30,1,0))))) -> 5 | I22: =IF(G22='Risk Methedology Matrix'!G$25,5,IF(G22='Risk Methedology Matrix'!F$25,4,IF(G22='Risk Methedology Matrix'!E$25,3,IF(G22='Risk Methedology Matrix'!D$25,2,IF(G22='Risk Methedology Matrix'!C$25,1,0))))) -> 3 | J22: Very High | K22: Conduct risk assessments on customers and flag PEPs as high-risk with enhanced monitoring. 1-Implemented automated PEP screening integrated with onboarding and monitoring systems 2-Ensure all identified PEPs are classified as high-risk and subject to EDD 3-Enforce mandatory senior management (CEO) approval before onboarding PEPs 4-Apply enhanced ongoing monitoring for PEP accounts and transactions 5-Conduct periodic reviews and updates of PEP status and related risk profiles | L22: Good | M22: =IF(OR(J22="",L22=""),"", IF(AND(J22="Very High",L22="Excellent"),"Low", IF(AND(J22="Very High",L22="Good"),"Medium", IF(AND(J22="Very High",L22="Fair"),"High", IF(AND(J22="Very High",L22="Poor"),"Very High", IF(AND(J22="Very High",L22="Unsatisfactory"),"Very High", IF(AND(J22="High",L22="Excellent"),"Very Low", IF(AND(J22="High",L22="Good"),"Low", IF(AND(J22="High",L22="Fair"),"Medium", IF(AND(J22="High",L22="Poor"),"High", IF(AND(J22="High",L22="Unsatisfactory"),"High", IF(AND(J22="Medium",L22="Excellent"),"Very Low", IF(AND(J22="Medium",L22="Good"),"Very Low", IF(AND(J22="Medium",L22="Fair"),"Low", IF(AND(J22="Medium",L22="Poor"),"Medium", IF(AND(J22="Medium",L22="Unsatisfactory"),"Medium", IF(AND(J22="Low",L22="Excellent"),"Very Low", IF(AND(J22="Low",L22="Good"),"Very Low", IF(AND(J22="Low",L22="Fair"),"Very Low", IF(AND(J22="Low",L22="Poor"),"Low", IF(AND(J22="Low",L22="Unsatisfactory"),"Low", IF(AND(J22="Very Low",L22="Excellent"),"Very Low", IF(AND(J22="Very Low",L22="Good"),"Very Low", IF(AND(J22="Very Low",L22="Fair"),"Very Low", IF(AND(J22="Very Low",L22="Poor"),"Very Low", IF(AND(J22="Very Low",L22="Unsatisfactory"),"Very Low","")))))))))))))))))))))))))) -> Medium | S22: =IF(OR(L22="",R22=""),"",IF(AND(L22="Very High",R22="Excellent"),"Low",IF(AND(L22="Very High",R22="Good"),"Medium",IF(AND(L22="Very High",R22="Fair"),"High",IF(AND(L22="Very High",R22="Poor"),"Very High",IF(AND(L22="Very High",R22="Unsatisfactory"),"Very High",IF(AND(L22="High",R22="Excellent"),"Low",IF(AND(L22="High",R22="Good"),"Low",IF(AND(L22="High",R22="Fair"),"Medium",IF(AND(L22="High",R22="Poor"),"High",IF(AND(L22="High",R22="Unsatisfactory"),"High",IF(AND(L22="Medium",R22="Excellent"),"Low",IF(AND(L22="Medium",R22="Good"),"Low",IF(AND(L22="Medium",R22="Fair"),"Low",IF(AND(L22="Medium",R22="Poor"),"Medium",IF(AND(L22="Medium",R22="Unsatisfactory"),"Medium",IF(AND(L22="Low",R22="Excellent"),"Very Low",IF(AND(L22="Low",R22="Good"),"Low",IF(AND(L22="Low",R22="Fair"),"Low",IF(AND(L22="Low",R22="Poor"),"Low",IF(AND(L22="Low",R22="Unsatisfactory"),"Low",IF(AND(L22="Very Low",R22="Excellent"),"Very Low",IF(AND(L22="Very Low",R22="Good"),"Very Low",IF(AND(L22="Very Low",R22="Fair"),"Very Low",IF(AND(L22="Very Low",R22="Poor"),"Very Low",IF(AND(L22="Very Low",R22="Unsatisfactory"),"Very Low","Low")))))))))))))))))))))))))) | T22: (Action plan+ time line + controls)
A23: AFC-016 | B23: Process | C23: Absence of AML Business Risk Assessment (BRA) | D23: Anti Money Laundering | E23: There is a risk that Foodics Pay may not adequately identify and manage money laundering and terrorist financing risks across its customers, products, services, delivery channels, and geographies, as a formal AML Business Risk Assessment has not yet been developed and approved, potentially impacting the effective application of a risk-based approach and regulatory compliance. | F23: Possible | G23: Major | H23: =IF(F23='Risk Methedology Matrix'!B$26,5,IF(F23='Risk Methedology Matrix'!B$27,4,IF(F23='Risk Methedology Matrix'!B$28,3,IF(F23='Risk Methedology Matrix'!B$29,2,IF(F23='Risk Methedology Matrix'!B$30,1,0))))) -> 3 | I23: =IF(G23='Risk Methedology Matrix'!G$25,5,IF(G23='Risk Methedology Matrix'!F$25,4,IF(G23='Risk Methedology Matrix'!E$25,3,IF(G23='Risk Methedology Matrix'!D$25,2,IF(G23='Risk Methedology Matrix'!C$25,1,0))))) -> 4 | J23: =IF(OR(F23="",G23=""),"",IF(H23*I23>=20,"Very High",IF(AND(H23*I23<20,H23*I23>=11),"High",IF(AND(H23*I23<11,H23*I23>=6),"Medium",IF(AND(H23*I23<6,H23*I23>=3),"Low",IF(AND(H23*I23<3,H23*I23>=1),"Very Low","")))))) -> High | K23: The assessment is substantially completed and is currently undergoing final review and minor refinements before being submitted for formal approval. | L23: Fair | M23: =IF(OR(J23="",L23=""),"", IF(AND(J23="Very High",L23="Excellent"),"Low", IF(AND(J23="Very High",L23="Good"),"Medium", IF(AND(J23="Very High",L23="Fair"),"High", IF(AND(J23="Very High",L23="Poor"),"Very High", IF(AND(J23="Very High",L23="Unsatisfactory"),"Very High", IF(AND(J23="High",L23="Excellent"),"Very Low", IF(AND(J23="High",L23="Good"),"Low", IF(AND(J23="High",L23="Fair"),"Medium", IF(AND(J23="High",L23="Poor"),"High", IF(AND(J23="High",L23="Unsatisfactory"),"High", IF(AND(J23="Medium",L23="Excellent"),"Very Low", IF(AND(J23="Medium",L23="Good"),"Very Low", IF(AND(J23="Medium",L23="Fair"),"Low", IF(AND(J23="Medium",L23="Poor"),"Medium", IF(AND(J23="Medium",L23="Unsatisfactory"),"Medium", IF(AND(J23="Low",L23="Excellent"),"Very Low", IF(AND(J23="Low",L23="Good"),"Very Low", IF(AND(J23="Low",L23="Fair"),"Very Low", IF(AND(J23="Low",L23="Poor"),"Low", IF(AND(J23="Low",L23="Unsatisfactory"),"Low", IF(AND(J23="Very Low",L23="Excellent"),"Very Low", IF(AND(J23="Very Low",L23="Good"),"Very Low", IF(AND(J23="Very Low",L23="Fair"),"Very Low", IF(AND(J23="Very Low",L23="Poor"),"Very Low", IF(AND(J23="Very Low",L23="Unsatisfactory"),"Very Low","")))))))))))))))))))))))))) -> Medium | S23: =IF(OR(L23="",R23=""),"",IF(AND(L23="Very High",R23="Excellent"),"Low",IF(AND(L23="Very High",R23="Good"),"Medium",IF(AND(L23="Very High",R23="Fair"),"High",IF(AND(L23="Very High",R23="Poor"),"Very High",IF(AND(L23="Very High",R23="Unsatisfactory"),"Very High",IF(AND(L23="High",R23="Excellent"),"Low",IF(AND(L23="High",R23="Good"),"Low",IF(AND(L23="High",R23="Fair"),"Medium",IF(AND(L23="High",R23="Poor"),"High",IF(AND(L23="High",R23="Unsatisfactory"),"High",IF(AND(L23="Medium",R23="Excellent"),"Low",IF(AND(L23="Medium",R23="Good"),"Low",IF(AND(L23="Medium",R23="Fair"),"Low",IF(AND(L23="Medium",R23="Poor"),"Medium",IF(AND(L23="Medium",R23="Unsatisfactory"),"Medium",IF(AND(L23="Low",R23="Excellent"),"Very Low",IF(AND(L23="Low",R23="Good"),"Low",IF(AND(L23="Low",R23="Fair"),"Low",IF(AND(L23="Low",R23="Poor"),"Low",IF(AND(L23="Low",R23="Unsatisfactory"),"Low",IF(AND(L23="Very Low",R23="Excellent"),"Very Low",IF(AND(L23="Very Low",R23="Good"),"Very Low",IF(AND(L23="Very Low",R23="Fair"),"Very Low",IF(AND(L23="Very Low",R23="Poor"),"Very Low",IF(AND(L23="Very Low",R23="Unsatisfactory"),"Very Low","Low")))))))))))))))))))))))))) | T23: (Action plan+ time line + controls)
A24: AFC-017 | B24: Process | C24: FOCAL Integration | D24: Anti Money Laundering | E24: Risk that incomplete/incorrect data transfer between the source system and FOCAL causes inaccurate AML processing. | F24: Likely | G24: Major | H24: =IF(F24='Risk Methedology Matrix'!B$26,5,IF(F24='Risk Methedology Matrix'!B$27,4,IF(F24='Risk Methedology Matrix'!B$28,3,IF(F24='Risk Methedology Matrix'!B$29,2,IF(F24='Risk Methedology Matrix'!B$30,1,0))))) -> 4 | I24: =IF(G24='Risk Methedology Matrix'!G$25,5,IF(G24='Risk Methedology Matrix'!F$25,4,IF(G24='Risk Methedology Matrix'!E$25,3,IF(G24='Risk Methedology Matrix'!D$25,2,IF(G24='Risk Methedology Matrix'!C$25,1,0))))) -> 4 | J24: =IF(OR(F24="",G24=""),"",IF(H24*I24>=20,"Very High",IF(AND(H24*I24<20,H24*I24>=11),"High",IF(AND(H24*I24<11,H24*I24>=6),"Medium",IF(AND(H24*I24<6,H24*I24>=3),"Low",IF(AND(H24*I24<3,H24*I24>=1),"Very Low","")))))) -> High | K24: The integration between the source system and FOCAL has been significantly enhanced to improve the completeness and accuracy of data transfer Multiple AML monitoring scenarios have been configured and activated in FOCAL and the integration and scenario performance are periodically reviewed to identify and address any data or processing issues. Further enhancements and additional scenarios are implemented based on identified risks and monitoring requirements. | L24: Fair | M24: =IF(OR(J24="",L24=""),"", IF(AND(J24="Very High",L24="Excellent"),"Low", IF(AND(J24="Very High",L24="Good"),"Medium", IF(AND(J24="Very High",L24="Fair"),"High", IF(AND(J24="Very High",L24="Poor"),"Very High", IF(AND(J24="Very High",L24="Unsatisfactory"),"Very High", IF(AND(J24="High",L24="Excellent"),"Very Low", IF(AND(J24="High",L24="Good"),"Low", IF(AND(J24="High",L24="Fair"),"Medium", IF(AND(J24="High",L24="Poor"),"High", IF(AND(J24="High",L24="Unsatisfactory"),"High", IF(AND(J24="Medium",L24="Excellent"),"Very Low", IF(AND(J24="Medium",L24="Good"),"Very Low", IF(AND(J24="Medium",L24="Fair"),"Low", IF(AND(J24="Medium",L24="Poor"),"Medium", IF(AND(J24="Medium",L24="Unsatisfactory"),"Medium", IF(AND(J24="Low",L24="Excellent"),"Very Low", IF(AND(J24="Low",L24="Good"),"Very Low", IF(AND(J24="Low",L24="Fair"),"Very Low", IF(AND(J24="Low",L24="Poor"),"Low", IF(AND(J24="Low",L24="Unsatisfactory"),"Low", IF(AND(J24="Very Low",L24="Excellent"),"Very Low", IF(AND(J24="Very Low",L24="Good"),"Very Low", IF(AND(J24="Very Low",L24="Fair"),"Very Low", IF(AND(J24="Very Low",L24="Poor"),"Very Low", IF(AND(J24="Very Low",L24="Unsatisfactory"),"Very Low","")))))))))))))))))))))))))) -> Medium
A25: AFC-018 | B25: Process | C25: Customer Risk Assessment | D25: Anti Money Laundering | E25: Risk that customers are assigned inaccurate risk ratings because FOCAL does not receive all factors required by the scoring model. | F25: Likely | G25: Major | H25: =IF(F25='Risk Methedology Matrix'!B$26,5,IF(F25='Risk Methedology Matrix'!B$27,4,IF(F25='Risk Methedology Matrix'!B$28,3,IF(F25='Risk Methedology Matrix'!B$29,2,IF(F25='Risk Methedology Matrix'!B$30,1,0))))) -> 4 | I25: =IF(G25='Risk Methedology Matrix'!G$25,5,IF(G25='Risk Methedology Matrix'!F$25,4,IF(G25='Risk Methedology Matrix'!E$25,3,IF(G25='Risk Methedology Matrix'!D$25,2,IF(G25='Risk Methedology Matrix'!C$25,1,0))))) -> 4 | J25: =IF(OR(F25="",G25=""),"",IF(H25*I25>=20,"Very High",IF(AND(H25*I25<20,H25*I25>=11),"High",IF(AND(H25*I25<11,H25*I25>=6),"Medium",IF(AND(H25*I25<6,H25*I25>=3),"Low",IF(AND(H25*I25<3,H25*I25>=1),"Very Low","")))))) -> High | K25: Currently a circular identifying high-risk Merchant Category Codes (MCCs) has been communicated to the Operations Department Merchants falling within the identified categories are referred through Tanar for review. Where applicable the customer’s classification is manually updated to High Risk in FOCAL, even if the system has not automatically classified the customer as high risk As part of the upcoming self-onboarding phase this process will be automated so that the customer’s risk classification is directly reflected in FOCAL based on the assigned MCC. | L25: Fair | M25: =IF(OR(J25="",L25=""),"", IF(AND(J25="Very High",L25="Excellent"),"Low", IF(AND(J25="Very High",L25="Good"),"Medium", IF(AND(J25="Very High",L25="Fair"),"High", IF(AND(J25="Very High",L25="Poor"),"Very High", IF(AND(J25="Very High",L25="Unsatisfactory"),"Very High", IF(AND(J25="High",L25="Excellent"),"Very Low", IF(AND(J25="High",L25="Good"),"Low", IF(AND(J25="High",L25="Fair"),"Medium", IF(AND(J25="High",L25="Poor"),"High", IF(AND(J25="High",L25="Unsatisfactory"),"High", IF(AND(J25="Medium",L25="Excellent"),"Very Low", IF(AND(J25="Medium",L25="Good"),"Very Low", IF(AND(J25="Medium",L25="Fair"),"Low", IF(AND(J25="Medium",L25="Poor"),"Medium", IF(AND(J25="Medium",L25="Unsatisfactory"),"Medium", IF(AND(J25="Low",L25="Excellent"),"Very Low", IF(AND(J25="Low",L25="Good"),"Very Low", IF(AND(J25="Low",L25="Fair"),"Very Low", IF(AND(J25="Low",L25="Poor"),"Low", IF(AND(J25="Low",L25="Unsatisfactory"),"Low", IF(AND(J25="Very Low",L25="Excellent"),"Very Low", IF(AND(J25="Very Low",L25="Good"),"Very Low", IF(AND(J25="Very Low",L25="Fair"),"Very Low", IF(AND(J25="Very Low",L25="Poor"),"Very Low", IF(AND(J25="Very Low",L25="Unsatisfactory"),"Very Low","")))))))))))))))))))))))))) -> Medium
A26: AFC-019 | B26: Process | C26: CRA Methodology | D26: Anti Money Laundering | E26: Risk that inconsistent or insufficiently governed risk-scoring criteria lead to inappropriate customer classifications. | F26: Likely | G26: Major | H26: =IF(F26='Risk Methedology Matrix'!B$26,5,IF(F26='Risk Methedology Matrix'!B$27,4,IF(F26='Risk Methedology Matrix'!B$28,3,IF(F26='Risk Methedology Matrix'!B$29,2,IF(F26='Risk Methedology Matrix'!B$30,1,0))))) -> 4 | I26: =IF(G26='Risk Methedology Matrix'!G$25,5,IF(G26='Risk Methedology Matrix'!F$25,4,IF(G26='Risk Methedology Matrix'!E$25,3,IF(G26='Risk Methedology Matrix'!D$25,2,IF(G26='Risk Methedology Matrix'!C$25,1,0))))) -> 4 | J26: =IF(OR(F26="",G26=""),"",IF(H26*I26>=20,"Very High",IF(AND(H26*I26<20,H26*I26>=11),"High",IF(AND(H26*I26<11,H26*I26>=6),"Medium",IF(AND(H26*I26<6,H26*I26>=3),"Low",IF(AND(H26*I26<3,H26*I26>=1),"Very Low","")))))) -> High | K26: Customer risk-scoring criteria are documented in the CRA methodology and include factors such as Merchant Category Code (MCC), geographic exposure, and legal entity type. The criteria are reviewed and updated when new risks are identified or relevant regulatory and FATF updates are issued. High-risk MCCs have also been communicated internally, and the applicable customer classifications are manually reflected in FOCAL pending implementation of the automated classification process | L26: Fair | M26: =IF(OR(J26="",L26=""),"", IF(AND(J26="Very High",L26="Excellent"),"Low", IF(AND(J26="Very High",L26="Good"),"Medium", IF(AND(J26="Very High",L26="Fair"),"High", IF(AND(J26="Very High",L26="Poor"),"Very High", IF(AND(J26="Very High",L26="Unsatisfactory"),"Very High", IF(AND(J26="High",L26="Excellent"),"Very Low", IF(AND(J26="High",L26="Good"),"Low", IF(AND(J26="High",L26="Fair"),"Medium", IF(AND(J26="High",L26="Poor"),"High", IF(AND(J26="High",L26="Unsatisfactory"),"High", IF(AND(J26="Medium",L26="Excellent"),"Very Low", IF(AND(J26="Medium",L26="Good"),"Very Low", IF(AND(J26="Medium",L26="Fair"),"Low", IF(AND(J26="Medium",L26="Poor"),"Medium", IF(AND(J26="Medium",L26="Unsatisfactory"),"Medium", IF(AND(J26="Low",L26="Excellent"),"Very Low", IF(AND(J26="Low",L26="Good"),"Very Low", IF(AND(J26="Low",L26="Fair"),"Very Low", IF(AND(J26="Low",L26="Poor"),"Low", IF(AND(J26="Low",L26="Unsatisfactory"),"Low", IF(AND(J26="Very Low",L26="Excellent"),"Very Low", IF(AND(J26="Very Low",L26="Good"),"Very Low", IF(AND(J26="Very Low",L26="Fair"),"Very Low", IF(AND(J26="Very Low",L26="Poor"),"Very Low", IF(AND(J26="Very Low",L26="Unsatisfactory"),"Very Low","")))))))))))))))))))))))))) -> Medium
A27: AFC-20 | B27: Process | C27: Sanctions/Name Screening | D27: Anti Money Laundering | E27: Risk that incomplete identifiers reduce screening accuracy or generate excessive false positives. | F27: Likely | G27: Major | H27: =IF(F27='Risk Methedology Matrix'!B$26,5,IF(F27='Risk Methedology Matrix'!B$27,4,IF(F27='Risk Methedology Matrix'!B$28,3,IF(F27='Risk Methedology Matrix'!B$29,2,IF(F27='Risk Methedology Matrix'!B$30,1,0))))) -> 4 | I27: =IF(G27='Risk Methedology Matrix'!G$25,5,IF(G27='Risk Methedology Matrix'!F$25,4,IF(G27='Risk Methedology Matrix'!E$25,3,IF(G27='Risk Methedology Matrix'!D$25,2,IF(G27='Risk Methedology Matrix'!C$25,1,0))))) -> 4 | J27: =IF(OR(F27="",G27=""),"",IF(H27*I27>=20,"Very High",IF(AND(H27*I27<20,H27*I27>=11),"High",IF(AND(H27*I27<11,H27*I27>=6),"Medium",IF(AND(H27*I27<6,H27*I27>=3),"Low",IF(AND(H27*I27<3,H27*I27>=1),"Very Low","")))))) -> High | K27: Customer identification data transferred to FOCAL through Tanar includes the customer’s name, commercial registration number, nationality, and other available identifiers. Mandatory fields are subject to automated validation to support data completeness. Where a potential name match is identified, the alert is reviewed against the customer’s information and supporting documents, including the date of birth shown on the provided identification document. The outcome of the review and the reason for closing any false-positive alert are documented in the system | L27: Poor | M27: =IF(OR(J27="",L27=""),"", IF(AND(J27="Very High",L27="Excellent"),"Low", IF(AND(J27="Very High",L27="Good"),"Medium", IF(AND(J27="Very High",L27="Fair"),"High", IF(AND(J27="Very High",L27="Poor"),"Very High", IF(AND(J27="Very High",L27="Unsatisfactory"),"Very High", IF(AND(J27="High",L27="Excellent"),"Very Low", IF(AND(J27="High",L27="Good"),"Low", IF(AND(J27="High",L27="Fair"),"Medium", IF(AND(J27="High",L27="Poor"),"High", IF(AND(J27="High",L27="Unsatisfactory"),"High", IF(AND(J27="Medium",L27="Excellent"),"Very Low", IF(AND(J27="Medium",L27="Good"),"Very Low", IF(AND(J27="Medium",L27="Fair"),"Low", IF(AND(J27="Medium",L27="Poor"),"Medium", IF(AND(J27="Medium",L27="Unsatisfactory"),"Medium", IF(AND(J27="Low",L27="Excellent"),"Very Low", IF(AND(J27="Low",L27="Good"),"Very Low", IF(AND(J27="Low",L27="Fair"),"Very Low", IF(AND(J27="Low",L27="Poor"),"Low", IF(AND(J27="Low",L27="Unsatisfactory"),"Low", IF(AND(J27="Very Low",L27="Excellent"),"Very Low", IF(AND(J27="Very Low",L27="Good"),"Very Low", IF(AND(J27="Very Low",L27="Fair"),"Very Low", IF(AND(J27="Very Low",L27="Poor"),"Very Low", IF(AND(J27="Very Low",L27="Unsatisfactory"),"Very Low","")))))))))))))))))))))))))) -> High
A28: AFC-21 | B28: Process | C28: Alert/Case Management | D28: Anti Money Laundering | E28: Risk that transaction-monitoring alerts are not investigated and closed within appropriate timelines. | F28: Likely | G28: Major | H28: =IF(F28='Risk Methedology Matrix'!B$26,5,IF(F28='Risk Methedology Matrix'!B$27,4,IF(F28='Risk Methedology Matrix'!B$28,3,IF(F28='Risk Methedology Matrix'!B$29,2,IF(F28='Risk Methedology Matrix'!B$30,1,0))))) -> 4 | I28: =IF(G28='Risk Methedology Matrix'!G$25,5,IF(G28='Risk Methedology Matrix'!F$25,4,IF(G28='Risk Methedology Matrix'!E$25,3,IF(G28='Risk Methedology Matrix'!D$25,2,IF(G28='Risk Methedology Matrix'!C$25,1,0))))) -> 4 | J28: =IF(OR(F28="",G28=""),"",IF(H28*I28>=20,"Very High",IF(AND(H28*I28<20,H28*I28>=11),"High",IF(AND(H28*I28<11,H28*I28>=6),"Medium",IF(AND(H28*I28<6,H28*I28>=3),"Low",IF(AND(H28*I28<3,H28*I28>=1),"Very Low","")))))) -> High | K28: An internal SLA has been established for the Anti-Money Laundering Department and is attached as supporting evidence. The SLA defines a clear timeframe requiring transaction-monitoring alerts to be reviewed, investigated, and closed within seven business days, supporting their timely handling and resolution. | L28: Fair | M28: =IF(OR(J28="",L28=""),"", IF(AND(J28="Very High",L28="Excellent"),"Low", IF(AND(J28="Very High",L28="Good"),"Medium", IF(AND(J28="Very High",L28="Fair"),"High", IF(AND(J28="Very High",L28="Poor"),"Very High", IF(AND(J28="Very High",L28="Unsatisfactory"),"Very High", IF(AND(J28="High",L28="Excellent"),"Very Low", IF(AND(J28="High",L28="Good"),"Low", IF(AND(J28="High",L28="Fair"),"Medium", IF(AND(J28="High",L28="Poor"),"High", IF(AND(J28="High",L28="Unsatisfactory"),"High", IF(AND(J28="Medium",L28="Excellent"),"Very Low", IF(AND(J28="Medium",L28="Good"),"Very Low", IF(AND(J28="Medium",L28="Fair"),"Low", IF(AND(J28="Medium",L28="Poor"),"Medium", IF(AND(J28="Medium",L28="Unsatisfactory"),"Medium", IF(AND(J28="Low",L28="Excellent"),"Very Low", IF(AND(J28="Low",L28="Good"),"Very Low", IF(AND(J28="Low",L28="Fair"),"Very Low", IF(AND(J28="Low",L28="Poor"),"Low", IF(AND(J28="Low",L28="Unsatisfactory"),"Low", IF(AND(J28="Very Low",L28="Excellent"),"Very Low", IF(AND(J28="Very Low",L28="Good"),"Very Low", IF(AND(J28="Very Low",L28="Fair"),"Very Low", IF(AND(J28="Very Low",L28="Poor"),"Very Low", IF(AND(J28="Very Low",L28="Unsatisfactory"),"Very Low","")))))))))))))))))))))))))) -> Medium
A29: AFC-22 | B29: Process | C29: STR Reporting | D29: Anti Money Laundering | E29: Risk that reportable suspicious activity is not reported to FIU accurately and within required timelines. | F29: Likely | G29: Major | H29: =IF(F29='Risk Methedology Matrix'!B$26,5,IF(F29='Risk Methedology Matrix'!B$27,4,IF(F29='Risk Methedology Matrix'!B$28,3,IF(F29='Risk Methedology Matrix'!B$29,2,IF(F29='Risk Methedology Matrix'!B$30,1,0))))) -> 4 | I29: =IF(G29='Risk Methedology Matrix'!G$25,5,IF(G29='Risk Methedology Matrix'!F$25,4,IF(G29='Risk Methedology Matrix'!E$25,3,IF(G29='Risk Methedology Matrix'!D$25,2,IF(G29='Risk Methedology Matrix'!C$25,1,0))))) -> 4 | J29: =IF(OR(F29="",G29=""),"",IF(H29*I29>=20,"Very High",IF(AND(H29*I29<20,H29*I29>=11),"High",IF(AND(H29*I29<11,H29*I29>=6),"Medium",IF(AND(H29*I29<6,H29*I29>=3),"Low",IF(AND(H29*I29<3,H29*I29>=1),"Very Low","")))))) -> High | K29: The internal AML/CTF SLA establishes a clear requirement for Suspicious Transaction Reports (STRs) to be filed with SAFIU immediately upon establishing reasonable grounds for suspicion. The investigation timeline must not delay the reporting process, and any reporting deadline imposed by SAMA, SAFIU, or another competent authority takes priority over the internal SLA. The signed AML/CTF SLA is attached as supporting evidence | L29: Good | M29: =IF(OR(J29="",L29=""),"", IF(AND(J29="Very High",L29="Excellent"),"Low", IF(AND(J29="Very High",L29="Good"),"Medium", IF(AND(J29="Very High",L29="Fair"),"High", IF(AND(J29="Very High",L29="Poor"),"Very High", IF(AND(J29="Very High",L29="Unsatisfactory"),"Very High", IF(AND(J29="High",L29="Excellent"),"Very Low", IF(AND(J29="High",L29="Good"),"Low", IF(AND(J29="High",L29="Fair"),"Medium", IF(AND(J29="High",L29="Poor"),"High", IF(AND(J29="High",L29="Unsatisfactory"),"High", IF(AND(J29="Medium",L29="Excellent"),"Very Low", IF(AND(J29="Medium",L29="Good"),"Very Low", IF(AND(J29="Medium",L29="Fair"),"Low", IF(AND(J29="Medium",L29="Poor"),"Medium", IF(AND(J29="Medium",L29="Unsatisfactory"),"Medium", IF(AND(J29="Low",L29="Excellent"),"Very Low", IF(AND(J29="Low",L29="Good"),"Very Low", IF(AND(J29="Low",L29="Fair"),"Very Low", IF(AND(J29="Low",L29="Poor"),"Low", IF(AND(J29="Low",L29="Unsatisfactory"),"Low", IF(AND(J29="Very Low",L29="Excellent"),"Very Low", IF(AND(J29="Very Low",L29="Good"),"Very Low", IF(AND(J29="Very Low",L29="Fair"),"Very Low", IF(AND(J29="Very Low",L29="Poor"),"Very Low", IF(AND(J29="Very Low",L29="Unsatisfactory"),"Very Low","")))))))))))))))))))))))))) -> Low
A30: AFC-23 | B30: Process | C30: New Product AML Risk | D30: Anti Money Laundering | E30: Risk that new products/services are launched without appropriate ML/TF risk assessment and mitigating controls. | F30: Likely | G30: Major | H30: =IF(F30='Risk Methedology Matrix'!B$26,5,IF(F30='Risk Methedology Matrix'!B$27,4,IF(F30='Risk Methedology Matrix'!B$28,3,IF(F30='Risk Methedology Matrix'!B$29,2,IF(F30='Risk Methedology Matrix'!B$30,1,0))))) -> 4 | I30: =IF(G30='Risk Methedology Matrix'!G$25,5,IF(G30='Risk Methedology Matrix'!F$25,4,IF(G30='Risk Methedology Matrix'!E$25,3,IF(G30='Risk Methedology Matrix'!D$25,2,IF(G30='Risk Methedology Matrix'!C$25,1,0))))) -> 4 | J30: =IF(OR(F30="",G30=""),"",IF(H30*I30>=20,"Very High",IF(AND(H30*I30<20,H30*I30>=11),"High",IF(AND(H30*I30<11,H30*I30>=6),"Medium",IF(AND(H30*I30<6,H30*I30>=3),"Low",IF(AND(H30*I30<3,H30*I30>=1),"Very Low","")))))) -> High | K30: Currently, there is no formal process requiring new products or services to be referred for an AML/CTF risk assessment before launch, and no previous product risk assessments have been provided to the AML function. As a planned enhancement, an AML review and approval step will be incorporated into the product-launch process in coordination with the Product and Risk teams to ensure that relevant ML/TF risks and required mitigating controls are assessed before launch | L30: Fair | M30: =IF(OR(J30="",L30=""),"", IF(AND(J30="Very High",L30="Excellent"),"Low", IF(AND(J30="Very High",L30="Good"),"Medium", IF(AND(J30="Very High",L30="Fair"),"High", IF(AND(J30="Very High",L30="Poor"),"Very High", IF(AND(J30="Very High",L30="Unsatisfactory"),"Very High", IF(AND(J30="High",L30="Excellent"),"Very Low", IF(AND(J30="High",L30="Good"),"Low", IF(AND(J30="High",L30="Fair"),"Medium", IF(AND(J30="High",L30="Poor"),"High", IF(AND(J30="High",L30="Unsatisfactory"),"High", IF(AND(J30="Medium",L30="Excellent"),"Very Low", IF(AND(J30="Medium",L30="Good"),"Very Low", IF(AND(J30="Medium",L30="Fair"),"Low", IF(AND(J30="Medium",L30="Poor"),"Medium", IF(AND(J30="Medium",L30="Unsatisfactory"),"Medium", IF(AND(J30="Low",L30="Excellent"),"Very Low", IF(AND(J30="Low",L30="Good"),"Very Low", IF(AND(J30="Low",L30="Fair"),"Very Low", IF(AND(J30="Low",L30="Poor"),"Low", IF(AND(J30="Low",L30="Unsatisfactory"),"Low", IF(AND(J30="Very Low",L30="Excellent"),"Very Low", IF(AND(J30="Very Low",L30="Good"),"Very Low", IF(AND(J30="Very Low",L30="Fair"),"Very Low", IF(AND(J30="Very Low",L30="Poor"),"Very Low", IF(AND(J30="Very Low",L30="Unsatisfactory"),"Very Low","")))))))))))))))))))))))))) -> Medium
A31: AFC-24 | B31: Process | C31: CRA/BRA Linkage | D31: Anti Money Laundering | E31: Risk that customer risk assessment does not appropriately reflect institution-level ML/TF risk factors. | F31: Likely | G31: Major | H31: =IF(F31='Risk Methedology Matrix'!B$26,5,IF(F31='Risk Methedology Matrix'!B$27,4,IF(F31='Risk Methedology Matrix'!B$28,3,IF(F31='Risk Methedology Matrix'!B$29,2,IF(F31='Risk Methedology Matrix'!B$30,1,0))))) -> 4 | I31: =IF(G31='Risk Methedology Matrix'!G$25,5,IF(G31='Risk Methedology Matrix'!F$25,4,IF(G31='Risk Methedology Matrix'!E$25,3,IF(G31='Risk Methedology Matrix'!D$25,2,IF(G31='Risk Methedology Matrix'!C$25,1,0))))) -> 4 | J31: =IF(OR(F31="",G31=""),"",IF(H31*I31>=20,"Very High",IF(AND(H31*I31<20,H31*I31>=11),"High",IF(AND(H31*I31<11,H31*I31>=6),"Medium",IF(AND(H31*I31<6,H31*I31>=3),"Low",IF(AND(H31*I31<3,H31*I31>=1),"Very Low","")))))) -> High | K31: Customer Risk Assessment (CRA) incorporates the institution-level ML/TF risk factors identified through the Business Risk Assessment (BRA), including Merchant Category Code (MCC), geographic exposure, legal entity type, and products or services. Customer classifications are applied through a combination of automated rules in FOCAL and manual adjustments. The risk factors and classification criteria are reviewed and updated when new or changing risks are identified. While the linkage is operationally applied, it is not currently supported by a standalone documented CRA/BRA mapping | L31: Fair | M31: =IF(OR(J31="",L31=""),"", IF(AND(J31="Very High",L31="Excellent"),"Low", IF(AND(J31="Very High",L31="Good"),"Medium", IF(AND(J31="Very High",L31="Fair"),"High", IF(AND(J31="Very High",L31="Poor"),"Very High", IF(AND(J31="Very High",L31="Unsatisfactory"),"Very High", IF(AND(J31="High",L31="Excellent"),"Very Low", IF(AND(J31="High",L31="Good"),"Low", IF(AND(J31="High",L31="Fair"),"Medium", IF(AND(J31="High",L31="Poor"),"High", IF(AND(J31="High",L31="Unsatisfactory"),"High", IF(AND(J31="Medium",L31="Excellent"),"Very Low", IF(AND(J31="Medium",L31="Good"),"Very Low", IF(AND(J31="Medium",L31="Fair"),"Low", IF(AND(J31="Medium",L31="Poor"),"Medium", IF(AND(J31="Medium",L31="Unsatisfactory"),"Medium", IF(AND(J31="Low",L31="Excellent"),"Very Low", IF(AND(J31="Low",L31="Good"),"Very Low", IF(AND(J31="Low",L31="Fair"),"Very Low", IF(AND(J31="Low",L31="Poor"),"Low", IF(AND(J31="Low",L31="Unsatisfactory"),"Low", IF(AND(J31="Very Low",L31="Excellent"),"Very Low", IF(AND(J31="Very Low",L31="Good"),"Very Low", IF(AND(J31="Very Low",L31="Fair"),"Very Low", IF(AND(J31="Very Low",L31="Poor"),"Very Low", IF(AND(J31="Very Low",L31="Unsatisfactory"),"Very Low","")))))))))))))))))))))))))) -> Medium
A32: AFC-25 | B32: Process | C32: Key-Person / Succession | D32: Anti Money Laundering | E32: Risk of disruption to AML operations and remediation due to departure of key AML/Compliance personnel. | F32: Likely | G32: Major | H32: =IF(F32='Risk Methedology Matrix'!B$26,5,IF(F32='Risk Methedology Matrix'!B$27,4,IF(F32='Risk Methedology Matrix'!B$28,3,IF(F32='Risk Methedology Matrix'!B$29,2,IF(F32='Risk Methedology Matrix'!B$30,1,0))))) -> 4 | I32: =IF(G32='Risk Methedology Matrix'!G$25,5,IF(G32='Risk Methedology Matrix'!F$25,4,IF(G32='Risk Methedology Matrix'!E$25,3,IF(G32='Risk Methedology Matrix'!D$25,2,IF(G32='Risk Methedology Matrix'!C$25,1,0))))) -> 4 | J32: =IF(OR(F32="",G32=""),"",IF(H32*I32>=20,"Very High",IF(AND(H32*I32<20,H32*I32>=11),"High",IF(AND(H32*I32<11,H32*I32>=6),"Medium",IF(AND(H32*I32<6,H32*I32>=3),"Low",IF(AND(H32*I32<3,H32*I32>=1),"Very Low","")))))) -> High | K32: The AML Department currently consists of two employees. In the event that either employee leaves the department, a complete handover of all responsibilities, ongoing tasks, open cases, and relevant documentation must be provided to the remaining employee to support continuity of AML operations and remediation activities | L32: Fair | M32: =IF(OR(J32="",L32=""),"", IF(AND(J32="Very High",L32="Excellent"),"Low", IF(AND(J32="Very High",L32="Good"),"Medium", IF(AND(J32="Very High",L32="Fair"),"High", IF(AND(J32="Very High",L32="Poor"),"Very High", IF(AND(J32="Very High",L32="Unsatisfactory"),"Very High", IF(AND(J32="High",L32="Excellent"),"Very Low", IF(AND(J32="High",L32="Good"),"Low", IF(AND(J32="High",L32="Fair"),"Medium", IF(AND(J32="High",L32="Poor"),"High", IF(AND(J32="High",L32="Unsatisfactory"),"High", IF(AND(J32="Medium",L32="Excellent"),"Very Low", IF(AND(J32="Medium",L32="Good"),"Very Low", IF(AND(J32="Medium",L32="Fair"),"Low", IF(AND(J32="Medium",L32="Poor"),"Medium", IF(AND(J32="Medium",L32="Unsatisfactory"),"Medium", IF(AND(J32="Low",L32="Excellent"),"Very Low", IF(AND(J32="Low",L32="Good"),"Very Low", IF(AND(J32="Low",L32="Fair"),"Very Low", IF(AND(J32="Low",L32="Poor"),"Low", IF(AND(J32="Low",L32="Unsatisfactory"),"Low", IF(AND(J32="Very Low",L32="Excellent"),"Very Low", IF(AND(J32="Very Low",L32="Good"),"Very Low", IF(AND(J32="Very Low",L32="Fair"),"Very Low", IF(AND(J32="Very Low",L32="Poor"),"Very Low", IF(AND(J32="Very Low",L32="Unsatisfactory"),"Very Low","")))))))))))))))))))))))))) -> Medium
A33: PAY-001 | B33: People | C33: Ineffective Policy Governance | D33: Pay Operations | E33: Failure by the Board to review and approve key policies annually may result in outdated, non-compliant, or irrelevant operational directives | F33: Possible | G33: Minor | H33: =IF(F33='Risk Methedology Matrix'!B$26,5,IF(F33='Risk Methedology Matrix'!B$27,4,IF(F33='Risk Methedology Matrix'!B$28,3,IF(F33='Risk Methedology Matrix'!B$29,2,IF(F33='Risk Methedology Matrix'!B$30,1,0))))) -> 3 | I33: =IF(G33='Risk Methedology Matrix'!G$25,5,IF(G33='Risk Methedology Matrix'!F$25,4,IF(G33='Risk Methedology Matrix'!E$25,3,IF(G33='Risk Methedology Matrix'!D$25,2,IF(G33='Risk Methedology Matrix'!C$25,1,0))))) -> 2 | J33: =IF(OR(F33="",G33=""),"",IF(H33*I33>=20,"Very High",IF(AND(H33*I33<20,H33*I33>=11),"High",IF(AND(H33*I33<11,H33*I33>=6),"Medium",IF(AND(H33*I33<6,H33*I33>=3),"Low",IF(AND(H33*I33<3,H33*I33>=1),"Very Low","")))))) -> Medium | K33: Annual policy review and approval mandated for the Board. | L33: Fair | M33: =IF(OR(J33="",L33=""),"", IF(AND(J33="Very High",L33="Excellent"),"Low", IF(AND(J33="Very High",L33="Good"),"Medium", IF(AND(J33="Very High",L33="Fair"),"High", IF(AND(J33="Very High",L33="Poor"),"Very High", IF(AND(J33="Very High",L33="Unsatisfactory"),"Very High", IF(AND(J33="High",L33="Excellent"),"Very Low", IF(AND(J33="High",L33="Good"),"Low", IF(AND(J33="High",L33="Fair"),"Medium", IF(AND(J33="High",L33="Poor"),"High", IF(AND(J33="High",L33="Unsatisfactory"),"High", IF(AND(J33="Medium",L33="Excellent"),"Very Low", IF(AND(J33="Medium",L33="Good"),"Very Low", IF(AND(J33="Medium",L33="Fair"),"Low", IF(AND(J33="Medium",L33="Poor"),"Medium", IF(AND(J33="Medium",L33="Unsatisfactory"),"Medium", IF(AND(J33="Low",L33="Excellent"),"Very Low", IF(AND(J33="Low",L33="Good"),"Very Low", IF(AND(J33="Low",L33="Fair"),"Very Low", IF(AND(J33="Low",L33="Poor"),"Low", IF(AND(J33="Low",L33="Unsatisfactory"),"Low", IF(AND(J33="Very Low",L33="Excellent"),"Very Low", IF(AND(J33="Very Low",L33="Good"),"Very Low", IF(AND(J33="Very Low",L33="Fair"),"Very Low", IF(AND(J33="Very Low",L33="Poor"),"Very Low", IF(AND(J33="Very Low",L33="Unsatisfactory"),"Very Low","")))))))))))))))))))))))))) -> Low | S33: =IF(OR(L33="",R33=""),"",IF(AND(L33="Very High",R33="Excellent"),"Low",IF(AND(L33="Very High",R33="Good"),"Medium",IF(AND(L33="Very High",R33="Fair"),"High",IF(AND(L33="Very High",R33="Poor"),"Very High",IF(AND(L33="Very High",R33="Unsatisfactory"),"Very High",IF(AND(L33="High",R33="Excellent"),"Low",IF(AND(L33="High",R33="Good"),"Low",IF(AND(L33="High",R33="Fair"),"Medium",IF(AND(L33="High",R33="Poor"),"High",IF(AND(L33="High",R33="Unsatisfactory"),"High",IF(AND(L33="Medium",R33="Excellent"),"Low",IF(AND(L33="Medium",R33="Good"),"Low",IF(AND(L33="Medium",R33="Fair"),"Low",IF(AND(L33="Medium",R33="Poor"),"Medium",IF(AND(L33="Medium",R33="Unsatisfactory"),"Medium",IF(AND(L33="Low",R33="Excellent"),"Very Low",IF(AND(L33="Low",R33="Good"),"Low",IF(AND(L33="Low",R33="Fair"),"Low",IF(AND(L33="Low",R33="Poor"),"Low",IF(AND(L33="Low",R33="Unsatisfactory"),"Low",IF(AND(L33="Very Low",R33="Excellent"),"Very Low",IF(AND(L33="Very Low",R33="Good"),"Very Low",IF(AND(L33="Very Low",R33="Fair"),"Very Low",IF(AND(L33="Very Low",R33="Poor"),"Very Low",IF(AND(L33="Very Low",R33="Unsatisfactory"),"Very Low","Low"))))))))))))))))))))))))))
A34: PAY-002 | B34: Process | C34: Inadequate Resource Allocation | D34: Pay Operations | E34: Failure of the General Manager to provide adequate support and resources to the Operations Department may result in underperformance or operational bottlenecks. | F34: Possible | G34: Minor | H34: =IF(F34='Risk Methedology Matrix'!B$26,5,IF(F34='Risk Methedology Matrix'!B$27,4,IF(F34='Risk Methedology Matrix'!B$28,3,IF(F34='Risk Methedology Matrix'!B$29,2,IF(F34='Risk Methedology Matrix'!B$30,1,0))))) -> 3 | I34: =IF(G34='Risk Methedology Matrix'!G$25,5,IF(G34='Risk Methedology Matrix'!F$25,4,IF(G34='Risk Methedology Matrix'!E$25,3,IF(G34='Risk Methedology Matrix'!D$25,2,IF(G34='Risk Methedology Matrix'!C$25,1,0))))) -> 2 | J34: =IF(OR(F34="",G34=""),"",IF(H34*I34>=20,"Very High",IF(AND(H34*I34<20,H34*I34>=11),"High",IF(AND(H34*I34<11,H34*I34>=6),"Medium",IF(AND(H34*I34<6,H34*I34>=3),"Low",IF(AND(H34*I34<3,H34*I34>=1),"Very Low","")))))) -> Medium | K34: GM is assigned responsibility to provide necessary resources and ensure policy is reviewed and updated. | L34: Fair | M34: =IF(OR(J34="",L34=""),"", IF(AND(J34="Very High",L34="Excellent"),"Low", IF(AND(J34="Very High",L34="Good"),"Medium", IF(AND(J34="Very High",L34="Fair"),"High", IF(AND(J34="Very High",L34="Poor"),"Very High", IF(AND(J34="Very High",L34="Unsatisfactory"),"Very High", IF(AND(J34="High",L34="Excellent"),"Very Low", IF(AND(J34="High",L34="Good"),"Low", IF(AND(J34="High",L34="Fair"),"Medium", IF(AND(J34="High",L34="Poor"),"High", IF(AND(J34="High",L34="Unsatisfactory"),"High", IF(AND(J34="Medium",L34="Excellent"),"Very Low", IF(AND(J34="Medium",L34="Good"),"Very Low", IF(AND(J34="Medium",L34="Fair"),"Low", IF(AND(J34="Medium",L34="Poor"),"Medium", IF(AND(J34="Medium",L34="Unsatisfactory"),"Medium", IF(AND(J34="Low",L34="Excellent"),"Very Low", IF(AND(J34="Low",L34="Good"),"Very Low", IF(AND(J34="Low",L34="Fair"),"Very Low", IF(AND(J34="Low",L34="Poor"),"Low", IF(AND(J34="Low",L34="Unsatisfactory"),"Low", IF(AND(J34="Very Low",L34="Excellent"),"Very Low", IF(AND(J34="Very Low",L34="Good"),"Very Low", IF(AND(J34="Very Low",L34="Fair"),"Very Low", IF(AND(J34="Very Low",L34="Poor"),"Very Low", IF(AND(J34="Very Low",L34="Unsatisfactory"),"Very Low","")))))))))))))))))))))))))) -> Low | S34: =IF(OR(L34="",R34=""),"",IF(AND(L34="Very High",R34="Excellent"),"Low",IF(AND(L34="Very High",R34="Good"),"Medium",IF(AND(L34="Very High",R34="Fair"),"High",IF(AND(L34="Very High",R34="Poor"),"Very High",IF(AND(L34="Very High",R34="Unsatisfactory"),"Very High",IF(AND(L34="High",R34="Excellent"),"Low",IF(AND(L34="High",R34="Good"),"Low",IF(AND(L34="High",R34="Fair"),"Medium",IF(AND(L34="High",R34="Poor"),"High",IF(AND(L34="High",R34="Unsatisfactory"),"High",IF(AND(L34="Medium",R34="Excellent"),"Low",IF(AND(L34="Medium",R34="Good"),"Low",IF(AND(L34="Medium",R34="Fair"),"Low",IF(AND(L34="Medium",R34="Poor"),"Medium",IF(AND(L34="Medium",R34="Unsatisfactory"),"Medium",IF(AND(L34="Low",R34="Excellent"),"Very Low",IF(AND(L34="Low",R34="Good"),"Low",IF(AND(L34="Low",R34="Fair"),"Low",IF(AND(L34="Low",R34="Poor"),"Low",IF(AND(L34="Low",R34="Unsatisfactory"),"Low",IF(AND(L34="Very Low",R34="Excellent"),"Very Low",IF(AND(L34="Very Low",R34="Good"),"Very Low",IF(AND(L34="Very Low",R34="Fair"),"Very Low",IF(AND(L34="Very Low",R34="Poor"),"Very Low",IF(AND(L34="Very Low",R34="Unsatisfactory"),"Very Low","Low"))))))))))))))))))))))))))
A35: PAY-003 | B35: Process | C35: Incomplete or Incorrect Merchant Onboarding Data - Online Onboarding Request (PAY) | D35: Pay Operations | E35: If merchant-provided data (CR number, national ID, IBAN certificate, branch photo) is incomplete, mismatched, or incorrect, it may result in erroneous onboarding or non-compliance. | F35: Likely | G35: Major | H35: =IF(F35='Risk Methedology Matrix'!B$26,5,IF(F35='Risk Methedology Matrix'!B$27,4,IF(F35='Risk Methedology Matrix'!B$28,3,IF(F35='Risk Methedology Matrix'!B$29,2,IF(F35='Risk Methedology Matrix'!B$30,1,0))))) -> 4 | I35: =IF(G35='Risk Methedology Matrix'!G$25,5,IF(G35='Risk Methedology Matrix'!F$25,4,IF(G35='Risk Methedology Matrix'!E$25,3,IF(G35='Risk Methedology Matrix'!D$25,2,IF(G35='Risk Methedology Matrix'!C$25,1,0))))) -> 4 | J35: =IF(OR(F35="",G35=""),"",IF(H35*I35>=20,"Very High",IF(AND(H35*I35<20,H35*I35>=11),"High",IF(AND(H35*I35<11,H35*I35>=6),"Medium",IF(AND(H35*I35<6,H35*I35>=3),"Low",IF(AND(H35*I35<3,H35*I35>=1),"Very Low","")))))) -> High | K35: Validation checks are performed by the Information Validator through MMS portal to ensure consistency between the submitted data (CR, ID, IBAN, CRM Opportunity). Requests with missing or inconsistent data are rejected, and merchants are notified via email/SMS. | L35: Good | M35: =IF(OR(J35="",L35=""),"", IF(AND(J35="Very High",L35="Excellent"),"Low", IF(AND(J35="Very High",L35="Good"),"Medium", IF(AND(J35="Very High",L35="Fair"),"High", IF(AND(J35="Very High",L35="Poor"),"Very High", IF(AND(J35="Very High",L35="Unsatisfactory"),"Very High", IF(AND(J35="High",L35="Excellent"),"Very Low", IF(AND(J35="High",L35="Good"),"Low", IF(AND(J35="High",L35="Fair"),"Medium", IF(AND(J35="High",L35="Poor"),"High", IF(AND(J35="High",L35="Unsatisfactory"),"High", IF(AND(J35="Medium",L35="Excellent"),"Very Low", IF(AND(J35="Medium",L35="Good"),"Very Low", IF(AND(J35="Medium",L35="Fair"),"Low", IF(AND(J35="Medium",L35="Poor"),"Medium", IF(AND(J35="Medium",L35="Unsatisfactory"),"Medium", IF(AND(J35="Low",L35="Excellent"),"Very Low", IF(AND(J35="Low",L35="Good"),"Very Low", IF(AND(J35="Low",L35="Fair"),"Very Low", IF(AND(J35="Low",L35="Poor"),"Low", IF(AND(J35="Low",L35="Unsatisfactory"),"Low", IF(AND(J35="Very Low",L35="Excellent"),"Very Low", IF(AND(J35="Very Low",L35="Good"),"Very Low", IF(AND(J35="Very Low",L35="Fair"),"Very Low", IF(AND(J35="Very Low",L35="Poor"),"Very Low", IF(AND(J35="Very Low",L35="Unsatisfactory"),"Very Low","")))))))))))))))))))))))))) -> Low | S35: =IF(OR(L35="",R35=""),"",IF(AND(L35="Very High",R35="Excellent"),"Low",IF(AND(L35="Very High",R35="Good"),"Medium",IF(AND(L35="Very High",R35="Fair"),"High",IF(AND(L35="Very High",R35="Poor"),"Very High",IF(AND(L35="Very High",R35="Unsatisfactory"),"Very High",IF(AND(L35="High",R35="Excellent"),"Low",IF(AND(L35="High",R35="Good"),"Low",IF(AND(L35="High",R35="Fair"),"Medium",IF(AND(L35="High",R35="Poor"),"High",IF(AND(L35="High",R35="Unsatisfactory"),"High",IF(AND(L35="Medium",R35="Excellent"),"Low",IF(AND(L35="Medium",R35="Good"),"Low",IF(AND(L35="Medium",R35="Fair"),"Low",IF(AND(L35="Medium",R35="Poor"),"Medium",IF(AND(L35="Medium",R35="Unsatisfactory"),"Medium",IF(AND(L35="Low",R35="Excellent"),"Very Low",IF(AND(L35="Low",R35="Good"),"Low",IF(AND(L35="Low",R35="Fair"),"Low",IF(AND(L35="Low",R35="Poor"),"Low",IF(AND(L35="Low",R35="Unsatisfactory"),"Low",IF(AND(L35="Very Low",R35="Excellent"),"Very Low",IF(AND(L35="Very Low",R35="Good"),"Very Low",IF(AND(L35="Very Low",R35="Fair"),"Very Low",IF(AND(L35="Very Low",R35="Poor"),"Very Low",IF(AND(L35="Very Low",R35="Unsatisfactory"),"Very Low","Low"))))))))))))))))))))))))))
A36: PAY-004 | B36: Process | C36: Device Request Mismatch - Online Onboarding Request (PAY) | D36: Pay Operations | E36: Risk that requested device type or quantity does not match CRM Opportunity records | F36: Likely | G36: Major | H36: =IF(F36='Risk Methedology Matrix'!B$26,5,IF(F36='Risk Methedology Matrix'!B$27,4,IF(F36='Risk Methedology Matrix'!B$28,3,IF(F36='Risk Methedology Matrix'!B$29,2,IF(F36='Risk Methedology Matrix'!B$30,1,0))))) -> 4 | I36: =IF(G36='Risk Methedology Matrix'!G$25,5,IF(G36='Risk Methedology Matrix'!F$25,4,IF(G36='Risk Methedology Matrix'!E$25,3,IF(G36='Risk Methedology Matrix'!D$25,2,IF(G36='Risk Methedology Matrix'!C$25,1,0))))) -> 4 | J36: =IF(OR(F36="",G36=""),"",IF(H36*I36>=20,"Very High",IF(AND(H36*I36<20,H36*I36>=11),"High",IF(AND(H36*I36<11,H36*I36>=6),"Medium",IF(AND(H36*I36<6,H36*I36>=3),"Low",IF(AND(H36*I36<3,H36*I36>=1),"Very Low","")))))) -> High | K36: Validation that device type and number match entries in the CRM Opportunity | L36: Good | M36: =IF(OR(J36="",L36=""),"", IF(AND(J36="Very High",L36="Excellent"),"Low", IF(AND(J36="Very High",L36="Good"),"Medium", IF(AND(J36="Very High",L36="Fair"),"High", IF(AND(J36="Very High",L36="Poor"),"Very High", IF(AND(J36="Very High",L36="Unsatisfactory"),"Very High", IF(AND(J36="High",L36="Excellent"),"Very Low", IF(AND(J36="High",L36="Good"),"Low", IF(AND(J36="High",L36="Fair"),"Medium", IF(AND(J36="High",L36="Poor"),"High", IF(AND(J36="High",L36="Unsatisfactory"),"High", IF(AND(J36="Medium",L36="Excellent"),"Very Low", IF(AND(J36="Medium",L36="Good"),"Very Low", IF(AND(J36="Medium",L36="Fair"),"Low", IF(AND(J36="Medium",L36="Poor"),"Medium", IF(AND(J36="Medium",L36="Unsatisfactory"),"Medium", IF(AND(J36="Low",L36="Excellent"),"Very Low", IF(AND(J36="Low",L36="Good"),"Very Low", IF(AND(J36="Low",L36="Fair"),"Very Low", IF(AND(J36="Low",L36="Poor"),"Low", IF(AND(J36="Low",L36="Unsatisfactory"),"Low", IF(AND(J36="Very Low",L36="Excellent"),"Very Low", IF(AND(J36="Very Low",L36="Good"),"Very Low", IF(AND(J36="Very Low",L36="Fair"),"Very Low", IF(AND(J36="Very Low",L36="Poor"),"Very Low", IF(AND(J36="Very Low",L36="Unsatisfactory"),"Very Low","")))))))))))))))))))))))))) -> Low | S36: =IF(OR(L36="",R36=""),"",IF(AND(L36="Very High",R36="Excellent"),"Low",IF(AND(L36="Very High",R36="Good"),"Medium",IF(AND(L36="Very High",R36="Fair"),"High",IF(AND(L36="Very High",R36="Poor"),"Very High",IF(AND(L36="Very High",R36="Unsatisfactory"),"Very High",IF(AND(L36="High",R36="Excellent"),"Low",IF(AND(L36="High",R36="Good"),"Low",IF(AND(L36="High",R36="Fair"),"Medium",IF(AND(L36="High",R36="Poor"),"High",IF(AND(L36="High",R36="Unsatisfactory"),"High",IF(AND(L36="Medium",R36="Excellent"),"Low",IF(AND(L36="Medium",R36="Good"),"Low",IF(AND(L36="Medium",R36="Fair"),"Low",IF(AND(L36="Medium",R36="Poor"),"Medium",IF(AND(L36="Medium",R36="Unsatisfactory"),"Medium",IF(AND(L36="Low",R36="Excellent"),"Very Low",IF(AND(L36="Low",R36="Good"),"Low",IF(AND(L36="Low",R36="Fair"),"Low",IF(AND(L36="Low",R36="Poor"),"Low",IF(AND(L36="Low",R36="Unsatisfactory"),"Low",IF(AND(L36="Very Low",R36="Excellent"),"Very Low",IF(AND(L36="Very Low",R36="Good"),"Very Low",IF(AND(L36="Very Low",R36="Fair"),"Very Low",IF(AND(L36="Very Low",R36="Poor"),"Very Low",IF(AND(L36="Very Low",R36="Unsatisfactory"),"Very Low","Low"))))))))))))))))))))))))))
A37: PAY-005 | B37: Process | C37: Onboarding of Non-Legitimate Business - Online Onboarding Request (PAY) | D37: Pay Operations | E37: Risk of onboarding merchants without confirming legitimacy of their business | F37: Likely | G37: Major | H37: =IF(F37='Risk Methedology Matrix'!B$26,5,IF(F37='Risk Methedology Matrix'!B$27,4,IF(F37='Risk Methedology Matrix'!B$28,3,IF(F37='Risk Methedology Matrix'!B$29,2,IF(F37='Risk Methedology Matrix'!B$30,1,0))))) -> 4 | I37: =IF(G37='Risk Methedology Matrix'!G$25,5,IF(G37='Risk Methedology Matrix'!F$25,4,IF(G37='Risk Methedology Matrix'!E$25,3,IF(G37='Risk Methedology Matrix'!D$25,2,IF(G37='Risk Methedology Matrix'!C$25,1,0))))) -> 4 | J37: =IF(OR(F37="",G37=""),"",IF(H37*I37>=20,"Very High",IF(AND(H37*I37<20,H37*I37>=11),"High",IF(AND(H37*I37<11,H37*I37>=6),"Medium",IF(AND(H37*I37<6,H37*I37>=3),"Low",IF(AND(H37*I37<3,H37*I37>=1),"Very Low","")))))) -> High | K37: Requirement of branch photo to prove legitimacy; automatic rejection and notification if validation fails | L37: Good | M37: =IF(OR(J37="",L37=""),"", IF(AND(J37="Very High",L37="Excellent"),"Low", IF(AND(J37="Very High",L37="Good"),"Medium", IF(AND(J37="Very High",L37="Fair"),"High", IF(AND(J37="Very High",L37="Poor"),"Very High", IF(AND(J37="Very High",L37="Unsatisfactory"),"Very High", IF(AND(J37="High",L37="Excellent"),"Very Low", IF(AND(J37="High",L37="Good"),"Low", IF(AND(J37="High",L37="Fair"),"Medium", IF(AND(J37="High",L37="Poor"),"High", IF(AND(J37="High",L37="Unsatisfactory"),"High", IF(AND(J37="Medium",L37="Excellent"),"Very Low", IF(AND(J37="Medium",L37="Good"),"Very Low", IF(AND(J37="Medium",L37="Fair"),"Low", IF(AND(J37="Medium",L37="Poor"),"Medium", IF(AND(J37="Medium",L37="Unsatisfactory"),"Medium", IF(AND(J37="Low",L37="Excellent"),"Very Low", IF(AND(J37="Low",L37="Good"),"Very Low", IF(AND(J37="Low",L37="Fair"),"Very Low", IF(AND(J37="Low",L37="Poor"),"Low", IF(AND(J37="Low",L37="Unsatisfactory"),"Low", IF(AND(J37="Very Low",L37="Excellent"),"Very Low", IF(AND(J37="Very Low",L37="Good"),"Very Low", IF(AND(J37="Very Low",L37="Fair"),"Very Low", IF(AND(J37="Very Low",L37="Poor"),"Very Low", IF(AND(J37="Very Low",L37="Unsatisfactory"),"Very Low","")))))))))))))))))))))))))) -> Low | S37: =IF(OR(L37="",R37=""),"",IF(AND(L37="Very High",R37="Excellent"),"Low",IF(AND(L37="Very High",R37="Good"),"Medium",IF(AND(L37="Very High",R37="Fair"),"High",IF(AND(L37="Very High",R37="Poor"),"Very High",IF(AND(L37="Very High",R37="Unsatisfactory"),"Very High",IF(AND(L37="High",R37="Excellent"),"Low",IF(AND(L37="High",R37="Good"),"Low",IF(AND(L37="High",R37="Fair"),"Medium",IF(AND(L37="High",R37="Poor"),"High",IF(AND(L37="High",R37="Unsatisfactory"),"High",IF(AND(L37="Medium",R37="Excellent"),"Low",IF(AND(L37="Medium",R37="Good"),"Low",IF(AND(L37="Medium",R37="Fair"),"Low",IF(AND(L37="Medium",R37="Poor"),"Medium",IF(AND(L37="Medium",R37="Unsatisfactory"),"Medium",IF(AND(L37="Low",R37="Excellent"),"Very Low",IF(AND(L37="Low",R37="Good"),"Low",IF(AND(L37="Low",R37="Fair"),"Low",IF(AND(L37="Low",R37="Poor"),"Low",IF(AND(L37="Low",R37="Unsatisfactory"),"Low",IF(AND(L37="Very Low",R37="Excellent"),"Very Low",IF(AND(L37="Very Low",R37="Good"),"Very Low",IF(AND(L37="Very Low",R37="Fair"),"Very Low",IF(AND(L37="Very Low",R37="Poor"),"Very Low",IF(AND(L37="Very Low",R37="Unsatisfactory"),"Very Low","Low"))))))))))))))))))))))))))
A38: PAY-006 | B38: Process | C38: Unauthorized or Uncontrolled Agreement Execution - Online Onboarding Request (PAY) | D38: Pay Operations | E38: Risk of sending or executing Pay agreements without proper documentation or recordkeeping | F38: Likely | G38: Major | H38: =IF(F38='Risk Methedology Matrix'!B$26,5,IF(F38='Risk Methedology Matrix'!B$27,4,IF(F38='Risk Methedology Matrix'!B$28,3,IF(F38='Risk Methedology Matrix'!B$29,2,IF(F38='Risk Methedology Matrix'!B$30,1,0))))) -> 4 | I38: =IF(G38='Risk Methedology Matrix'!G$25,5,IF(G38='Risk Methedology Matrix'!F$25,4,IF(G38='Risk Methedology Matrix'!E$25,3,IF(G38='Risk Methedology Matrix'!D$25,2,IF(G38='Risk Methedology Matrix'!C$25,1,0))))) -> 4 | J38: =IF(OR(F38="",G38=""),"",IF(H38*I38>=20,"Very High",IF(AND(H38*I38<20,H38*I38>=11),"High",IF(AND(H38*I38<11,H38*I38>=6),"Medium",IF(AND(H38*I38<6,H38*I38>=3),"Low",IF(AND(H38*I38<3,H38*I38>=1),"Very Low","")))))) -> High | K38: Pay agreement is sent to the merchant and securely saved in the Pay MMS merchant account | L38: Good | M38: =IF(OR(J38="",L38=""),"", IF(AND(J38="Very High",L38="Excellent"),"Low", IF(AND(J38="Very High",L38="Good"),"Medium", IF(AND(J38="Very High",L38="Fair"),"High", IF(AND(J38="Very High",L38="Poor"),"Very High", IF(AND(J38="Very High",L38="Unsatisfactory"),"Very High", IF(AND(J38="High",L38="Excellent"),"Very Low", IF(AND(J38="High",L38="Good"),"Low", IF(AND(J38="High",L38="Fair"),"Medium", IF(AND(J38="High",L38="Poor"),"High", IF(AND(J38="High",L38="Unsatisfactory"),"High", IF(AND(J38="Medium",L38="Excellent"),"Very Low", IF(AND(J38="Medium",L38="Good"),"Very Low", IF(AND(J38="Medium",L38="Fair"),"Low", IF(AND(J38="Medium",L38="Poor"),"Medium", IF(AND(J38="Medium",L38="Unsatisfactory"),"Medium", IF(AND(J38="Low",L38="Excellent"),"Very Low", IF(AND(J38="Low",L38="Good"),"Very Low", IF(AND(J38="Low",L38="Fair"),"Very Low", IF(AND(J38="Low",L38="Poor"),"Low", IF(AND(J38="Low",L38="Unsatisfactory"),"Low", IF(AND(J38="Very Low",L38="Excellent"),"Very Low", IF(AND(J38="Very Low",L38="Good"),"Very Low", IF(AND(J38="Very Low",L38="Fair"),"Very Low", IF(AND(J38="Very Low",L38="Poor"),"Very Low", IF(AND(J38="Very Low",L38="Unsatisfactory"),"Very Low","")))))))))))))))))))))))))) -> Low | S38: =IF(OR(L38="",R38=""),"",IF(AND(L38="Very High",R38="Excellent"),"Low",IF(AND(L38="Very High",R38="Good"),"Medium",IF(AND(L38="Very High",R38="Fair"),"High",IF(AND(L38="Very High",R38="Poor"),"Very High",IF(AND(L38="Very High",R38="Unsatisfactory"),"Very High",IF(AND(L38="High",R38="Excellent"),"Low",IF(AND(L38="High",R38="Good"),"Low",IF(AND(L38="High",R38="Fair"),"Medium",IF(AND(L38="High",R38="Poor"),"High",IF(AND(L38="High",R38="Unsatisfactory"),"High",IF(AND(L38="Medium",R38="Excellent"),"Low",IF(AND(L38="Medium",R38="Good"),"Low",IF(AND(L38="Medium",R38="Fair"),"Low",IF(AND(L38="Medium",R38="Poor"),"Medium",IF(AND(L38="Medium",R38="Unsatisfactory"),"Medium",IF(AND(L38="Low",R38="Excellent"),"Very Low",IF(AND(L38="Low",R38="Good"),"Low",IF(AND(L38="Low",R38="Fair"),"Low",IF(AND(L38="Low",R38="Poor"),"Low",IF(AND(L38="Low",R38="Unsatisfactory"),"Low",IF(AND(L38="Very Low",R38="Excellent"),"Very Low",IF(AND(L38="Very Low",R38="Good"),"Very Low",IF(AND(L38="Very Low",R38="Fair"),"Very Low",IF(AND(L38="Very Low",R38="Poor"),"Very Low",IF(AND(L38="Very Low",R38="Unsatisfactory"),"Very Low","Low"))))))))))))))))))))))))))
A39: PAY-007 | B39: Process | C39: Delay or Failure in Completing Onboarding and Installation - Online Onboarding Request (PAY) | D39: Pay Operations | E39: Risk of delay in merchant onboarding due to incomplete validation or communication failure | F39: Likely | G39: Major | H39: =IF(F39='Risk Methedology Matrix'!B$26,5,IF(F39='Risk Methedology Matrix'!B$27,4,IF(F39='Risk Methedology Matrix'!B$28,3,IF(F39='Risk Methedology Matrix'!B$29,2,IF(F39='Risk Methedology Matrix'!B$30,1,0))))) -> 4 | I39: =IF(G39='Risk Methedology Matrix'!G$25,5,IF(G39='Risk Methedology Matrix'!F$25,4,IF(G39='Risk Methedology Matrix'!E$25,3,IF(G39='Risk Methedology Matrix'!D$25,2,IF(G39='Risk Methedology Matrix'!C$25,1,0))))) -> 4 | J39: =IF(OR(F39="",G39=""),"",IF(H39*I39>=20,"Very High",IF(AND(H39*I39<20,H39*I39>=11),"High",IF(AND(H39*I39<11,H39*I39>=6),"Medium",IF(AND(H39*I39<6,H39*I39>=3),"Low",IF(AND(H39*I39<3,H39*I39>=1),"Very Low","")))))) -> High | K39: Email notifications to Pay Ops team upon onboarding request; auto-rejection of incomplete applications with email/SMS alerts to merchants | L39: Good | M39: =IF(OR(J39="",L39=""),"", IF(AND(J39="Very High",L39="Excellent"),"Low", IF(AND(J39="Very High",L39="Good"),"Medium", IF(AND(J39="Very High",L39="Fair"),"High", IF(AND(J39="Very High",L39="Poor"),"Very High", IF(AND(J39="Very High",L39="Unsatisfactory"),"Very High", IF(AND(J39="High",L39="Excellent"),"Very Low", IF(AND(J39="High",L39="Good"),"Low", IF(AND(J39="High",L39="Fair"),"Medium", IF(AND(J39="High",L39="Poor"),"High", IF(AND(J39="High",L39="Unsatisfactory"),"High", IF(AND(J39="Medium",L39="Excellent"),"Very Low", IF(AND(J39="Medium",L39="Good"),"Very Low", IF(AND(J39="Medium",L39="Fair"),"Low", IF(AND(J39="Medium",L39="Poor"),"Medium", IF(AND(J39="Medium",L39="Unsatisfactory"),"Medium", IF(AND(J39="Low",L39="Excellent"),"Very Low", IF(AND(J39="Low",L39="Good"),"Very Low", IF(AND(J39="Low",L39="Fair"),"Very Low", IF(AND(J39="Low",L39="Poor"),"Low", IF(AND(J39="Low",L39="Unsatisfactory"),"Low", IF(AND(J39="Very Low",L39="Excellent"),"Very Low", IF(AND(J39="Very Low",L39="Good"),"Very Low", IF(AND(J39="Very Low",L39="Fair"),"Very Low", IF(AND(J39="Very Low",L39="Poor"),"Very Low", IF(AND(J39="Very Low",L39="Unsatisfactory"),"Very Low","")))))))))))))))))))))))))) -> Low | S39: =IF(OR(L39="",R39=""),"",IF(AND(L39="Very High",R39="Excellent"),"Low",IF(AND(L39="Very High",R39="Good"),"Medium",IF(AND(L39="Very High",R39="Fair"),"High",IF(AND(L39="Very High",R39="Poor"),"Very High",IF(AND(L39="Very High",R39="Unsatisfactory"),"Very High",IF(AND(L39="High",R39="Excellent"),"Low",IF(AND(L39="High",R39="Good"),"Low",IF(AND(L39="High",R39="Fair"),"Medium",IF(AND(L39="High",R39="Poor"),"High",IF(AND(L39="High",R39="Unsatisfactory"),"High",IF(AND(L39="Medium",R39="Excellent"),"Low",IF(AND(L39="Medium",R39="Good"),"Low",IF(AND(L39="Medium",R39="Fair"),"Low",IF(AND(L39="Medium",R39="Poor"),"Medium",IF(AND(L39="Medium",R39="Unsatisfactory"),"Medium",IF(AND(L39="Low",R39="Excellent"),"Very Low",IF(AND(L39="Low",R39="Good"),"Low",IF(AND(L39="Low",R39="Fair"),"Low",IF(AND(L39="Low",R39="Poor"),"Low",IF(AND(L39="Low",R39="Unsatisfactory"),"Low",IF(AND(L39="Very Low",R39="Excellent"),"Very Low",IF(AND(L39="Very Low",R39="Good"),"Very Low",IF(AND(L39="Very Low",R39="Fair"),"Very Low",IF(AND(L39="Very Low",R39="Poor"),"Very Low",IF(AND(L39="Very Low",R39="Unsatisfactory"),"Very Low","Low"))))))))))))))))))))))))))
A40: PAY-008 | B40: Process | C40: Incomplete Merchant Validation - Online Onboarding Request (Online) | D40: Pay Operations | E40: Onboarding may proceed without fully validating merchant documents (CR, National ID, IBAN, CRM details), leading to compliance or operational issues. | F40: Likely | G40: Major | H40: =IF(F40='Risk Methedology Matrix'!B$26,5,IF(F40='Risk Methedology Matrix'!B$27,4,IF(F40='Risk Methedology Matrix'!B$28,3,IF(F40='Risk Methedology Matrix'!B$29,2,IF(F40='Risk Methedology Matrix'!B$30,1,0))))) -> 4 | I40: =IF(G40='Risk Methedology Matrix'!G$25,5,IF(G40='Risk Methedology Matrix'!F$25,4,IF(G40='Risk Methedology Matrix'!E$25,3,IF(G40='Risk Methedology Matrix'!D$25,2,IF(G40='Risk Methedology Matrix'!C$25,1,0))))) -> 4 | J40: =IF(OR(F40="",G40=""),"",IF(H40*I40>=20,"Very High",IF(AND(H40*I40<20,H40*I40>=11),"High",IF(AND(H40*I40<11,H40*I40>=6),"Medium",IF(AND(H40*I40<6,H40*I40>=3),"Low",IF(AND(H40*I40<3,H40*I40>=1),"Very Low","")))))) -> High | K40: Information validator checks CR name, National ID, IBAN certificate, CRM opportunity fields, and branch photo to validate request before approval. | L40: Good | M40: =IF(OR(J40="",L40=""),"", IF(AND(J40="Very High",L40="Excellent"),"Low", IF(AND(J40="Very High",L40="Good"),"Medium", IF(AND(J40="Very High",L40="Fair"),"High", IF(AND(J40="Very High",L40="Poor"),"Very High", IF(AND(J40="Very High",L40="Unsatisfactory"),"Very High", IF(AND(J40="High",L40="Excellent"),"Very Low", IF(AND(J40="High",L40="Good"),"Low", IF(AND(J40="High",L40="Fair"),"Medium", IF(AND(J40="High",L40="Poor"),"High", IF(AND(J40="High",L40="Unsatisfactory"),"High", IF(AND(J40="Medium",L40="Excellent"),"Very Low", IF(AND(J40="Medium",L40="Good"),"Very Low", IF(AND(J40="Medium",L40="Fair"),"Low", IF(AND(J40="Medium",L40="Poor"),"Medium", IF(AND(J40="Medium",L40="Unsatisfactory"),"Medium", IF(AND(J40="Low",L40="Excellent"),"Very Low", IF(AND(J40="Low",L40="Good"),"Very Low", IF(AND(J40="Low",L40="Fair"),"Very Low", IF(AND(J40="Low",L40="Poor"),"Low", IF(AND(J40="Low",L40="Unsatisfactory"),"Low", IF(AND(J40="Very Low",L40="Excellent"),"Very Low", IF(AND(J40="Very Low",L40="Good"),"Very Low", IF(AND(J40="Very Low",L40="Fair"),"Very Low", IF(AND(J40="Very Low",L40="Poor"),"Very Low", IF(AND(J40="Very Low",L40="Unsatisfactory"),"Very Low","")))))))))))))))))))))))))) -> Low | S40: =IF(OR(L40="",R40=""),"",IF(AND(L40="Very High",R40="Excellent"),"Low",IF(AND(L40="Very High",R40="Good"),"Medium",IF(AND(L40="Very High",R40="Fair"),"High",IF(AND(L40="Very High",R40="Poor"),"Very High",IF(AND(L40="Very High",R40="Unsatisfactory"),"Very High",IF(AND(L40="High",R40="Excellent"),"Low",IF(AND(L40="High",R40="Good"),"Low",IF(AND(L40="High",R40="Fair"),"Medium",IF(AND(L40="High",R40="Poor"),"High",IF(AND(L40="High",R40="Unsatisfactory"),"High",IF(AND(L40="Medium",R40="Excellent"),"Low",IF(AND(L40="Medium",R40="Good"),"Low",IF(AND(L40="Medium",R40="Fair"),"Low",IF(AND(L40="Medium",R40="Poor"),"Medium",IF(AND(L40="Medium",R40="Unsatisfactory"),"Medium",IF(AND(L40="Low",R40="Excellent"),"Very Low",IF(AND(L40="Low",R40="Good"),"Low",IF(AND(L40="Low",R40="Fair"),"Low",IF(AND(L40="Low",R40="Poor"),"Low",IF(AND(L40="Low",R40="Unsatisfactory"),"Low",IF(AND(L40="Very Low",R40="Excellent"),"Very Low",IF(AND(L40="Very Low",R40="Good"),"Very Low",IF(AND(L40="Very Low",R40="Fair"),"Very Low",IF(AND(L40="Very Low",R40="Poor"),"Very Low",IF(AND(L40="Very Low",R40="Unsatisfactory"),"Very Low","Low"))))))))))))))))))))))))))
A41: PAY-009 | B41: System | C41: Failure to Notify Rejection to Merchant - Online Onboarding Request (Online) | D41: Pay Operations | E41: Failure in notifying rejected merchants could result in customer dissatisfaction or miscommunication. | F41: Likely | G41: Major | H41: =IF(F41='Risk Methedology Matrix'!B$26,5,IF(F41='Risk Methedology Matrix'!B$27,4,IF(F41='Risk Methedology Matrix'!B$28,3,IF(F41='Risk Methedology Matrix'!B$29,2,IF(F41='Risk Methedology Matrix'!B$30,1,0))))) -> 4 | I41: =IF(G41='Risk Methedology Matrix'!G$25,5,IF(G41='Risk Methedology Matrix'!F$25,4,IF(G41='Risk Methedology Matrix'!E$25,3,IF(G41='Risk Methedology Matrix'!D$25,2,IF(G41='Risk Methedology Matrix'!C$25,1,0))))) -> 4 | J41: =IF(OR(F41="",G41=""),"",IF(H41*I41>=20,"Very High",IF(AND(H41*I41<20,H41*I41>=11),"High",IF(AND(H41*I41<11,H41*I41>=6),"Medium",IF(AND(H41*I41<6,H41*I41>=3),"Low",IF(AND(H41*I41<3,H41*I41>=1),"Very Low","")))))) -> High | K41: Rejected merchants are notified automatically via email and SMS. | L41: Good | M41: =IF(OR(J41="",L41=""),"", IF(AND(J41="Very High",L41="Excellent"),"Low", IF(AND(J41="Very High",L41="Good"),"Medium", IF(AND(J41="Very High",L41="Fair"),"High", IF(AND(J41="Very High",L41="Poor"),"Very High", IF(AND(J41="Very High",L41="Unsatisfactory"),"Very High", IF(AND(J41="High",L41="Excellent"),"Very Low", IF(AND(J41="High",L41="Good"),"Low", IF(AND(J41="High",L41="Fair"),"Medium", IF(AND(J41="High",L41="Poor"),"High", IF(AND(J41="High",L41="Unsatisfactory"),"High", IF(AND(J41="Medium",L41="Excellent"),"Very Low", IF(AND(J41="Medium",L41="Good"),"Very Low", IF(AND(J41="Medium",L41="Fair"),"Low", IF(AND(J41="Medium",L41="Poor"),"Medium", IF(AND(J41="Medium",L41="Unsatisfactory"),"Medium", IF(AND(J41="Low",L41="Excellent"),"Very Low", IF(AND(J41="Low",L41="Good"),"Very Low", IF(AND(J41="Low",L41="Fair"),"Very Low", IF(AND(J41="Low",L41="Poor"),"Low", IF(AND(J41="Low",L41="Unsatisfactory"),"Low", IF(AND(J41="Very Low",L41="Excellent"),"Very Low", IF(AND(J41="Very Low",L41="Good"),"Very Low", IF(AND(J41="Very Low",L41="Fair"),"Very Low", IF(AND(J41="Very Low",L41="Poor"),"Very Low", IF(AND(J41="Very Low",L41="Unsatisfactory"),"Very Low","")))))))))))))))))))))))))) -> Low | S41: =IF(OR(L41="",R41=""),"",IF(AND(L41="Very High",R41="Excellent"),"Low",IF(AND(L41="Very High",R41="Good"),"Medium",IF(AND(L41="Very High",R41="Fair"),"High",IF(AND(L41="Very High",R41="Poor"),"Very High",IF(AND(L41="Very High",R41="Unsatisfactory"),"Very High",IF(AND(L41="High",R41="Excellent"),"Low",IF(AND(L41="High",R41="Good"),"Low",IF(AND(L41="High",R41="Fair"),"Medium",IF(AND(L41="High",R41="Poor"),"High",IF(AND(L41="High",R41="Unsatisfactory"),"High",IF(AND(L41="Medium",R41="Excellent"),"Low",IF(AND(L41="Medium",R41="Good"),"Low",IF(AND(L41="Medium",R41="Fair"),"Low",IF(AND(L41="Medium",R41="Poor"),"Medium",IF(AND(L41="Medium",R41="Unsatisfactory"),"Medium",IF(AND(L41="Low",R41="Excellent"),"Very Low",IF(AND(L41="Low",R41="Good"),"Low",IF(AND(L41="Low",R41="Fair"),"Low",IF(AND(L41="Low",R41="Poor"),"Low",IF(AND(L41="Low",R41="Unsatisfactory"),"Low",IF(AND(L41="Very Low",R41="Excellent"),"Very Low",IF(AND(L41="Very Low",R41="Good"),"Very Low",IF(AND(L41="Very Low",R41="Fair"),"Very Low",IF(AND(L41="Very Low",R41="Poor"),"Very Low",IF(AND(L41="Very Low",R41="Unsatisfactory"),"Very Low","Low"))))))))))))))))))))))))))
A42: PAY-010 | B42: System | C42: Unauthorized or Premature TID Generation - Online Onboarding Request (Online) | D42: Pay Operations | E42: Generating virtual TID before proper validation could allow unauthorized access to services. | F42: Likely | G42: Major | H42: =IF(F42='Risk Methedology Matrix'!B$26,5,IF(F42='Risk Methedology Matrix'!B$27,4,IF(F42='Risk Methedology Matrix'!B$28,3,IF(F42='Risk Methedology Matrix'!B$29,2,IF(F42='Risk Methedology Matrix'!B$30,1,0))))) -> 4 | I42: =IF(G42='Risk Methedology Matrix'!G$25,5,IF(G42='Risk Methedology Matrix'!F$25,4,IF(G42='Risk Methedology Matrix'!E$25,3,IF(G42='Risk Methedology Matrix'!D$25,2,IF(G42='Risk Methedology Matrix'!C$25,1,0))))) -> 4 | J42: =IF(OR(F42="",G42=""),"",IF(H42*I42>=20,"Very High",IF(AND(H42*I42<20,H42*I42>=11),"High",IF(AND(H42*I42<11,H42*I42>=6),"Medium",IF(AND(H42*I42<6,H42*I42>=3),"Low",IF(AND(H42*I42<3,H42*I42>=1),"Very Low","")))))) -> High | K42: TID creation is automated only after request is approved post validation. | L42: Good | M42: =IF(OR(J42="",L42=""),"", IF(AND(J42="Very High",L42="Excellent"),"Low", IF(AND(J42="Very High",L42="Good"),"Medium", IF(AND(J42="Very High",L42="Fair"),"High", IF(AND(J42="Very High",L42="Poor"),"Very High", IF(AND(J42="Very High",L42="Unsatisfactory"),"Very High", IF(AND(J42="High",L42="Excellent"),"Very Low", IF(AND(J42="High",L42="Good"),"Low", IF(AND(J42="High",L42="Fair"),"Medium", IF(AND(J42="High",L42="Poor"),"High", IF(AND(J42="High",L42="Unsatisfactory"),"High", IF(AND(J42="Medium",L42="Excellent"),"Very Low", IF(AND(J42="Medium",L42="Good"),"Very Low", IF(AND(J42="Medium",L42="Fair"),"Low", IF(AND(J42="Medium",L42="Poor"),"Medium", IF(AND(J42="Medium",L42="Unsatisfactory"),"Medium", IF(AND(J42="Low",L42="Excellent"),"Very Low", IF(AND(J42="Low",L42="Good"),"Very Low", IF(AND(J42="Low",L42="Fair"),"Very Low", IF(AND(J42="Low",L42="Poor"),"Low", IF(AND(J42="Low",L42="Unsatisfactory"),"Low", IF(AND(J42="Very Low",L42="Excellent"),"Very Low", IF(AND(J42="Very Low",L42="Good"),"Very Low", IF(AND(J42="Very Low",L42="Fair"),"Very Low", IF(AND(J42="Very Low",L42="Poor"),"Very Low", IF(AND(J42="Very Low",L42="Unsatisfactory"),"Very Low","")))))))))))))))))))))))))) -> Low | S42: =IF(OR(L42="",R42=""),"",IF(AND(L42="Very High",R42="Excellent"),"Low",IF(AND(L42="Very High",R42="Good"),"Medium",IF(AND(L42="Very High",R42="Fair"),"High",IF(AND(L42="Very High",R42="Poor"),"Very High",IF(AND(L42="Very High",R42="Unsatisfactory"),"Very High",IF(AND(L42="High",R42="Excellent"),"Low",IF(AND(L42="High",R42="Good"),"Low",IF(AND(L42="High",R42="Fair"),"Medium",IF(AND(L42="High",R42="Poor"),"High",IF(AND(L42="High",R42="Unsatisfactory"),"High",IF(AND(L42="Medium",R42="Excellent"),"Low",IF(AND(L42="Medium",R42="Good"),"Low",IF(AND(L42="Medium",R42="Fair"),"Low",IF(AND(L42="Medium",R42="Poor"),"Medium",IF(AND(L42="Medium",R42="Unsatisfactory"),"Medium",IF(AND(L42="Low",R42="Excellent"),"Very Low",IF(AND(L42="Low",R42="Good"),"Low",IF(AND(L42="Low",R42="Fair"),"Low",IF(AND(L42="Low",R42="Poor"),"Low",IF(AND(L42="Low",R42="Unsatisfactory"),"Low",IF(AND(L42="Very Low",R42="Excellent"),"Very Low",IF(AND(L42="Very Low",R42="Good"),"Very Low",IF(AND(L42="Very Low",R42="Fair"),"Very Low",IF(AND(L42="Very Low",R42="Poor"),"Very Low",IF(AND(L42="Very Low",R42="Unsatisfactory"),"Very Low","Low"))))))))))))))))))))))))))
A43: PAY-011 | B43: Process | C43: Operational Delay in Pay Ops Notification - Online Onboarding Request (Online) | D43: Pay Operations | E43: Delay or failure in notifying Pay Ops about onboarding requests could cause process bottlenecks and SLA breaches. | F43: Likely | G43: Major | H43: =IF(F43='Risk Methedology Matrix'!B$26,5,IF(F43='Risk Methedology Matrix'!B$27,4,IF(F43='Risk Methedology Matrix'!B$28,3,IF(F43='Risk Methedology Matrix'!B$29,2,IF(F43='Risk Methedology Matrix'!B$30,1,0))))) -> 4 | I43: =IF(G43='Risk Methedology Matrix'!G$25,5,IF(G43='Risk Methedology Matrix'!F$25,4,IF(G43='Risk Methedology Matrix'!E$25,3,IF(G43='Risk Methedology Matrix'!D$25,2,IF(G43='Risk Methedology Matrix'!C$25,1,0))))) -> 4 | J43: =IF(OR(F43="",G43=""),"",IF(H43*I43>=20,"Very High",IF(AND(H43*I43<20,H43*I43>=11),"High",IF(AND(H43*I43<11,H43*I43>=6),"Medium",IF(AND(H43*I43<6,H43*I43>=3),"Low",IF(AND(H43*I43<3,H43*I43>=1),"Very Low","")))))) -> High | K43: Pay Ops team is notified via email once the merchant request is pending, ensuring timely processing. | L43: Good | M43: =IF(OR(J43="",L43=""),"", IF(AND(J43="Very High",L43="Excellent"),"Low", IF(AND(J43="Very High",L43="Good"),"Medium", IF(AND(J43="Very High",L43="Fair"),"High", IF(AND(J43="Very High",L43="Poor"),"Very High", IF(AND(J43="Very High",L43="Unsatisfactory"),"Very High", IF(AND(J43="High",L43="Excellent"),"Very Low", IF(AND(J43="High",L43="Good"),"Low", IF(AND(J43="High",L43="Fair"),"Medium", IF(AND(J43="High",L43="Poor"),"High", IF(AND(J43="High",L43="Unsatisfactory"),"High", IF(AND(J43="Medium",L43="Excellent"),"Very Low", IF(AND(J43="Medium",L43="Good"),"Very Low", IF(AND(J43="Medium",L43="Fair"),"Low", IF(AND(J43="Medium",L43="Poor"),"Medium", IF(AND(J43="Medium",L43="Unsatisfactory"),"Medium", IF(AND(J43="Low",L43="Excellent"),"Very Low", IF(AND(J43="Low",L43="Good"),"Very Low", IF(AND(J43="Low",L43="Fair"),"Very Low", IF(AND(J43="Low",L43="Poor"),"Low", IF(AND(J43="Low",L43="Unsatisfactory"),"Low", IF(AND(J43="Very Low",L43="Excellent"),"Very Low", IF(AND(J43="Very Low",L43="Good"),"Very Low", IF(AND(J43="Very Low",L43="Fair"),"Very Low", IF(AND(J43="Very Low",L43="Poor"),"Very Low", IF(AND(J43="Very Low",L43="Unsatisfactory"),"Very Low","")))))))))))))))))))))))))) -> Low | S43: =IF(OR(L43="",R43=""),"",IF(AND(L43="Very High",R43="Excellent"),"Low",IF(AND(L43="Very High",R43="Good"),"Medium",IF(AND(L43="Very High",R43="Fair"),"High",IF(AND(L43="Very High",R43="Poor"),"Very High",IF(AND(L43="Very High",R43="Unsatisfactory"),"Very High",IF(AND(L43="High",R43="Excellent"),"Low",IF(AND(L43="High",R43="Good"),"Low",IF(AND(L43="High",R43="Fair"),"Medium",IF(AND(L43="High",R43="Poor"),"High",IF(AND(L43="High",R43="Unsatisfactory"),"High",IF(AND(L43="Medium",R43="Excellent"),"Low",IF(AND(L43="Medium",R43="Good"),"Low",IF(AND(L43="Medium",R43="Fair"),"Low",IF(AND(L43="Medium",R43="Poor"),"Medium",IF(AND(L43="Medium",R43="Unsatisfactory"),"Medium",IF(AND(L43="Low",R43="Excellent"),"Very Low",IF(AND(L43="Low",R43="Good"),"Low",IF(AND(L43="Low",R43="Fair"),"Low",IF(AND(L43="Low",R43="Poor"),"Low",IF(AND(L43="Low",R43="Unsatisfactory"),"Low",IF(AND(L43="Very Low",R43="Excellent"),"Very Low",IF(AND(L43="Very Low",R43="Good"),"Very Low",IF(AND(L43="Very Low",R43="Fair"),"Very Low",IF(AND(L43="Very Low",R43="Poor"),"Very Low",IF(AND(L43="Very Low",R43="Unsatisfactory"),"Very Low","Low"))))))))))))))))))))))))))
A44: PAY-012 | B44: Process | C44: Improper Device Handling for E-commerce - Online Onboarding Request (Online) | D44: Pay Operations | E44: Assuming no physical device handling may result in confusion if mistakenly considered a POS merchant instead of e-commerce. | F44: Likely | G44: Major | H44: =IF(F44='Risk Methedology Matrix'!B$26,5,IF(F44='Risk Methedology Matrix'!B$27,4,IF(F44='Risk Methedology Matrix'!B$28,3,IF(F44='Risk Methedology Matrix'!B$29,2,IF(F44='Risk Methedology Matrix'!B$30,1,0))))) -> 4 | I44: =IF(G44='Risk Methedology Matrix'!G$25,5,IF(G44='Risk Methedology Matrix'!F$25,4,IF(G44='Risk Methedology Matrix'!E$25,3,IF(G44='Risk Methedology Matrix'!D$25,2,IF(G44='Risk Methedology Matrix'!C$25,1,0))))) -> 4 | J44: =IF(OR(F44="",G44=""),"",IF(H44*I44>=20,"Very High",IF(AND(H44*I44<20,H44*I44>=11),"High",IF(AND(H44*I44<11,H44*I44>=6),"Medium",IF(AND(H44*I44<6,H44*I44>=3),"Low",IF(AND(H44*I44<3,H44*I44>=1),"Very Low","")))))) -> High | K44: E-commerce merchants are not required to register or install physical devices—clearly defined process. | L44: Good | M44: =IF(OR(J44="",L44=""),"", IF(AND(J44="Very High",L44="Excellent"),"Low", IF(AND(J44="Very High",L44="Good"),"Medium", IF(AND(J44="Very High",L44="Fair"),"High", IF(AND(J44="Very High",L44="Poor"),"Very High", IF(AND(J44="Very High",L44="Unsatisfactory"),"Very High", IF(AND(J44="High",L44="Excellent"),"Very Low", IF(AND(J44="High",L44="Good"),"Low", IF(AND(J44="High",L44="Fair"),"Medium", IF(AND(J44="High",L44="Poor"),"High", IF(AND(J44="High",L44="Unsatisfactory"),"High", IF(AND(J44="Medium",L44="Excellent"),"Very Low", IF(AND(J44="Medium",L44="Good"),"Very Low", IF(AND(J44="Medium",L44="Fair"),"Low", IF(AND(J44="Medium",L44="Poor"),"Medium", IF(AND(J44="Medium",L44="Unsatisfactory"),"Medium", IF(AND(J44="Low",L44="Excellent"),"Very Low", IF(AND(J44="Low",L44="Good"),"Very Low", IF(AND(J44="Low",L44="Fair"),"Very Low", IF(AND(J44="Low",L44="Poor"),"Low", IF(AND(J44="Low",L44="Unsatisfactory"),"Low", IF(AND(J44="Very Low",L44="Excellent"),"Very Low", IF(AND(J44="Very Low",L44="Good"),"Very Low", IF(AND(J44="Very Low",L44="Fair"),"Very Low", IF(AND(J44="Very Low",L44="Poor"),"Very Low", IF(AND(J44="Very Low",L44="Unsatisfactory"),"Very Low","")))))))))))))))))))))))))) -> Low | S44: =IF(OR(L44="",R44=""),"",IF(AND(L44="Very High",R44="Excellent"),"Low",IF(AND(L44="Very High",R44="Good"),"Medium",IF(AND(L44="Very High",R44="Fair"),"High",IF(AND(L44="Very High",R44="Poor"),"Very High",IF(AND(L44="Very High",R44="Unsatisfactory"),"Very High",IF(AND(L44="High",R44="Excellent"),"Low",IF(AND(L44="High",R44="Good"),"Low",IF(AND(L44="High",R44="Fair"),"Medium",IF(AND(L44="High",R44="Poor"),"High",IF(AND(L44="High",R44="Unsatisfactory"),"High",IF(AND(L44="Medium",R44="Excellent"),"Low",IF(AND(L44="Medium",R44="Good"),"Low",IF(AND(L44="Medium",R44="Fair"),"Low",IF(AND(L44="Medium",R44="Poor"),"Medium",IF(AND(L44="Medium",R44="Unsatisfactory"),"Medium",IF(AND(L44="Low",R44="Excellent"),"Very Low",IF(AND(L44="Low",R44="Good"),"Low",IF(AND(L44="Low",R44="Fair"),"Low",IF(AND(L44="Low",R44="Poor"),"Low",IF(AND(L44="Low",R44="Unsatisfactory"),"Low",IF(AND(L44="Very Low",R44="Excellent"),"Very Low",IF(AND(L44="Very Low",R44="Good"),"Very Low",IF(AND(L44="Very Low",R44="Fair"),"Very Low",IF(AND(L44="Very Low",R44="Poor"),"Very Low",IF(AND(L44="Very Low",R44="Unsatisfactory"),"Very Low","Low"))))))))))))))))))))))))))
A45: PAY-013 | B45: Process | C45: Manual Onboarding Process Error - Manual Onboarding (PAY & Online) | D45: Pay Operations | E45: Manual onboarding may lead to errors, omissions, or delays compared to automated onboarding due to lack of system-driven validation. | F45: Likely | G45: Major | H45: =IF(F45='Risk Methedology Matrix'!B$26,5,IF(F45='Risk Methedology Matrix'!B$27,4,IF(F45='Risk Methedology Matrix'!B$28,3,IF(F45='Risk Methedology Matrix'!B$29,2,IF(F45='Risk Methedology Matrix'!B$30,1,0))))) -> 4 | I45: =IF(G45='Risk Methedology Matrix'!G$25,5,IF(G45='Risk Methedology Matrix'!F$25,4,IF(G45='Risk Methedology Matrix'!E$25,3,IF(G45='Risk Methedology Matrix'!D$25,2,IF(G45='Risk Methedology Matrix'!C$25,1,0))))) -> 4 | J45: =IF(OR(F45="",G45=""),"",IF(H45*I45>=20,"Very High",IF(AND(H45*I45<20,H45*I45>=11),"High",IF(AND(H45*I45<11,H45*I45>=6),"Medium",IF(AND(H45*I45<6,H45*I45>=3),"Low",IF(AND(H45*I45<3,H45*I45>=1),"Very Low","")))))) -> High | K45: Merchants are manually onboarded using Signit when technical issues prevent online onboarding. | L45: Good | M45: =IF(OR(J45="",L45=""),"", IF(AND(J45="Very High",L45="Excellent"),"Low", IF(AND(J45="Very High",L45="Good"),"Medium", IF(AND(J45="Very High",L45="Fair"),"High", IF(AND(J45="Very High",L45="Poor"),"Very High", IF(AND(J45="Very High",L45="Unsatisfactory"),"Very High", IF(AND(J45="High",L45="Excellent"),"Very Low", IF(AND(J45="High",L45="Good"),"Low", IF(AND(J45="High",L45="Fair"),"Medium", IF(AND(J45="High",L45="Poor"),"High", IF(AND(J45="High",L45="Unsatisfactory"),"High", IF(AND(J45="Medium",L45="Excellent"),"Very Low", IF(AND(J45="Medium",L45="Good"),"Very Low", IF(AND(J45="Medium",L45="Fair"),"Low", IF(AND(J45="Medium",L45="Poor"),"Medium", IF(AND(J45="Medium",L45="Unsatisfactory"),"Medium", IF(AND(J45="Low",L45="Excellent"),"Very Low", IF(AND(J45="Low",L45="Good"),"Very Low", IF(AND(J45="Low",L45="Fair"),"Very Low", IF(AND(J45="Low",L45="Poor"),"Low", IF(AND(J45="Low",L45="Unsatisfactory"),"Low", IF(AND(J45="Very Low",L45="Excellent"),"Very Low", IF(AND(J45="Very Low",L45="Good"),"Very Low", IF(AND(J45="Very Low",L45="Fair"),"Very Low", IF(AND(J45="Very Low",L45="Poor"),"Very Low", IF(AND(J45="Very Low",L45="Unsatisfactory"),"Very Low","")))))))))))))))))))))))))) -> Low | S45: =IF(OR(L45="",R45=""),"",IF(AND(L45="Very High",R45="Excellent"),"Low",IF(AND(L45="Very High",R45="Good"),"Medium",IF(AND(L45="Very High",R45="Fair"),"High",IF(AND(L45="Very High",R45="Poor"),"Very High",IF(AND(L45="Very High",R45="Unsatisfactory"),"Very High",IF(AND(L45="High",R45="Excellent"),"Low",IF(AND(L45="High",R45="Good"),"Low",IF(AND(L45="High",R45="Fair"),"Medium",IF(AND(L45="High",R45="Poor"),"High",IF(AND(L45="High",R45="Unsatisfactory"),"High",IF(AND(L45="Medium",R45="Excellent"),"Low",IF(AND(L45="Medium",R45="Good"),"Low",IF(AND(L45="Medium",R45="Fair"),"Low",IF(AND(L45="Medium",R45="Poor"),"Medium",IF(AND(L45="Medium",R45="Unsatisfactory"),"Medium",IF(AND(L45="Low",R45="Excellent"),"Very Low",IF(AND(L45="Low",R45="Good"),"Low",IF(AND(L45="Low",R45="Fair"),"Low",IF(AND(L45="Low",R45="Poor"),"Low",IF(AND(L45="Low",R45="Unsatisfactory"),"Low",IF(AND(L45="Very Low",R45="Excellent"),"Very Low",IF(AND(L45="Very Low",R45="Good"),"Very Low",IF(AND(L45="Very Low",R45="Fair"),"Very Low",IF(AND(L45="Very Low",R45="Poor"),"Very Low",IF(AND(L45="Very Low",R45="Unsatisfactory"),"Very Low","Low")))))))))))))))))))))))))) | U45: Completed | V45: Fully Automated
A46: PAY-014 | B46: System | C46: Sanction Screening Failure - Manual Onboarding (PAY & Online) | D46: Pay Operations | E46: Manually onboarded merchants may bypass key sanction screening steps, exposing the company to regulatory risks. | F46: Likely | G46: Major | H46: =IF(F46='Risk Methedology Matrix'!B$26,5,IF(F46='Risk Methedology Matrix'!B$27,4,IF(F46='Risk Methedology Matrix'!B$28,3,IF(F46='Risk Methedology Matrix'!B$29,2,IF(F46='Risk Methedology Matrix'!B$30,1,0))))) -> 4 | I46: =IF(G46='Risk Methedology Matrix'!G$25,5,IF(G46='Risk Methedology Matrix'!F$25,4,IF(G46='Risk Methedology Matrix'!E$25,3,IF(G46='Risk Methedology Matrix'!D$25,2,IF(G46='Risk Methedology Matrix'!C$25,1,0))))) -> 4 | J46: =IF(OR(F46="",G46=""),"",IF(H46*I46>=20,"Very High",IF(AND(H46*I46<20,H46*I46>=11),"High",IF(AND(H46*I46<11,H46*I46>=6),"Medium",IF(AND(H46*I46<6,H46*I46>=3),"Low",IF(AND(H46*I46<3,H46*I46>=1),"Very Low","")))))) -> High | K46: Sanction screening is conducted via Wathq, Nafath, and Focal integrations for all manually onboarded merchants. | L46: Good | M46: =IF(OR(J46="",L46=""),"", IF(AND(J46="Very High",L46="Excellent"),"Low", IF(AND(J46="Very High",L46="Good"),"Medium", IF(AND(J46="Very High",L46="Fair"),"High", IF(AND(J46="Very High",L46="Poor"),"Very High", IF(AND(J46="Very High",L46="Unsatisfactory"),"Very High", IF(AND(J46="High",L46="Excellent"),"Very Low", IF(AND(J46="High",L46="Good"),"Low", IF(AND(J46="High",L46="Fair"),"Medium", IF(AND(J46="High",L46="Poor"),"High", IF(AND(J46="High",L46="Unsatisfactory"),"High", IF(AND(J46="Medium",L46="Excellent"),"Very Low", IF(AND(J46="Medium",L46="Good"),"Very Low", IF(AND(J46="Medium",L46="Fair"),"Low", IF(AND(J46="Medium",L46="Poor"),"Medium", IF(AND(J46="Medium",L46="Unsatisfactory"),"Medium", IF(AND(J46="Low",L46="Excellent"),"Very Low", IF(AND(J46="Low",L46="Good"),"Very Low", IF(AND(J46="Low",L46="Fair"),"Very Low", IF(AND(J46="Low",L46="Poor"),"Low", IF(AND(J46="Low",L46="Unsatisfactory"),"Low", IF(AND(J46="Very Low",L46="Excellent"),"Very Low", IF(AND(J46="Very Low",L46="Good"),"Very Low", IF(AND(J46="Very Low",L46="Fair"),"Very Low", IF(AND(J46="Very Low",L46="Poor"),"Very Low", IF(AND(J46="Very Low",L46="Unsatisfactory"),"Very Low","")))))))))))))))))))))))))) -> Low | S46: =IF(OR(L46="",R46=""),"",IF(AND(L46="Very High",R46="Excellent"),"Low",IF(AND(L46="Very High",R46="Good"),"Medium",IF(AND(L46="Very High",R46="Fair"),"High",IF(AND(L46="Very High",R46="Poor"),"Very High",IF(AND(L46="Very High",R46="Unsatisfactory"),"Very High",IF(AND(L46="High",R46="Excellent"),"Low",IF(AND(L46="High",R46="Good"),"Low",IF(AND(L46="High",R46="Fair"),"Medium",IF(AND(L46="High",R46="Poor"),"High",IF(AND(L46="High",R46="Unsatisfactory"),"High",IF(AND(L46="Medium",R46="Excellent"),"Low",IF(AND(L46="Medium",R46="Good"),"Low",IF(AND(L46="Medium",R46="Fair"),"Low",IF(AND(L46="Medium",R46="Poor"),"Medium",IF(AND(L46="Medium",R46="Unsatisfactory"),"Medium",IF(AND(L46="Low",R46="Excellent"),"Very Low",IF(AND(L46="Low",R46="Good"),"Low",IF(AND(L46="Low",R46="Fair"),"Low",IF(AND(L46="Low",R46="Poor"),"Low",IF(AND(L46="Low",R46="Unsatisfactory"),"Low",IF(AND(L46="Very Low",R46="Excellent"),"Very Low",IF(AND(L46="Very Low",R46="Good"),"Very Low",IF(AND(L46="Very Low",R46="Fair"),"Very Low",IF(AND(L46="Very Low",R46="Poor"),"Very Low",IF(AND(L46="Very Low",R46="Unsatisfactory"),"Very Low","Low")))))))))))))))))))))))))) | U46: Completed | V46: Fully Automated
A47: PAY-015 | B47: System | C47: Premature Settlement Activation - Manual Onboarding (PAY & Online) | D47: Pay Operations | E47: Settlement may be enabled before completing identity verification, leading to potential regulatory violations or fraud. | F47: Likely | G47: Major | H47: =IF(F47='Risk Methedology Matrix'!B$26,5,IF(F47='Risk Methedology Matrix'!B$27,4,IF(F47='Risk Methedology Matrix'!B$28,3,IF(F47='Risk Methedology Matrix'!B$29,2,IF(F47='Risk Methedology Matrix'!B$30,1,0))))) -> 4 | I47: =IF(G47='Risk Methedology Matrix'!G$25,5,IF(G47='Risk Methedology Matrix'!F$25,4,IF(G47='Risk Methedology Matrix'!E$25,3,IF(G47='Risk Methedology Matrix'!D$25,2,IF(G47='Risk Methedology Matrix'!C$25,1,0))))) -> 4 | J47: =IF(OR(F47="",G47=""),"",IF(H47*I47>=20,"Very High",IF(AND(H47*I47<20,H47*I47>=11),"High",IF(AND(H47*I47<11,H47*I47>=6),"Medium",IF(AND(H47*I47<6,H47*I47>=3),"Low",IF(AND(H47*I47<3,H47*I47>=1),"Very Low","")))))) -> High | K47: Settlements are not enabled until the merchant completes Nafath verification. | L47: Good | M47: =IF(OR(J47="",L47=""),"", IF(AND(J47="Very High",L47="Excellent"),"Low", IF(AND(J47="Very High",L47="Good"),"Medium", IF(AND(J47="Very High",L47="Fair"),"High", IF(AND(J47="Very High",L47="Poor"),"Very High", IF(AND(J47="Very High",L47="Unsatisfactory"),"Very High", IF(AND(J47="High",L47="Excellent"),"Very Low", IF(AND(J47="High",L47="Good"),"Low", IF(AND(J47="High",L47="Fair"),"Medium", IF(AND(J47="High",L47="Poor"),"High", IF(AND(J47="High",L47="Unsatisfactory"),"High", IF(AND(J47="Medium",L47="Excellent"),"Very Low", IF(AND(J47="Medium",L47="Good"),"Very Low", IF(AND(J47="Medium",L47="Fair"),"Low", IF(AND(J47="Medium",L47="Poor"),"Medium", IF(AND(J47="Medium",L47="Unsatisfactory"),"Medium", IF(AND(J47="Low",L47="Excellent"),"Very Low", IF(AND(J47="Low",L47="Good"),"Very Low", IF(AND(J47="Low",L47="Fair"),"Very Low", IF(AND(J47="Low",L47="Poor"),"Low", IF(AND(J47="Low",L47="Unsatisfactory"),"Low", IF(AND(J47="Very Low",L47="Excellent"),"Very Low", IF(AND(J47="Very Low",L47="Good"),"Very Low", IF(AND(J47="Very Low",L47="Fair"),"Very Low", IF(AND(J47="Very Low",L47="Poor"),"Very Low", IF(AND(J47="Very Low",L47="Unsatisfactory"),"Very Low","")))))))))))))))))))))))))) -> Low | S47: =IF(OR(L47="",R47=""),"",IF(AND(L47="Very High",R47="Excellent"),"Low",IF(AND(L47="Very High",R47="Good"),"Medium",IF(AND(L47="Very High",R47="Fair"),"High",IF(AND(L47="Very High",R47="Poor"),"Very High",IF(AND(L47="Very High",R47="Unsatisfactory"),"Very High",IF(AND(L47="High",R47="Excellent"),"Low",IF(AND(L47="High",R47="Good"),"Low",IF(AND(L47="High",R47="Fair"),"Medium",IF(AND(L47="High",R47="Poor"),"High",IF(AND(L47="High",R47="Unsatisfactory"),"High",IF(AND(L47="Medium",R47="Excellent"),"Low",IF(AND(L47="Medium",R47="Good"),"Low",IF(AND(L47="Medium",R47="Fair"),"Low",IF(AND(L47="Medium",R47="Poor"),"Medium",IF(AND(L47="Medium",R47="Unsatisfactory"),"Medium",IF(AND(L47="Low",R47="Excellent"),"Very Low",IF(AND(L47="Low",R47="Good"),"Low",IF(AND(L47="Low",R47="Fair"),"Low",IF(AND(L47="Low",R47="Poor"),"Low",IF(AND(L47="Low",R47="Unsatisfactory"),"Low",IF(AND(L47="Very Low",R47="Excellent"),"Very Low",IF(AND(L47="Very Low",R47="Good"),"Very Low",IF(AND(L47="Very Low",R47="Fair"),"Very Low",IF(AND(L47="Very Low",R47="Poor"),"Very Low",IF(AND(L47="Very Low",R47="Unsatisfactory"),"Very Low","Low")))))))))))))))))))))))))) | U47: Completed | V47: Fully Automated
A48: PAY-016 | B48: People | C48: Incomplete Nafath Verification - Manual Onboarding (PAY & Online) | D48: Pay Operations | E48: Merchant may delay or fail to complete the Nafath verification, delaying onboarding or causing compliance issues. | F48: Likely | G48: Major | H48: =IF(F48='Risk Methedology Matrix'!B$26,5,IF(F48='Risk Methedology Matrix'!B$27,4,IF(F48='Risk Methedology Matrix'!B$28,3,IF(F48='Risk Methedology Matrix'!B$29,2,IF(F48='Risk Methedology Matrix'!B$30,1,0))))) -> 4 | I48: =IF(G48='Risk Methedology Matrix'!G$25,5,IF(G48='Risk Methedology Matrix'!F$25,4,IF(G48='Risk Methedology Matrix'!E$25,3,IF(G48='Risk Methedology Matrix'!D$25,2,IF(G48='Risk Methedology Matrix'!C$25,1,0))))) -> 4 | J48: =IF(OR(F48="",G48=""),"",IF(H48*I48>=20,"Very High",IF(AND(H48*I48<20,H48*I48>=11),"High",IF(AND(H48*I48<11,H48*I48>=6),"Medium",IF(AND(H48*I48<6,H48*I48>=3),"Low",IF(AND(H48*I48<3,H48*I48>=1),"Very Low","")))))) -> High | K48: Nafath verification is initiated via a standalone link or Customer Portal popup prompting completion. | L48: Good | M48: =IF(OR(J48="",L48=""),"", IF(AND(J48="Very High",L48="Excellent"),"Low", IF(AND(J48="Very High",L48="Good"),"Medium", IF(AND(J48="Very High",L48="Fair"),"High", IF(AND(J48="Very High",L48="Poor"),"Very High", IF(AND(J48="Very High",L48="Unsatisfactory"),"Very High", IF(AND(J48="High",L48="Excellent"),"Very Low", IF(AND(J48="High",L48="Good"),"Low", IF(AND(J48="High",L48="Fair"),"Medium", IF(AND(J48="High",L48="Poor"),"High", IF(AND(J48="High",L48="Unsatisfactory"),"High", IF(AND(J48="Medium",L48="Excellent"),"Very Low", IF(AND(J48="Medium",L48="Good"),"Very Low", IF(AND(J48="Medium",L48="Fair"),"Low", IF(AND(J48="Medium",L48="Poor"),"Medium", IF(AND(J48="Medium",L48="Unsatisfactory"),"Medium", IF(AND(J48="Low",L48="Excellent"),"Very Low", IF(AND(J48="Low",L48="Good"),"Very Low", IF(AND(J48="Low",L48="Fair"),"Very Low", IF(AND(J48="Low",L48="Poor"),"Low", IF(AND(J48="Low",L48="Unsatisfactory"),"Low", IF(AND(J48="Very Low",L48="Excellent"),"Very Low", IF(AND(J48="Very Low",L48="Good"),"Very Low", IF(AND(J48="Very Low",L48="Fair"),"Very Low", IF(AND(J48="Very Low",L48="Poor"),"Very Low", IF(AND(J48="Very Low",L48="Unsatisfactory"),"Very Low","")))))))))))))))))))))))))) -> Low | S48: =IF(OR(L48="",R48=""),"",IF(AND(L48="Very High",R48="Excellent"),"Low",IF(AND(L48="Very High",R48="Good"),"Medium",IF(AND(L48="Very High",R48="Fair"),"High",IF(AND(L48="Very High",R48="Poor"),"Very High",IF(AND(L48="Very High",R48="Unsatisfactory"),"Very High",IF(AND(L48="High",R48="Excellent"),"Low",IF(AND(L48="High",R48="Good"),"Low",IF(AND(L48="High",R48="Fair"),"Medium",IF(AND(L48="High",R48="Poor"),"High",IF(AND(L48="High",R48="Unsatisfactory"),"High",IF(AND(L48="Medium",R48="Excellent"),"Low",IF(AND(L48="Medium",R48="Good"),"Low",IF(AND(L48="Medium",R48="Fair"),"Low",IF(AND(L48="Medium",R48="Poor"),"Medium",IF(AND(L48="Medium",R48="Unsatisfactory"),"Medium",IF(AND(L48="Low",R48="Excellent"),"Very Low",IF(AND(L48="Low",R48="Good"),"Low",IF(AND(L48="Low",R48="Fair"),"Low",IF(AND(L48="Low",R48="Poor"),"Low",IF(AND(L48="Low",R48="Unsatisfactory"),"Low",IF(AND(L48="Very Low",R48="Excellent"),"Very Low",IF(AND(L48="Very Low",R48="Good"),"Very Low",IF(AND(L48="Very Low",R48="Fair"),"Very Low",IF(AND(L48="Very Low",R48="Poor"),"Very Low",IF(AND(L48="Very Low",R48="Unsatisfactory"),"Very Low","Low")))))))))))))))))))))))))) | U48: Completed | V48: Fully Automated
A49: PAY-017 | B49: Process | C49: Freelancer Identity Misclassification - Manual Onboarding (PAY & Online) | D49: Pay Operations | E49: Freelancer merchants may be treated as corporate merchants, leading to inappropriate CR validations and onboarding errors. | F49: Likely | G49: Minor | H49: =IF(F49='Risk Methedology Matrix'!B$26,5,IF(F49='Risk Methedology Matrix'!B$27,4,IF(F49='Risk Methedology Matrix'!B$28,3,IF(F49='Risk Methedology Matrix'!B$29,2,IF(F49='Risk Methedology Matrix'!B$30,1,0))))) -> 4 | I49: =IF(G49='Risk Methedology Matrix'!G$25,5,IF(G49='Risk Methedology Matrix'!F$25,4,IF(G49='Risk Methedology Matrix'!E$25,3,IF(G49='Risk Methedology Matrix'!D$25,2,IF(G49='Risk Methedology Matrix'!C$25,1,0))))) -> 2 | J49: =IF(OR(F49="",G49=""),"",IF(H49*I49>=20,"Very High",IF(AND(H49*I49<20,H49*I49>=11),"High",IF(AND(H49*I49<11,H49*I49>=6),"Medium",IF(AND(H49*I49<6,H49*I49>=3),"Low",IF(AND(H49*I49<3,H49*I49>=1),"Very Low","")))))) -> Medium | K49: Freelancer licenses are manually verified instead of CR validation. | L49: Fair | M49: =IF(OR(J49="",L49=""),"", IF(AND(J49="Very High",L49="Excellent"),"Low", IF(AND(J49="Very High",L49="Good"),"Medium", IF(AND(J49="Very High",L49="Fair"),"High", IF(AND(J49="Very High",L49="Poor"),"Very High", IF(AND(J49="Very High",L49="Unsatisfactory"),"Very High", IF(AND(J49="High",L49="Excellent"),"Very Low", IF(AND(J49="High",L49="Good"),"Low", IF(AND(J49="High",L49="Fair"),"Medium", IF(AND(J49="High",L49="Poor"),"High", IF(AND(J49="High",L49="Unsatisfactory"),"High", IF(AND(J49="Medium",L49="Excellent"),"Very Low", IF(AND(J49="Medium",L49="Good"),"Very Low", IF(AND(J49="Medium",L49="Fair"),"Low", IF(AND(J49="Medium",L49="Poor"),"Medium", IF(AND(J49="Medium",L49="Unsatisfactory"),"Medium", IF(AND(J49="Low",L49="Excellent"),"Very Low", IF(AND(J49="Low",L49="Good"),"Very Low", IF(AND(J49="Low",L49="Fair"),"Very Low", IF(AND(J49="Low",L49="Poor"),"Low", IF(AND(J49="Low",L49="Unsatisfactory"),"Low", IF(AND(J49="Very Low",L49="Excellent"),"Very Low", IF(AND(J49="Very Low",L49="Good"),"Very Low", IF(AND(J49="Very Low",L49="Fair"),"Very Low", IF(AND(J49="Very Low",L49="Poor"),"Very Low", IF(AND(J49="Very Low",L49="Unsatisfactory"),"Very Low","")))))))))))))))))))))))))) -> Low | S49: =IF(OR(L49="",R49=""),"",IF(AND(L49="Very High",R49="Excellent"),"Low",IF(AND(L49="Very High",R49="Good"),"Medium",IF(AND(L49="Very High",R49="Fair"),"High",IF(AND(L49="Very High",R49="Poor"),"Very High",IF(AND(L49="Very High",R49="Unsatisfactory"),"Very High",IF(AND(L49="High",R49="Excellent"),"Low",IF(AND(L49="High",R49="Good"),"Low",IF(AND(L49="High",R49="Fair"),"Medium",IF(AND(L49="High",R49="Poor"),"High",IF(AND(L49="High",R49="Unsatisfactory"),"High",IF(AND(L49="Medium",R49="Excellent"),"Low",IF(AND(L49="Medium",R49="Good"),"Low",IF(AND(L49="Medium",R49="Fair"),"Low",IF(AND(L49="Medium",R49="Poor"),"Medium",IF(AND(L49="Medium",R49="Unsatisfactory"),"Medium",IF(AND(L49="Low",R49="Excellent"),"Very Low",IF(AND(L49="Low",R49="Good"),"Low",IF(AND(L49="Low",R49="Fair"),"Low",IF(AND(L49="Low",R49="Poor"),"Low",IF(AND(L49="Low",R49="Unsatisfactory"),"Low",IF(AND(L49="Very Low",R49="Excellent"),"Very Low",IF(AND(L49="Very Low",R49="Good"),"Very Low",IF(AND(L49="Very Low",R49="Fair"),"Very Low",IF(AND(L49="Very Low",R49="Poor"),"Very Low",IF(AND(L49="Very Low",R49="Unsatisfactory"),"Very Low","Low")))))))))))))))))))))))))) | U49: In Progress | V49: We need to integrate with Future Work to accomplish this. No Timeline still.
A50: PAY-018 | B50: External Event | C50: Insufficient Due Diligence for Charities - Manual Onboarding (PAY & Online) | D50: Pay Operations | E50: Onboarding charitable trusts without full documentary verification may expose the company to reputational and compliance risks. | F50: Likely | G50: Minor | H50: =IF(F50='Risk Methedology Matrix'!B$26,5,IF(F50='Risk Methedology Matrix'!B$27,4,IF(F50='Risk Methedology Matrix'!B$28,3,IF(F50='Risk Methedology Matrix'!B$29,2,IF(F50='Risk Methedology Matrix'!B$30,1,0))))) -> 4 | I50: =IF(G50='Risk Methedology Matrix'!G$25,5,IF(G50='Risk Methedology Matrix'!F$25,4,IF(G50='Risk Methedology Matrix'!E$25,3,IF(G50='Risk Methedology Matrix'!D$25,2,IF(G50='Risk Methedology Matrix'!C$25,1,0))))) -> 2 | J50: =IF(OR(F50="",G50=""),"",IF(H50*I50>=20,"Very High",IF(AND(H50*I50<20,H50*I50>=11),"High",IF(AND(H50*I50<11,H50*I50>=6),"Medium",IF(AND(H50*I50<6,H50*I50>=3),"Low",IF(AND(H50*I50<3,H50*I50>=1),"Very Low","")))))) -> Medium | K50: Charitable merchants are required to submit additional documents including License, Foundation Regulation, and Ministerial Decree from MHRD. | L50: Fair | M50: =IF(OR(J50="",L50=""),"", IF(AND(J50="Very High",L50="Excellent"),"Low", IF(AND(J50="Very High",L50="Good"),"Medium", IF(AND(J50="Very High",L50="Fair"),"High", IF(AND(J50="Very High",L50="Poor"),"Very High", IF(AND(J50="Very High",L50="Unsatisfactory"),"Very High", IF(AND(J50="High",L50="Excellent"),"Very Low", IF(AND(J50="High",L50="Good"),"Low", IF(AND(J50="High",L50="Fair"),"Medium", IF(AND(J50="High",L50="Poor"),"High", IF(AND(J50="High",L50="Unsatisfactory"),"High", IF(AND(J50="Medium",L50="Excellent"),"Very Low", IF(AND(J50="Medium",L50="Good"),"Very Low", IF(AND(J50="Medium",L50="Fair"),"Low", IF(AND(J50="Medium",L50="Poor"),"Medium", IF(AND(J50="Medium",L50="Unsatisfactory"),"Medium", IF(AND(J50="Low",L50="Excellent"),"Very Low", IF(AND(J50="Low",L50="Good"),"Very Low", IF(AND(J50="Low",L50="Fair"),"Very Low", IF(AND(J50="Low",L50="Poor"),"Low", IF(AND(J50="Low",L50="Unsatisfactory"),"Low", IF(AND(J50="Very Low",L50="Excellent"),"Very Low", IF(AND(J50="Very Low",L50="Good"),"Very Low", IF(AND(J50="Very Low",L50="Fair"),"Very Low", IF(AND(J50="Very Low",L50="Poor"),"Very Low", IF(AND(J50="Very Low",L50="Unsatisfactory"),"Very Low","")))))))))))))))))))))))))) -> Low | S50: =IF(OR(L50="",R50=""),"",IF(AND(L50="Very High",R50="Excellent"),"Low",IF(AND(L50="Very High",R50="Good"),"Medium",IF(AND(L50="Very High",R50="Fair"),"High",IF(AND(L50="Very High",R50="Poor"),"Very High",IF(AND(L50="Very High",R50="Unsatisfactory"),"Very High",IF(AND(L50="High",R50="Excellent"),"Low",IF(AND(L50="High",R50="Good"),"Low",IF(AND(L50="High",R50="Fair"),"Medium",IF(AND(L50="High",R50="Poor"),"High",IF(AND(L50="High",R50="Unsatisfactory"),"High",IF(AND(L50="Medium",R50="Excellent"),"Low",IF(AND(L50="Medium",R50="Good"),"Low",IF(AND(L50="Medium",R50="Fair"),"Low",IF(AND(L50="Medium",R50="Poor"),"Medium",IF(AND(L50="Medium",R50="Unsatisfactory"),"Medium",IF(AND(L50="Low",R50="Excellent"),"Very Low",IF(AND(L50="Low",R50="Good"),"Low",IF(AND(L50="Low",R50="Fair"),"Low",IF(AND(L50="Low",R50="Poor"),"Low",IF(AND(L50="Low",R50="Unsatisfactory"),"Low",IF(AND(L50="Very Low",R50="Excellent"),"Very Low",IF(AND(L50="Very Low",R50="Good"),"Very Low",IF(AND(L50="Very Low",R50="Fair"),"Very Low",IF(AND(L50="Very Low",R50="Poor"),"Very Low",IF(AND(L50="Very Low",R50="Unsatisfactory"),"Very Low","Low")))))))))))))))))))))))))) | U50: Partially Completed | V50: Product team will include this in EKYC process soon.
A51: PAY-019 | B51: System | C51: Lack of System Controls During Exceptions - Manual Onboarding (PAY & Online) | D51: Pay Operations | E51: Manual exception processes bypass system validations, increasing the likelihood of control lapses or fraud. | F51: Likely | G51: Major | H51: =IF(F51='Risk Methedology Matrix'!B$26,5,IF(F51='Risk Methedology Matrix'!B$27,4,IF(F51='Risk Methedology Matrix'!B$28,3,IF(F51='Risk Methedology Matrix'!B$29,2,IF(F51='Risk Methedology Matrix'!B$30,1,0))))) -> 4 | I51: =IF(G51='Risk Methedology Matrix'!G$25,5,IF(G51='Risk Methedology Matrix'!F$25,4,IF(G51='Risk Methedology Matrix'!E$25,3,IF(G51='Risk Methedology Matrix'!D$25,2,IF(G51='Risk Methedology Matrix'!C$25,1,0))))) -> 4 | J51: =IF(OR(F51="",G51=""),"",IF(H51*I51>=20,"Very High",IF(AND(H51*I51<20,H51*I51>=11),"High",IF(AND(H51*I51<11,H51*I51>=6),"Medium",IF(AND(H51*I51<6,H51*I51>=3),"Low",IF(AND(H51*I51<3,H51*I51>=1),"Very Low","")))))) -> High | K51: Manual process is used only exceptionally when technical issues arise; onboarding is still tied to verification and documentation through Signit and other integrated systems. | L51: Good | M51: =IF(OR(J51="",L51=""),"", IF(AND(J51="Very High",L51="Excellent"),"Low", IF(AND(J51="Very High",L51="Good"),"Medium", IF(AND(J51="Very High",L51="Fair"),"High", IF(AND(J51="Very High",L51="Poor"),"Very High", IF(AND(J51="Very High",L51="Unsatisfactory"),"Very High", IF(AND(J51="High",L51="Excellent"),"Very Low", IF(AND(J51="High",L51="Good"),"Low", IF(AND(J51="High",L51="Fair"),"Medium", IF(AND(J51="High",L51="Poor"),"High", IF(AND(J51="High",L51="Unsatisfactory"),"High", IF(AND(J51="Medium",L51="Excellent"),"Very Low", IF(AND(J51="Medium",L51="Good"),"Very Low", IF(AND(J51="Medium",L51="Fair"),"Low", IF(AND(J51="Medium",L51="Poor"),"Medium", IF(AND(J51="Medium",L51="Unsatisfactory"),"Medium", IF(AND(J51="Low",L51="Excellent"),"Very Low", IF(AND(J51="Low",L51="Good"),"Very Low", IF(AND(J51="Low",L51="Fair"),"Very Low", IF(AND(J51="Low",L51="Poor"),"Low", IF(AND(J51="Low",L51="Unsatisfactory"),"Low", IF(AND(J51="Very Low",L51="Excellent"),"Very Low", IF(AND(J51="Very Low",L51="Good"),"Very Low", IF(AND(J51="Very Low",L51="Fair"),"Very Low", IF(AND(J51="Very Low",L51="Poor"),"Very Low", IF(AND(J51="Very Low",L51="Unsatisfactory"),"Very Low","")))))))))))))))))))))))))) -> Low | S51: =IF(OR(L51="",R51=""),"",IF(AND(L51="Very High",R51="Excellent"),"Low",IF(AND(L51="Very High",R51="Good"),"Medium",IF(AND(L51="Very High",R51="Fair"),"High",IF(AND(L51="Very High",R51="Poor"),"Very High",IF(AND(L51="Very High",R51="Unsatisfactory"),"Very High",IF(AND(L51="High",R51="Excellent"),"Low",IF(AND(L51="High",R51="Good"),"Low",IF(AND(L51="High",R51="Fair"),"Medium",IF(AND(L51="High",R51="Poor"),"High",IF(AND(L51="High",R51="Unsatisfactory"),"High",IF(AND(L51="Medium",R51="Excellent"),"Low",IF(AND(L51="Medium",R51="Good"),"Low",IF(AND(L51="Medium",R51="Fair"),"Low",IF(AND(L51="Medium",R51="Poor"),"Medium",IF(AND(L51="Medium",R51="Unsatisfactory"),"Medium",IF(AND(L51="Low",R51="Excellent"),"Very Low",IF(AND(L51="Low",R51="Good"),"Low",IF(AND(L51="Low",R51="Fair"),"Low",IF(AND(L51="Low",R51="Poor"),"Low",IF(AND(L51="Low",R51="Unsatisfactory"),"Low",IF(AND(L51="Very Low",R51="Excellent"),"Very Low",IF(AND(L51="Very Low",R51="Good"),"Very Low",IF(AND(L51="Very Low",R51="Fair"),"Very Low",IF(AND(L51="Very Low",R51="Poor"),"Very Low",IF(AND(L51="Very Low",R51="Unsatisfactory"),"Very Low","Low")))))))))))))))))))))))))) | U51: Completed | V51: Fully Automated
A52: PAY-020 | B52: People | C52: High-Risk Merchant Approval Without AFC Oversight | D52: Pay Operations | E52: Approving high-risk merchants without AFC approval can lead to AML/CFT breaches. | F52: Likely | G52: Major | H52: =IF(F52='Risk Methedology Matrix'!B$26,5,IF(F52='Risk Methedology Matrix'!B$27,4,IF(F52='Risk Methedology Matrix'!B$28,3,IF(F52='Risk Methedology Matrix'!B$29,2,IF(F52='Risk Methedology Matrix'!B$30,1,0))))) -> 4 | I52: =IF(G52='Risk Methedology Matrix'!G$25,5,IF(G52='Risk Methedology Matrix'!F$25,4,IF(G52='Risk Methedology Matrix'!E$25,3,IF(G52='Risk Methedology Matrix'!D$25,2,IF(G52='Risk Methedology Matrix'!C$25,1,0))))) -> 4 | J52: =IF(OR(F52="",G52=""),"",IF(H52*I52>=20,"Very High",IF(AND(H52*I52<20,H52*I52>=11),"High",IF(AND(H52*I52<11,H52*I52>=6),"Medium",IF(AND(H52*I52<6,H52*I52>=3),"Low",IF(AND(H52*I52<3,H52*I52>=1),"Very Low","")))))) -> High | K52: AFC Officer approval is mandatory before proceeding. | L52: Good | M52: =IF(OR(J52="",L52=""),"", IF(AND(J52="Very High",L52="Excellent"),"Low", IF(AND(J52="Very High",L52="Good"),"Medium", IF(AND(J52="Very High",L52="Fair"),"High", IF(AND(J52="Very High",L52="Poor"),"Very High", IF(AND(J52="Very High",L52="Unsatisfactory"),"Very High", IF(AND(J52="High",L52="Excellent"),"Very Low", IF(AND(J52="High",L52="Good"),"Low", IF(AND(J52="High",L52="Fair"),"Medium", IF(AND(J52="High",L52="Poor"),"High", IF(AND(J52="High",L52="Unsatisfactory"),"High", IF(AND(J52="Medium",L52="Excellent"),"Very Low", IF(AND(J52="Medium",L52="Good"),"Very Low", IF(AND(J52="Medium",L52="Fair"),"Low", IF(AND(J52="Medium",L52="Poor"),"Medium", IF(AND(J52="Medium",L52="Unsatisfactory"),"Medium", IF(AND(J52="Low",L52="Excellent"),"Very Low", IF(AND(J52="Low",L52="Good"),"Very Low", IF(AND(J52="Low",L52="Fair"),"Very Low", IF(AND(J52="Low",L52="Poor"),"Low", IF(AND(J52="Low",L52="Unsatisfactory"),"Low", IF(AND(J52="Very Low",L52="Excellent"),"Very Low", IF(AND(J52="Very Low",L52="Good"),"Very Low", IF(AND(J52="Very Low",L52="Fair"),"Very Low", IF(AND(J52="Very Low",L52="Poor"),"Very Low", IF(AND(J52="Very Low",L52="Unsatisfactory"),"Very Low","")))))))))))))))))))))))))) -> Low | S52: =IF(OR(L52="",R52=""),"",IF(AND(L52="Very High",R52="Excellent"),"Low",IF(AND(L52="Very High",R52="Good"),"Medium",IF(AND(L52="Very High",R52="Fair"),"High",IF(AND(L52="Very High",R52="Poor"),"Very High",IF(AND(L52="Very High",R52="Unsatisfactory"),"Very High",IF(AND(L52="High",R52="Excellent"),"Low",IF(AND(L52="High",R52="Good"),"Low",IF(AND(L52="High",R52="Fair"),"Medium",IF(AND(L52="High",R52="Poor"),"High",IF(AND(L52="High",R52="Unsatisfactory"),"High",IF(AND(L52="Medium",R52="Excellent"),"Low",IF(AND(L52="Medium",R52="Good"),"Low",IF(AND(L52="Medium",R52="Fair"),"Low",IF(AND(L52="Medium",R52="Poor"),"Medium",IF(AND(L52="Medium",R52="Unsatisfactory"),"Medium",IF(AND(L52="Low",R52="Excellent"),"Very Low",IF(AND(L52="Low",R52="Good"),"Low",IF(AND(L52="Low",R52="Fair"),"Low",IF(AND(L52="Low",R52="Poor"),"Low",IF(AND(L52="Low",R52="Unsatisfactory"),"Low",IF(AND(L52="Very Low",R52="Excellent"),"Very Low",IF(AND(L52="Very Low",R52="Good"),"Very Low",IF(AND(L52="Very Low",R52="Fair"),"Very Low",IF(AND(L52="Very Low",R52="Poor"),"Very Low",IF(AND(L52="Very Low",R52="Unsatisfactory"),"Very Low","Low"))))))))))))))))))))))))))
A53: PAY-021 | B53: Process | C53: Device Installation Errors | D53: Pay Operations | E53: Errors in device installation at merchant sites may lead to transaction failures or customer dissatisfaction. | F53: Unlikely | G53: Minor | H53: =IF(F53='Risk Methedology Matrix'!B$26,5,IF(F53='Risk Methedology Matrix'!B$27,4,IF(F53='Risk Methedology Matrix'!B$28,3,IF(F53='Risk Methedology Matrix'!B$29,2,IF(F53='Risk Methedology Matrix'!B$30,1,0))))) -> 2 | I53: =IF(G53='Risk Methedology Matrix'!G$25,5,IF(G53='Risk Methedology Matrix'!F$25,4,IF(G53='Risk Methedology Matrix'!E$25,3,IF(G53='Risk Methedology Matrix'!D$25,2,IF(G53='Risk Methedology Matrix'!C$25,1,0))))) -> 2 | J53: =IF(OR(F53="",G53=""),"",IF(H53*I53>=20,"Very High",IF(AND(H53*I53<20,H53*I53>=11),"High",IF(AND(H53*I53<11,H53*I53>=6),"Medium",IF(AND(H53*I53<6,H53*I53>=3),"Low",IF(AND(H53*I53<3,H53*I53>=1),"Very Low","")))))) -> Low | K53: Job Order confirmation and ticket closure in ZUPER upon installation. | L53: Good | M53: =IF(OR(J53="",L53=""),"", IF(AND(J53="Very High",L53="Excellent"),"Low", IF(AND(J53="Very High",L53="Good"),"Medium", IF(AND(J53="Very High",L53="Fair"),"High", IF(AND(J53="Very High",L53="Poor"),"Very High", IF(AND(J53="Very High",L53="Unsatisfactory"),"Very High", IF(AND(J53="High",L53="Excellent"),"Very Low", IF(AND(J53="High",L53="Good"),"Low", IF(AND(J53="High",L53="Fair"),"Medium", IF(AND(J53="High",L53="Poor"),"High", IF(AND(J53="High",L53="Unsatisfactory"),"High", IF(AND(J53="Medium",L53="Excellent"),"Very Low", IF(AND(J53="Medium",L53="Good"),"Very Low", IF(AND(J53="Medium",L53="Fair"),"Low", IF(AND(J53="Medium",L53="Poor"),"Medium", IF(AND(J53="Medium",L53="Unsatisfactory"),"Medium", IF(AND(J53="Low",L53="Excellent"),"Very Low", IF(AND(J53="Low",L53="Good"),"Very Low", IF(AND(J53="Low",L53="Fair"),"Very Low", IF(AND(J53="Low",L53="Poor"),"Low", IF(AND(J53="Low",L53="Unsatisfactory"),"Low", IF(AND(J53="Very Low",L53="Excellent"),"Very Low", IF(AND(J53="Very Low",L53="Good"),"Very Low", IF(AND(J53="Very Low",L53="Fair"),"Very Low", IF(AND(J53="Very Low",L53="Poor"),"Very Low", IF(AND(J53="Very Low",L53="Unsatisfactory"),"Very Low","")))))))))))))))))))))))))) -> Very Low | S53: =IF(OR(L53="",R53=""),"",IF(AND(L53="Very High",R53="Excellent"),"Low",IF(AND(L53="Very High",R53="Good"),"Medium",IF(AND(L53="Very High",R53="Fair"),"High",IF(AND(L53="Very High",R53="Poor"),"Very High",IF(AND(L53="Very High",R53="Unsatisfactory"),"Very High",IF(AND(L53="High",R53="Excellent"),"Low",IF(AND(L53="High",R53="Good"),"Low",IF(AND(L53="High",R53="Fair"),"Medium",IF(AND(L53="High",R53="Poor"),"High",IF(AND(L53="High",R53="Unsatisfactory"),"High",IF(AND(L53="Medium",R53="Excellent"),"Low",IF(AND(L53="Medium",R53="Good"),"Low",IF(AND(L53="Medium",R53="Fair"),"Low",IF(AND(L53="Medium",R53="Poor"),"Medium",IF(AND(L53="Medium",R53="Unsatisfactory"),"Medium",IF(AND(L53="Low",R53="Excellent"),"Very Low",IF(AND(L53="Low",R53="Good"),"Low",IF(AND(L53="Low",R53="Fair"),"Low",IF(AND(L53="Low",R53="Poor"),"Low",IF(AND(L53="Low",R53="Unsatisfactory"),"Low",IF(AND(L53="Very Low",R53="Excellent"),"Very Low",IF(AND(L53="Very Low",R53="Good"),"Very Low",IF(AND(L53="Very Low",R53="Fair"),"Very Low",IF(AND(L53="Very Low",R53="Poor"),"Very Low",IF(AND(L53="Very Low",R53="Unsatisfactory"),"Very Low","Low"))))))))))))))))))))))))))
A54: PAY-022 | B54: people | C54: Unauthorized Change Requests | D54: Pay Operations | E54: Customer change requests (e.g., bank change) processed without proper verification may result in fraud. | F54: Likely | G54: Major | H54: =IF(F54='Risk Methedology Matrix'!B$26,5,IF(F54='Risk Methedology Matrix'!B$27,4,IF(F54='Risk Methedology Matrix'!B$28,3,IF(F54='Risk Methedology Matrix'!B$29,2,IF(F54='Risk Methedology Matrix'!B$30,1,0))))) -> 4 | I54: =IF(G54='Risk Methedology Matrix'!G$25,5,IF(G54='Risk Methedology Matrix'!F$25,4,IF(G54='Risk Methedology Matrix'!E$25,3,IF(G54='Risk Methedology Matrix'!D$25,2,IF(G54='Risk Methedology Matrix'!C$25,1,0))))) -> 4 | J54: =IF(OR(F54="",G54=""),"",IF(H54*I54>=20,"Very High",IF(AND(H54*I54<20,H54*I54>=11),"High",IF(AND(H54*I54<11,H54*I54>=6),"Medium",IF(AND(H54*I54<6,H54*I54>=3),"Low",IF(AND(H54*I54<3,H54*I54>=1),"Very Low","")))))) -> High | K54: Requests only processed through registered official emails , call centres and MMS with validation. | L54: Good | M54: =IF(OR(J54="",L54=""),"", IF(AND(J54="Very High",L54="Excellent"),"Low", IF(AND(J54="Very High",L54="Good"),"Medium", IF(AND(J54="Very High",L54="Fair"),"High", IF(AND(J54="Very High",L54="Poor"),"Very High", IF(AND(J54="Very High",L54="Unsatisfactory"),"Very High", IF(AND(J54="High",L54="Excellent"),"Very Low", IF(AND(J54="High",L54="Good"),"Low", IF(AND(J54="High",L54="Fair"),"Medium", IF(AND(J54="High",L54="Poor"),"High", IF(AND(J54="High",L54="Unsatisfactory"),"High", IF(AND(J54="Medium",L54="Excellent"),"Very Low", IF(AND(J54="Medium",L54="Good"),"Very Low", IF(AND(J54="Medium",L54="Fair"),"Low", IF(AND(J54="Medium",L54="Poor"),"Medium", IF(AND(J54="Medium",L54="Unsatisfactory"),"Medium", IF(AND(J54="Low",L54="Excellent"),"Very Low", IF(AND(J54="Low",L54="Good"),"Very Low", IF(AND(J54="Low",L54="Fair"),"Very Low", IF(AND(J54="Low",L54="Poor"),"Low", IF(AND(J54="Low",L54="Unsatisfactory"),"Low", IF(AND(J54="Very Low",L54="Excellent"),"Very Low", IF(AND(J54="Very Low",L54="Good"),"Very Low", IF(AND(J54="Very Low",L54="Fair"),"Very Low", IF(AND(J54="Very Low",L54="Poor"),"Very Low", IF(AND(J54="Very Low",L54="Unsatisfactory"),"Very Low","")))))))))))))))))))))))))) -> Low | S54: =IF(OR(L54="",R54=""),"",IF(AND(L54="Very High",R54="Excellent"),"Low",IF(AND(L54="Very High",R54="Good"),"Medium",IF(AND(L54="Very High",R54="Fair"),"High",IF(AND(L54="Very High",R54="Poor"),"Very High",IF(AND(L54="Very High",R54="Unsatisfactory"),"Very High",IF(AND(L54="High",R54="Excellent"),"Low",IF(AND(L54="High",R54="Good"),"Low",IF(AND(L54="High",R54="Fair"),"Medium",IF(AND(L54="High",R54="Poor"),"High",IF(AND(L54="High",R54="Unsatisfactory"),"High",IF(AND(L54="Medium",R54="Excellent"),"Low",IF(AND(L54="Medium",R54="Good"),"Low",IF(AND(L54="Medium",R54="Fair"),"Low",IF(AND(L54="Medium",R54="Poor"),"Medium",IF(AND(L54="Medium",R54="Unsatisfactory"),"Medium",IF(AND(L54="Low",R54="Excellent"),"Very Low",IF(AND(L54="Low",R54="Good"),"Low",IF(AND(L54="Low",R54="Fair"),"Low",IF(AND(L54="Low",R54="Poor"),"Low",IF(AND(L54="Low",R54="Unsatisfactory"),"Low",IF(AND(L54="Very Low",R54="Excellent"),"Very Low",IF(AND(L54="Very Low",R54="Good"),"Very Low",IF(AND(L54="Very Low",R54="Fair"),"Very Low",IF(AND(L54="Very Low",R54="Poor"),"Very Low",IF(AND(L54="Very Low",R54="Unsatisfactory"),"Very Low","Low"))))))))))))))))))))))))))
A55: PAY-023 | B55: Process | C55: Delayed Settlement Notification | D55: Pay Operations | E55: Failure to notify merchants about settlements may cause confusion or disputes | F55: Likely | G55: Minor | H55: =IF(F55='Risk Methedology Matrix'!B$26,5,IF(F55='Risk Methedology Matrix'!B$27,4,IF(F55='Risk Methedology Matrix'!B$28,3,IF(F55='Risk Methedology Matrix'!B$29,2,IF(F55='Risk Methedology Matrix'!B$30,1,0))))) -> 4 | I55: =IF(G55='Risk Methedology Matrix'!G$25,5,IF(G55='Risk Methedology Matrix'!F$25,4,IF(G55='Risk Methedology Matrix'!E$25,3,IF(G55='Risk Methedology Matrix'!D$25,2,IF(G55='Risk Methedology Matrix'!C$25,1,0))))) -> 2 | J55: =IF(OR(F55="",G55=""),"",IF(H55*I55>=20,"Very High",IF(AND(H55*I55<20,H55*I55>=11),"High",IF(AND(H55*I55<11,H55*I55>=6),"Medium",IF(AND(H55*I55<6,H55*I55>=3),"Low",IF(AND(H55*I55<3,H55*I55>=1),"Very Low","")))))) -> Medium | K55: Automated email and SMS notifications to registered contacts | L55: Fair | M55: =IF(OR(J55="",L55=""),"", IF(AND(J55="Very High",L55="Excellent"),"Low", IF(AND(J55="Very High",L55="Good"),"Medium", IF(AND(J55="Very High",L55="Fair"),"High", IF(AND(J55="Very High",L55="Poor"),"Very High", IF(AND(J55="Very High",L55="Unsatisfactory"),"Very High", IF(AND(J55="High",L55="Excellent"),"Very Low", IF(AND(J55="High",L55="Good"),"Low", IF(AND(J55="High",L55="Fair"),"Medium", IF(AND(J55="High",L55="Poor"),"High", IF(AND(J55="High",L55="Unsatisfactory"),"High", IF(AND(J55="Medium",L55="Excellent"),"Very Low", IF(AND(J55="Medium",L55="Good"),"Very Low", IF(AND(J55="Medium",L55="Fair"),"Low", IF(AND(J55="Medium",L55="Poor"),"Medium", IF(AND(J55="Medium",L55="Unsatisfactory"),"Medium", IF(AND(J55="Low",L55="Excellent"),"Very Low", IF(AND(J55="Low",L55="Good"),"Very Low", IF(AND(J55="Low",L55="Fair"),"Very Low", IF(AND(J55="Low",L55="Poor"),"Low", IF(AND(J55="Low",L55="Unsatisfactory"),"Low", IF(AND(J55="Very Low",L55="Excellent"),"Very Low", IF(AND(J55="Very Low",L55="Good"),"Very Low", IF(AND(J55="Very Low",L55="Fair"),"Very Low", IF(AND(J55="Very Low",L55="Poor"),"Very Low", IF(AND(J55="Very Low",L55="Unsatisfactory"),"Very Low","")))))))))))))))))))))))))) -> Low | S55: =IF(OR(L55="",R55=""),"",IF(AND(L55="Very High",R55="Excellent"),"Low",IF(AND(L55="Very High",R55="Good"),"Medium",IF(AND(L55="Very High",R55="Fair"),"High",IF(AND(L55="Very High",R55="Poor"),"Very High",IF(AND(L55="Very High",R55="Unsatisfactory"),"Very High",IF(AND(L55="High",R55="Excellent"),"Low",IF(AND(L55="High",R55="Good"),"Low",IF(AND(L55="High",R55="Fair"),"Medium",IF(AND(L55="High",R55="Poor"),"High",IF(AND(L55="High",R55="Unsatisfactory"),"High",IF(AND(L55="Medium",R55="Excellent"),"Low",IF(AND(L55="Medium",R55="Good"),"Low",IF(AND(L55="Medium",R55="Fair"),"Low",IF(AND(L55="Medium",R55="Poor"),"Medium",IF(AND(L55="Medium",R55="Unsatisfactory"),"Medium",IF(AND(L55="Low",R55="Excellent"),"Very Low",IF(AND(L55="Low",R55="Good"),"Low",IF(AND(L55="Low",R55="Fair"),"Low",IF(AND(L55="Low",R55="Poor"),"Low",IF(AND(L55="Low",R55="Unsatisfactory"),"Low",IF(AND(L55="Very Low",R55="Excellent"),"Very Low",IF(AND(L55="Very Low",R55="Good"),"Very Low",IF(AND(L55="Very Low",R55="Fair"),"Very Low",IF(AND(L55="Very Low",R55="Poor"),"Very Low",IF(AND(L55="Very Low",R55="Unsatisfactory"),"Very Low","Low")))))))))))))))))))))))))) | U55: NA | V55: We shouldn't notify our merchants about payments delays. Proactive delay notifications create unnecessary concern and damage trust. Our focus should be on fixing the issue in the background and shielding merchants from operational noise, not surfacing it
A56: PAY-024 | B56: External Event | C56: Settlement Delays Due to Bank Dependency | D56: Pay Operations | E56: Delays in receiving transaction data from banks cause delayed merchant settlements. | F56: Likely | G56: Major | H56: =IF(F56='Risk Methedology Matrix'!B$26,5,IF(F56='Risk Methedology Matrix'!B$27,4,IF(F56='Risk Methedology Matrix'!B$28,3,IF(F56='Risk Methedology Matrix'!B$29,2,IF(F56='Risk Methedology Matrix'!B$30,1,0))))) -> 4 | I56: =IF(G56='Risk Methedology Matrix'!G$25,5,IF(G56='Risk Methedology Matrix'!F$25,4,IF(G56='Risk Methedology Matrix'!E$25,3,IF(G56='Risk Methedology Matrix'!D$25,2,IF(G56='Risk Methedology Matrix'!C$25,1,0))))) -> 4 | J56: =IF(OR(F56="",G56=""),"",IF(H56*I56>=20,"Very High",IF(AND(H56*I56<20,H56*I56>=11),"High",IF(AND(H56*I56<11,H56*I56>=6),"Medium",IF(AND(H56*I56<6,H56*I56>=3),"Low",IF(AND(H56*I56<3,H56*I56>=1),"Very Low","")))))) -> High | K56: Merchants perform POS reconciliation on a daily basis, as per the reconciliation guidelines stipulated by SAMA, to avoid having amounts pending in the system network. Once the data of the transactions and money is received by us from the bank we settle the merchants in the next settlement cycle. The Mada transactions are settled in T+1 days , whereas the CC transactions are settled in T+3 days. | L56: Good | M56: =IF(OR(J56="",L56=""),"", IF(AND(J56="Very High",L56="Excellent"),"Low", IF(AND(J56="Very High",L56="Good"),"Medium", IF(AND(J56="Very High",L56="Fair"),"High", IF(AND(J56="Very High",L56="Poor"),"Very High", IF(AND(J56="Very High",L56="Unsatisfactory"),"Very High", IF(AND(J56="High",L56="Excellent"),"Very Low", IF(AND(J56="High",L56="Good"),"Low", IF(AND(J56="High",L56="Fair"),"Medium", IF(AND(J56="High",L56="Poor"),"High", IF(AND(J56="High",L56="Unsatisfactory"),"High", IF(AND(J56="Medium",L56="Excellent"),"Very Low", IF(AND(J56="Medium",L56="Good"),"Very Low", IF(AND(J56="Medium",L56="Fair"),"Low", IF(AND(J56="Medium",L56="Poor"),"Medium", IF(AND(J56="Medium",L56="Unsatisfactory"),"Medium", IF(AND(J56="Low",L56="Excellent"),"Very Low", IF(AND(J56="Low",L56="Good"),"Very Low", IF(AND(J56="Low",L56="Fair"),"Very Low", IF(AND(J56="Low",L56="Poor"),"Low", IF(AND(J56="Low",L56="Unsatisfactory"),"Low", IF(AND(J56="Very Low",L56="Excellent"),"Very Low", IF(AND(J56="Very Low",L56="Good"),"Very Low", IF(AND(J56="Very Low",L56="Fair"),"Very Low", IF(AND(J56="Very Low",L56="Poor"),"Very Low", IF(AND(J56="Very Low",L56="Unsatisfactory"),"Very Low","")))))))))))))))))))))))))) -> Low | S56: =IF(OR(L56="",R56=""),"",IF(AND(L56="Very High",R56="Excellent"),"Low",IF(AND(L56="Very High",R56="Good"),"Medium",IF(AND(L56="Very High",R56="Fair"),"High",IF(AND(L56="Very High",R56="Poor"),"Very High",IF(AND(L56="Very High",R56="Unsatisfactory"),"Very High",IF(AND(L56="High",R56="Excellent"),"Low",IF(AND(L56="High",R56="Good"),"Low",IF(AND(L56="High",R56="Fair"),"Medium",IF(AND(L56="High",R56="Poor"),"High",IF(AND(L56="High",R56="Unsatisfactory"),"High",IF(AND(L56="Medium",R56="Excellent"),"Low",IF(AND(L56="Medium",R56="Good"),"Low",IF(AND(L56="Medium",R56="Fair"),"Low",IF(AND(L56="Medium",R56="Poor"),"Medium",IF(AND(L56="Medium",R56="Unsatisfactory"),"Medium",IF(AND(L56="Low",R56="Excellent"),"Very Low",IF(AND(L56="Low",R56="Good"),"Low",IF(AND(L56="Low",R56="Fair"),"Low",IF(AND(L56="Low",R56="Poor"),"Low",IF(AND(L56="Low",R56="Unsatisfactory"),"Low",IF(AND(L56="Very Low",R56="Excellent"),"Very Low",IF(AND(L56="Very Low",R56="Good"),"Very Low",IF(AND(L56="Very Low",R56="Fair"),"Very Low",IF(AND(L56="Very Low",R56="Poor"),"Very Low",IF(AND(L56="Very Low",R56="Unsatisfactory"),"Very Low","Low"))))))))))))))))))))))))))
A57: PAY-025 | B57: Process | C57: Inaccurate Fee Disclosure | D57: Pay Operations | E57: Failure to disclose all charges and fees to clients within the SLA may lead to disputes. | F57: Possible | G57: Moderate | H57: =IF(F57='Risk Methedology Matrix'!B$26,5,IF(F57='Risk Methedology Matrix'!B$27,4,IF(F57='Risk Methedology Matrix'!B$28,3,IF(F57='Risk Methedology Matrix'!B$29,2,IF(F57='Risk Methedology Matrix'!B$30,1,0))))) -> 3 | I57: =IF(G57='Risk Methedology Matrix'!G$25,5,IF(G57='Risk Methedology Matrix'!F$25,4,IF(G57='Risk Methedology Matrix'!E$25,3,IF(G57='Risk Methedology Matrix'!D$25,2,IF(G57='Risk Methedology Matrix'!C$25,1,0))))) -> 3 | J57: =IF(OR(F57="",G57=""),"",IF(H57*I57>=20,"Very High",IF(AND(H57*I57<20,H57*I57>=11),"High",IF(AND(H57*I57<11,H57*I57>=6),"Medium",IF(AND(H57*I57<6,H57*I57>=3),"Low",IF(AND(H57*I57<3,H57*I57>=1),"Very Low","")))))) -> Medium | K57: Mandatory disclosure of fees within 3 business days from client request. | L57: Fair | M57: =IF(OR(J57="",L57=""),"", IF(AND(J57="Very High",L57="Excellent"),"Low", IF(AND(J57="Very High",L57="Good"),"Medium", IF(AND(J57="Very High",L57="Fair"),"High", IF(AND(J57="Very High",L57="Poor"),"Very High", IF(AND(J57="Very High",L57="Unsatisfactory"),"Very High", IF(AND(J57="High",L57="Excellent"),"Very Low", IF(AND(J57="High",L57="Good"),"Low", IF(AND(J57="High",L57="Fair"),"Medium", IF(AND(J57="High",L57="Poor"),"High", IF(AND(J57="High",L57="Unsatisfactory"),"High", IF(AND(J57="Medium",L57="Excellent"),"Very Low", IF(AND(J57="Medium",L57="Good"),"Very Low", IF(AND(J57="Medium",L57="Fair"),"Low", IF(AND(J57="Medium",L57="Poor"),"Medium", IF(AND(J57="Medium",L57="Unsatisfactory"),"Medium", IF(AND(J57="Low",L57="Excellent"),"Very Low", IF(AND(J57="Low",L57="Good"),"Very Low", IF(AND(J57="Low",L57="Fair"),"Very Low", IF(AND(J57="Low",L57="Poor"),"Low", IF(AND(J57="Low",L57="Unsatisfactory"),"Low", IF(AND(J57="Very Low",L57="Excellent"),"Very Low", IF(AND(J57="Very Low",L57="Good"),"Very Low", IF(AND(J57="Very Low",L57="Fair"),"Very Low", IF(AND(J57="Very Low",L57="Poor"),"Very Low", IF(AND(J57="Very Low",L57="Unsatisfactory"),"Very Low","")))))))))))))))))))))))))) -> Low | S57: =IF(OR(L57="",R57=""),"",IF(AND(L57="Very High",R57="Excellent"),"Low",IF(AND(L57="Very High",R57="Good"),"Medium",IF(AND(L57="Very High",R57="Fair"),"High",IF(AND(L57="Very High",R57="Poor"),"Very High",IF(AND(L57="Very High",R57="Unsatisfactory"),"Very High",IF(AND(L57="High",R57="Excellent"),"Low",IF(AND(L57="High",R57="Good"),"Low",IF(AND(L57="High",R57="Fair"),"Medium",IF(AND(L57="High",R57="Poor"),"High",IF(AND(L57="High",R57="Unsatisfactory"),"High",IF(AND(L57="Medium",R57="Excellent"),"Low",IF(AND(L57="Medium",R57="Good"),"Low",IF(AND(L57="Medium",R57="Fair"),"Low",IF(AND(L57="Medium",R57="Poor"),"Medium",IF(AND(L57="Medium",R57="Unsatisfactory"),"Medium",IF(AND(L57="Low",R57="Excellent"),"Very Low",IF(AND(L57="Low",R57="Good"),"Low",IF(AND(L57="Low",R57="Fair"),"Low",IF(AND(L57="Low",R57="Poor"),"Low",IF(AND(L57="Low",R57="Unsatisfactory"),"Low",IF(AND(L57="Very Low",R57="Excellent"),"Very Low",IF(AND(L57="Very Low",R57="Good"),"Very Low",IF(AND(L57="Very Low",R57="Fair"),"Very Low",IF(AND(L57="Very Low",R57="Poor"),"Very Low",IF(AND(L57="Very Low",R57="Unsatisfactory"),"Very Low","Low"))))))))))))))))))))))))))
A58: PAY-026 | B58: Sysetm | C58: Terminal Fee Overcharging | D58: Pay Operations | E58: System may incorrectly apply terminal charges to merchants not meeting transaction threshold of 15K in a month | F58: Likely | G58: Major | H58: =IF(F58='Risk Methedology Matrix'!B$26,5,IF(F58='Risk Methedology Matrix'!B$27,4,IF(F58='Risk Methedology Matrix'!B$28,3,IF(F58='Risk Methedology Matrix'!B$29,2,IF(F58='Risk Methedology Matrix'!B$30,1,0))))) -> 4 | I58: =IF(G58='Risk Methedology Matrix'!G$25,5,IF(G58='Risk Methedology Matrix'!F$25,4,IF(G58='Risk Methedology Matrix'!E$25,3,IF(G58='Risk Methedology Matrix'!D$25,2,IF(G58='Risk Methedology Matrix'!C$25,1,0))))) -> 4 | J58: =IF(OR(F58="",G58=""),"",IF(H58*I58>=20,"Very High",IF(AND(H58*I58<20,H58*I58>=11),"High",IF(AND(H58*I58<11,H58*I58>=6),"Medium",IF(AND(H58*I58<6,H58*I58>=3),"Low",IF(AND(H58*I58<3,H58*I58>=1),"Very Low","")))))) -> High | K58: Fees calculated and displayed in MMS and monthly statement. | L58: Good | M58: =IF(OR(J58="",L58=""),"", IF(AND(J58="Very High",L58="Excellent"),"Low", IF(AND(J58="Very High",L58="Good"),"Medium", IF(AND(J58="Very High",L58="Fair"),"High", IF(AND(J58="Very High",L58="Poor"),"Very High", IF(AND(J58="Very High",L58="Unsatisfactory"),"Very High", IF(AND(J58="High",L58="Excellent"),"Very Low", IF(AND(J58="High",L58="Good"),"Low", IF(AND(J58="High",L58="Fair"),"Medium", IF(AND(J58="High",L58="Poor"),"High", IF(AND(J58="High",L58="Unsatisfactory"),"High", IF(AND(J58="Medium",L58="Excellent"),"Very Low", IF(AND(J58="Medium",L58="Good"),"Very Low", IF(AND(J58="Medium",L58="Fair"),"Low", IF(AND(J58="Medium",L58="Poor"),"Medium", IF(AND(J58="Medium",L58="Unsatisfactory"),"Medium", IF(AND(J58="Low",L58="Excellent"),"Very Low", IF(AND(J58="Low",L58="Good"),"Very Low", IF(AND(J58="Low",L58="Fair"),"Very Low", IF(AND(J58="Low",L58="Poor"),"Low", IF(AND(J58="Low",L58="Unsatisfactory"),"Low", IF(AND(J58="Very Low",L58="Excellent"),"Very Low", IF(AND(J58="Very Low",L58="Good"),"Very Low", IF(AND(J58="Very Low",L58="Fair"),"Very Low", IF(AND(J58="Very Low",L58="Poor"),"Very Low", IF(AND(J58="Very Low",L58="Unsatisfactory"),"Very Low","")))))))))))))))))))))))))) -> Low | S58: =IF(OR(L58="",R58=""),"",IF(AND(L58="Very High",R58="Excellent"),"Low",IF(AND(L58="Very High",R58="Good"),"Medium",IF(AND(L58="Very High",R58="Fair"),"High",IF(AND(L58="Very High",R58="Poor"),"Very High",IF(AND(L58="Very High",R58="Unsatisfactory"),"Very High",IF(AND(L58="High",R58="Excellent"),"Low",IF(AND(L58="High",R58="Good"),"Low",IF(AND(L58="High",R58="Fair"),"Medium",IF(AND(L58="High",R58="Poor"),"High",IF(AND(L58="High",R58="Unsatisfactory"),"High",IF(AND(L58="Medium",R58="Excellent"),"Low",IF(AND(L58="Medium",R58="Good"),"Low",IF(AND(L58="Medium",R58="Fair"),"Low",IF(AND(L58="Medium",R58="Poor"),"Medium",IF(AND(L58="Medium",R58="Unsatisfactory"),"Medium",IF(AND(L58="Low",R58="Excellent"),"Very Low",IF(AND(L58="Low",R58="Good"),"Low",IF(AND(L58="Low",R58="Fair"),"Low",IF(AND(L58="Low",R58="Poor"),"Low",IF(AND(L58="Low",R58="Unsatisfactory"),"Low",IF(AND(L58="Very Low",R58="Excellent"),"Very Low",IF(AND(L58="Very Low",R58="Good"),"Very Low",IF(AND(L58="Very Low",R58="Fair"),"Very Low",IF(AND(L58="Very Low",R58="Poor"),"Very Low",IF(AND(L58="Very Low",R58="Unsatisfactory"),"Very Low","Low"))))))))))))))))))))))))))
A59: PAY-027 | B59: Process | C59: Inactive Terminals Not Reported | D59: Pay Operations | E59: Failure to identify and act on inactive terminals may result in unproductive asset usage and billing issues. | F59: Possible | G59: Minor | H59: =IF(F59='Risk Methedology Matrix'!B$26,5,IF(F59='Risk Methedology Matrix'!B$27,4,IF(F59='Risk Methedology Matrix'!B$28,3,IF(F59='Risk Methedology Matrix'!B$29,2,IF(F59='Risk Methedology Matrix'!B$30,1,0))))) -> 3 | I59: =IF(G59='Risk Methedology Matrix'!G$25,5,IF(G59='Risk Methedology Matrix'!F$25,4,IF(G59='Risk Methedology Matrix'!E$25,3,IF(G59='Risk Methedology Matrix'!D$25,2,IF(G59='Risk Methedology Matrix'!C$25,1,0))))) -> 2 | J59: =IF(OR(F59="",G59=""),"",IF(H59*I59>=20,"Very High",IF(AND(H59*I59<20,H59*I59>=11),"High",IF(AND(H59*I59<11,H59*I59>=6),"Medium",IF(AND(H59*I59<6,H59*I59>=3),"Low",IF(AND(H59*I59<3,H59*I59>=1),"Very Low","")))))) -> Medium | K59: COE team collects data and follows up with clients after 3 months of inactivity. | L59: Fair | M59: =IF(OR(J59="",L59=""),"", IF(AND(J59="Very High",L59="Excellent"),"Low", IF(AND(J59="Very High",L59="Good"),"Medium", IF(AND(J59="Very High",L59="Fair"),"High", IF(AND(J59="Very High",L59="Poor"),"Very High", IF(AND(J59="Very High",L59="Unsatisfactory"),"Very High", IF(AND(J59="High",L59="Excellent"),"Very Low", IF(AND(J59="High",L59="Good"),"Low", IF(AND(J59="High",L59="Fair"),"Medium", IF(AND(J59="High",L59="Poor"),"High", IF(AND(J59="High",L59="Unsatisfactory"),"High", IF(AND(J59="Medium",L59="Excellent"),"Very Low", IF(AND(J59="Medium",L59="Good"),"Very Low", IF(AND(J59="Medium",L59="Fair"),"Low", IF(AND(J59="Medium",L59="Poor"),"Medium", IF(AND(J59="Medium",L59="Unsatisfactory"),"Medium", IF(AND(J59="Low",L59="Excellent"),"Very Low", IF(AND(J59="Low",L59="Good"),"Very Low", IF(AND(J59="Low",L59="Fair"),"Very Low", IF(AND(J59="Low",L59="Poor"),"Low", IF(AND(J59="Low",L59="Unsatisfactory"),"Low", IF(AND(J59="Very Low",L59="Excellent"),"Very Low", IF(AND(J59="Very Low",L59="Good"),"Very Low", IF(AND(J59="Very Low",L59="Fair"),"Very Low", IF(AND(J59="Very Low",L59="Poor"),"Very Low", IF(AND(J59="Very Low",L59="Unsatisfactory"),"Very Low","")))))))))))))))))))))))))) -> Low | S59: =IF(OR(L59="",R59=""),"",IF(AND(L59="Very High",R59="Excellent"),"Low",IF(AND(L59="Very High",R59="Good"),"Medium",IF(AND(L59="Very High",R59="Fair"),"High",IF(AND(L59="Very High",R59="Poor"),"Very High",IF(AND(L59="Very High",R59="Unsatisfactory"),"Very High",IF(AND(L59="High",R59="Excellent"),"Low",IF(AND(L59="High",R59="Good"),"Low",IF(AND(L59="High",R59="Fair"),"Medium",IF(AND(L59="High",R59="Poor"),"High",IF(AND(L59="High",R59="Unsatisfactory"),"High",IF(AND(L59="Medium",R59="Excellent"),"Low",IF(AND(L59="Medium",R59="Good"),"Low",IF(AND(L59="Medium",R59="Fair"),"Low",IF(AND(L59="Medium",R59="Poor"),"Medium",IF(AND(L59="Medium",R59="Unsatisfactory"),"Medium",IF(AND(L59="Low",R59="Excellent"),"Very Low",IF(AND(L59="Low",R59="Good"),"Low",IF(AND(L59="Low",R59="Fair"),"Low",IF(AND(L59="Low",R59="Poor"),"Low",IF(AND(L59="Low",R59="Unsatisfactory"),"Low",IF(AND(L59="Very Low",R59="Excellent"),"Very Low",IF(AND(L59="Very Low",R59="Good"),"Very Low",IF(AND(L59="Very Low",R59="Fair"),"Very Low",IF(AND(L59="Very Low",R59="Poor"),"Very Low",IF(AND(L59="Very Low",R59="Unsatisfactory"),"Very Low","Low"))))))))))))))))))))))))))
A60: PAY-028 | B60: Sysetm | C60: Terminal Inventory Discrepancies | D60: Pay Operations | E60: Inaccurate inventory records could result in overbilling or asset mismanagement. | F60: Likely | G60: Major | H60: =IF(F60='Risk Methedology Matrix'!B$26,5,IF(F60='Risk Methedology Matrix'!B$27,4,IF(F60='Risk Methedology Matrix'!B$28,3,IF(F60='Risk Methedology Matrix'!B$29,2,IF(F60='Risk Methedology Matrix'!B$30,1,0))))) -> 4 | I60: =IF(G60='Risk Methedology Matrix'!G$25,5,IF(G60='Risk Methedology Matrix'!F$25,4,IF(G60='Risk Methedology Matrix'!E$25,3,IF(G60='Risk Methedology Matrix'!D$25,2,IF(G60='Risk Methedology Matrix'!C$25,1,0))))) -> 4 | J60: =IF(OR(F60="",G60=""),"",IF(H60*I60>=20,"Very High",IF(AND(H60*I60<20,H60*I60>=11),"High",IF(AND(H60*I60<11,H60*I60>=6),"Medium",IF(AND(H60*I60<6,H60*I60>=3),"Low",IF(AND(H60*I60<3,H60*I60>=1),"Very Low","")))))) -> High | K60: Regular updates in TMS and vendor billing aligned with active terminals. | L60: Good | M60: =IF(OR(J60="",L60=""),"", IF(AND(J60="Very High",L60="Excellent"),"Low", IF(AND(J60="Very High",L60="Good"),"Medium", IF(AND(J60="Very High",L60="Fair"),"High", IF(AND(J60="Very High",L60="Poor"),"Very High", IF(AND(J60="Very High",L60="Unsatisfactory"),"Very High", IF(AND(J60="High",L60="Excellent"),"Very Low", IF(AND(J60="High",L60="Good"),"Low", IF(AND(J60="High",L60="Fair"),"Medium", IF(AND(J60="High",L60="Poor"),"High", IF(AND(J60="High",L60="Unsatisfactory"),"High", IF(AND(J60="Medium",L60="Excellent"),"Very Low", IF(AND(J60="Medium",L60="Good"),"Very Low", IF(AND(J60="Medium",L60="Fair"),"Low", IF(AND(J60="Medium",L60="Poor"),"Medium", IF(AND(J60="Medium",L60="Unsatisfactory"),"Medium", IF(AND(J60="Low",L60="Excellent"),"Very Low", IF(AND(J60="Low",L60="Good"),"Very Low", IF(AND(J60="Low",L60="Fair"),"Very Low", IF(AND(J60="Low",L60="Poor"),"Low", IF(AND(J60="Low",L60="Unsatisfactory"),"Low", IF(AND(J60="Very Low",L60="Excellent"),"Very Low", IF(AND(J60="Very Low",L60="Good"),"Very Low", IF(AND(J60="Very Low",L60="Fair"),"Very Low", IF(AND(J60="Very Low",L60="Poor"),"Very Low", IF(AND(J60="Very Low",L60="Unsatisfactory"),"Very Low","")))))))))))))))))))))))))) -> Low | S60: =IF(OR(L60="",R60=""),"",IF(AND(L60="Very High",R60="Excellent"),"Low",IF(AND(L60="Very High",R60="Good"),"Medium",IF(AND(L60="Very High",R60="Fair"),"High",IF(AND(L60="Very High",R60="Poor"),"Very High",IF(AND(L60="Very High",R60="Unsatisfactory"),"Very High",IF(AND(L60="High",R60="Excellent"),"Low",IF(AND(L60="High",R60="Good"),"Low",IF(AND(L60="High",R60="Fair"),"Medium",IF(AND(L60="High",R60="Poor"),"High",IF(AND(L60="High",R60="Unsatisfactory"),"High",IF(AND(L60="Medium",R60="Excellent"),"Low",IF(AND(L60="Medium",R60="Good"),"Low",IF(AND(L60="Medium",R60="Fair"),"Low",IF(AND(L60="Medium",R60="Poor"),"Medium",IF(AND(L60="Medium",R60="Unsatisfactory"),"Medium",IF(AND(L60="Low",R60="Excellent"),"Very Low",IF(AND(L60="Low",R60="Good"),"Low",IF(AND(L60="Low",R60="Fair"),"Low",IF(AND(L60="Low",R60="Poor"),"Low",IF(AND(L60="Low",R60="Unsatisfactory"),"Low",IF(AND(L60="Very Low",R60="Excellent"),"Very Low",IF(AND(L60="Very Low",R60="Good"),"Very Low",IF(AND(L60="Very Low",R60="Fair"),"Very Low",IF(AND(L60="Very Low",R60="Poor"),"Very Low",IF(AND(L60="Very Low",R60="Unsatisfactory"),"Very Low","Low"))))))))))))))))))))))))))
A61: PAY-029 | B61: People | C61: Unresolved Customer Complaints | D61: Pay Operations | E61: Delayed resolution of complaints may result in reputational loss and regulatory breaches. | F61: Likely | G61: Major | H61: =IF(F61='Risk Methedology Matrix'!B$26,5,IF(F61='Risk Methedology Matrix'!B$27,4,IF(F61='Risk Methedology Matrix'!B$28,3,IF(F61='Risk Methedology Matrix'!B$29,2,IF(F61='Risk Methedology Matrix'!B$30,1,0))))) -> 4 | I61: =IF(G61='Risk Methedology Matrix'!G$25,5,IF(G61='Risk Methedology Matrix'!F$25,4,IF(G61='Risk Methedology Matrix'!E$25,3,IF(G61='Risk Methedology Matrix'!D$25,2,IF(G61='Risk Methedology Matrix'!C$25,1,0))))) -> 4 | J61: =IF(OR(F61="",G61=""),"",IF(H61*I61>=20,"Very High",IF(AND(H61*I61<20,H61*I61>=11),"High",IF(AND(H61*I61<11,H61*I61>=6),"Medium",IF(AND(H61*I61<6,H61*I61>=3),"Low",IF(AND(H61*I61<3,H61*I61>=1),"Very Low","")))))) -> High | K61: SLA-based handling by Pay Ops and product team. | L61: Good | M61: =IF(OR(J61="",L61=""),"", IF(AND(J61="Very High",L61="Excellent"),"Low", IF(AND(J61="Very High",L61="Good"),"Medium", IF(AND(J61="Very High",L61="Fair"),"High", IF(AND(J61="Very High",L61="Poor"),"Very High", IF(AND(J61="Very High",L61="Unsatisfactory"),"Very High", IF(AND(J61="High",L61="Excellent"),"Very Low", IF(AND(J61="High",L61="Good"),"Low", IF(AND(J61="High",L61="Fair"),"Medium", IF(AND(J61="High",L61="Poor"),"High", IF(AND(J61="High",L61="Unsatisfactory"),"High", IF(AND(J61="Medium",L61="Excellent"),"Very Low", IF(AND(J61="Medium",L61="Good"),"Very Low", IF(AND(J61="Medium",L61="Fair"),"Low", IF(AND(J61="Medium",L61="Poor"),"Medium", IF(AND(J61="Medium",L61="Unsatisfactory"),"Medium", IF(AND(J61="Low",L61="Excellent"),"Very Low", IF(AND(J61="Low",L61="Good"),"Very Low", IF(AND(J61="Low",L61="Fair"),"Very Low", IF(AND(J61="Low",L61="Poor"),"Low", IF(AND(J61="Low",L61="Unsatisfactory"),"Low", IF(AND(J61="Very Low",L61="Excellent"),"Very Low", IF(AND(J61="Very Low",L61="Good"),"Very Low", IF(AND(J61="Very Low",L61="Fair"),"Very Low", IF(AND(J61="Very Low",L61="Poor"),"Very Low", IF(AND(J61="Very Low",L61="Unsatisfactory"),"Very Low","")))))))))))))))))))))))))) -> Low | S61: =IF(OR(L61="",R61=""),"",IF(AND(L61="Very High",R61="Excellent"),"Low",IF(AND(L61="Very High",R61="Good"),"Medium",IF(AND(L61="Very High",R61="Fair"),"High",IF(AND(L61="Very High",R61="Poor"),"Very High",IF(AND(L61="Very High",R61="Unsatisfactory"),"Very High",IF(AND(L61="High",R61="Excellent"),"Low",IF(AND(L61="High",R61="Good"),"Low",IF(AND(L61="High",R61="Fair"),"Medium",IF(AND(L61="High",R61="Poor"),"High",IF(AND(L61="High",R61="Unsatisfactory"),"High",IF(AND(L61="Medium",R61="Excellent"),"Low",IF(AND(L61="Medium",R61="Good"),"Low",IF(AND(L61="Medium",R61="Fair"),"Low",IF(AND(L61="Medium",R61="Poor"),"Medium",IF(AND(L61="Medium",R61="Unsatisfactory"),"Medium",IF(AND(L61="Low",R61="Excellent"),"Very Low",IF(AND(L61="Low",R61="Good"),"Low",IF(AND(L61="Low",R61="Fair"),"Low",IF(AND(L61="Low",R61="Poor"),"Low",IF(AND(L61="Low",R61="Unsatisfactory"),"Low",IF(AND(L61="Very Low",R61="Excellent"),"Very Low",IF(AND(L61="Very Low",R61="Good"),"Very Low",IF(AND(L61="Very Low",R61="Fair"),"Very Low",IF(AND(L61="Very Low",R61="Poor"),"Very Low",IF(AND(L61="Very Low",R61="Unsatisfactory"),"Very Low","Low"))))))))))))))))))))))))))
A62: PAY-030 | B62: Process | C62: Improper Contract Cancellation Handling | D62: Pay Operations | E62: Service cancellation without validation may result in legal or operational issues | F62: Likely | G62: Major | H62: =IF(F62='Risk Methedology Matrix'!B$26,5,IF(F62='Risk Methedology Matrix'!B$27,4,IF(F62='Risk Methedology Matrix'!B$28,3,IF(F62='Risk Methedology Matrix'!B$29,2,IF(F62='Risk Methedology Matrix'!B$30,1,0))))) -> 4 | I62: =IF(G62='Risk Methedology Matrix'!G$25,5,IF(G62='Risk Methedology Matrix'!F$25,4,IF(G62='Risk Methedology Matrix'!E$25,3,IF(G62='Risk Methedology Matrix'!D$25,2,IF(G62='Risk Methedology Matrix'!C$25,1,0))))) -> 4 | J62: =IF(OR(F62="",G62=""),"",IF(H62*I62>=20,"Very High",IF(AND(H62*I62<20,H62*I62>=11),"High",IF(AND(H62*I62<11,H62*I62>=6),"Medium",IF(AND(H62*I62<6,H62*I62>=3),"Low",IF(AND(H62*I62<3,H62*I62>=1),"Very Low","")))))) -> High | K62: Cancellation requests must come via official email and be validated before pull-out. | L62: Good | M62: =IF(OR(J62="",L62=""),"", IF(AND(J62="Very High",L62="Excellent"),"Low", IF(AND(J62="Very High",L62="Good"),"Medium", IF(AND(J62="Very High",L62="Fair"),"High", IF(AND(J62="Very High",L62="Poor"),"Very High", IF(AND(J62="Very High",L62="Unsatisfactory"),"Very High", IF(AND(J62="High",L62="Excellent"),"Very Low", IF(AND(J62="High",L62="Good"),"Low", IF(AND(J62="High",L62="Fair"),"Medium", IF(AND(J62="High",L62="Poor"),"High", IF(AND(J62="High",L62="Unsatisfactory"),"High", IF(AND(J62="Medium",L62="Excellent"),"Very Low", IF(AND(J62="Medium",L62="Good"),"Very Low", IF(AND(J62="Medium",L62="Fair"),"Low", IF(AND(J62="Medium",L62="Poor"),"Medium", IF(AND(J62="Medium",L62="Unsatisfactory"),"Medium", IF(AND(J62="Low",L62="Excellent"),"Very Low", IF(AND(J62="Low",L62="Good"),"Very Low", IF(AND(J62="Low",L62="Fair"),"Very Low", IF(AND(J62="Low",L62="Poor"),"Low", IF(AND(J62="Low",L62="Unsatisfactory"),"Low", IF(AND(J62="Very Low",L62="Excellent"),"Very Low", IF(AND(J62="Very Low",L62="Good"),"Very Low", IF(AND(J62="Very Low",L62="Fair"),"Very Low", IF(AND(J62="Very Low",L62="Poor"),"Very Low", IF(AND(J62="Very Low",L62="Unsatisfactory"),"Very Low","")))))))))))))))))))))))))) -> Low | S62: =IF(OR(L62="",R62=""),"",IF(AND(L62="Very High",R62="Excellent"),"Low",IF(AND(L62="Very High",R62="Good"),"Medium",IF(AND(L62="Very High",R62="Fair"),"High",IF(AND(L62="Very High",R62="Poor"),"Very High",IF(AND(L62="Very High",R62="Unsatisfactory"),"Very High",IF(AND(L62="High",R62="Excellent"),"Low",IF(AND(L62="High",R62="Good"),"Low",IF(AND(L62="High",R62="Fair"),"Medium",IF(AND(L62="High",R62="Poor"),"High",IF(AND(L62="High",R62="Unsatisfactory"),"High",IF(AND(L62="Medium",R62="Excellent"),"Low",IF(AND(L62="Medium",R62="Good"),"Low",IF(AND(L62="Medium",R62="Fair"),"Low",IF(AND(L62="Medium",R62="Poor"),"Medium",IF(AND(L62="Medium",R62="Unsatisfactory"),"Medium",IF(AND(L62="Low",R62="Excellent"),"Very Low",IF(AND(L62="Low",R62="Good"),"Low",IF(AND(L62="Low",R62="Fair"),"Low",IF(AND(L62="Low",R62="Poor"),"Low",IF(AND(L62="Low",R62="Unsatisfactory"),"Low",IF(AND(L62="Very Low",R62="Excellent"),"Very Low",IF(AND(L62="Very Low",R62="Good"),"Very Low",IF(AND(L62="Very Low",R62="Fair"),"Very Low",IF(AND(L62="Very Low",R62="Poor"),"Very Low",IF(AND(L62="Very Low",R62="Unsatisfactory"),"Very Low","Low"))))))))))))))))))))))))))
A63: PAY-031 | B63: Process | C63: Document Expiry Without Merchant Notification | D63: Pay Operations | E63: Failure to notify merchants about expired CR or IDs could disrupt settlements. | F63: Possible | G63: Moderate | H63: =IF(F63='Risk Methedology Matrix'!B$26,5,IF(F63='Risk Methedology Matrix'!B$27,4,IF(F63='Risk Methedology Matrix'!B$28,3,IF(F63='Risk Methedology Matrix'!B$29,2,IF(F63='Risk Methedology Matrix'!B$30,1,0))))) -> 3 | I63: =IF(G63='Risk Methedology Matrix'!G$25,5,IF(G63='Risk Methedology Matrix'!F$25,4,IF(G63='Risk Methedology Matrix'!E$25,3,IF(G63='Risk Methedology Matrix'!D$25,2,IF(G63='Risk Methedology Matrix'!C$25,1,0))))) -> 3 | J63: =IF(OR(F63="",G63=""),"",IF(H63*I63>=20,"Very High",IF(AND(H63*I63<20,H63*I63>=11),"High",IF(AND(H63*I63<11,H63*I63>=6),"Medium",IF(AND(H63*I63<6,H63*I63>=3),"Low",IF(AND(H63*I63<3,H63*I63>=1),"Very Low","")))))) -> Medium | K63: 1. If the merchant CR has expired: If the owner is Saudi National, we will notify him 60 days prior to expiry through different channels – Calling, messages, emails. If the merchant fails to respond within 90 days after expiry, we will block his settlements. 2. If the merchant CR has expired: If the owner is Non-Saudi National, we will notify him 60 days prior to expiry through different channels – Calling, messages, emails. If the merchant fails to respond within 180 days after expiry, we will block his settlements. 3. If the merchant National ID is expired: If the owner is Saudi National, we will notify him 60 days prior to expiry through different channels – Calling, messages, emails. If the merchant fails to respond within 60 days after expiry, we will block his settlements. 4.If the merchant National ID is expired: If the owner is Non-Saudi National, we will notify him 60 days prior to expiry through different channels – Call, SMS, emails. If the merchant fails to respond within 90 days after expiry, we will block his settlements. | L63: Fair | M63: =IF(OR(J63="",L63=""),"", IF(AND(J63="Very High",L63="Excellent"),"Low", IF(AND(J63="Very High",L63="Good"),"Medium", IF(AND(J63="Very High",L63="Fair"),"High", IF(AND(J63="Very High",L63="Poor"),"Very High", IF(AND(J63="Very High",L63="Unsatisfactory"),"Very High", IF(AND(J63="High",L63="Excellent"),"Very Low", IF(AND(J63="High",L63="Good"),"Low", IF(AND(J63="High",L63="Fair"),"Medium", IF(AND(J63="High",L63="Poor"),"High", IF(AND(J63="High",L63="Unsatisfactory"),"High", IF(AND(J63="Medium",L63="Excellent"),"Very Low", IF(AND(J63="Medium",L63="Good"),"Very Low", IF(AND(J63="Medium",L63="Fair"),"Low", IF(AND(J63="Medium",L63="Poor"),"Medium", IF(AND(J63="Medium",L63="Unsatisfactory"),"Medium", IF(AND(J63="Low",L63="Excellent"),"Very Low", IF(AND(J63="Low",L63="Good"),"Very Low", IF(AND(J63="Low",L63="Fair"),"Very Low", IF(AND(J63="Low",L63="Poor"),"Low", IF(AND(J63="Low",L63="Unsatisfactory"),"Low", IF(AND(J63="Very Low",L63="Excellent"),"Very Low", IF(AND(J63="Very Low",L63="Good"),"Very Low", IF(AND(J63="Very Low",L63="Fair"),"Very Low", IF(AND(J63="Very Low",L63="Poor"),"Very Low", IF(AND(J63="Very Low",L63="Unsatisfactory"),"Very Low","")))))))))))))))))))))))))) -> Low | S63: =IF(OR(L63="",R63=""),"",IF(AND(L63="Very High",R63="Excellent"),"Low",IF(AND(L63="Very High",R63="Good"),"Medium",IF(AND(L63="Very High",R63="Fair"),"High",IF(AND(L63="Very High",R63="Poor"),"Very High",IF(AND(L63="Very High",R63="Unsatisfactory"),"Very High",IF(AND(L63="High",R63="Excellent"),"Low",IF(AND(L63="High",R63="Good"),"Low",IF(AND(L63="High",R63="Fair"),"Medium",IF(AND(L63="High",R63="Poor"),"High",IF(AND(L63="High",R63="Unsatisfactory"),"High",IF(AND(L63="Medium",R63="Excellent"),"Low",IF(AND(L63="Medium",R63="Good"),"Low",IF(AND(L63="Medium",R63="Fair"),"Low",IF(AND(L63="Medium",R63="Poor"),"Medium",IF(AND(L63="Medium",R63="Unsatisfactory"),"Medium",IF(AND(L63="Low",R63="Excellent"),"Very Low",IF(AND(L63="Low",R63="Good"),"Low",IF(AND(L63="Low",R63="Fair"),"Low",IF(AND(L63="Low",R63="Poor"),"Low",IF(AND(L63="Low",R63="Unsatisfactory"),"Low",IF(AND(L63="Very Low",R63="Excellent"),"Very Low",IF(AND(L63="Very Low",R63="Good"),"Very Low",IF(AND(L63="Very Low",R63="Fair"),"Very Low",IF(AND(L63="Very Low",R63="Poor"),"Very Low",IF(AND(L63="Very Low",R63="Unsatisfactory"),"Very Low","Low"))))))))))))))))))))))))))
